Workbook

Sheet README
A1: NutriQA-ArEn - YouTube source master file
A3: Purpose: one traceable table linking every YouTube QA pair to its video URL, channel and batch, built from the batch outputs, the consolidated QA file and the channel/video lists.
A5: Live counts (formulas over the other sheets)
A6: QA rows in QA_Master | B6: =COUNTA(QA_Master!A:A)-1 -> 2305
A7: confirmed by title match | B7: =COUNTIF(QA_Master!L:L,"Confirmed*") -> 2200
A8: position-inferred (batch 12, videos 79-89) | B8: =COUNTIF(QA_Master!L:L,"Position*") -> 55
A9: unresolved (one of videos 581-591) | B9: =COUNTIF(QA_Master!L:L,"Unresolved*") -> 50
A10: Videos listed (rows in Videos) | B10: =COUNTA(Videos!A:A)-1 -> 675
A11: Videos with QA (batch output or position-inferred) | B11: =COUNTIF(Videos!G:G,"Has QA*") -> 440
A12: Videos with no QA found | B12: =COUNTIF(Videos!G:G,"No QA found") -> 224
A13: Videos listed more than once | B13: =COUNTIF(Videos!J:J,"Y") -> 35
A14: QA rows on videos processed twice | B14: =COUNTIF(QA_Master!N:N,"Y") -> 170
A15: QA rows whose question repeats elsewhere | B15: =COUNTIF(QA_Master!O:O,"Y") -> 53
A16: Exact duplicate pairs (later copies) | B16: =COUNTIF(QA_Master!P:P,"Y") -> 3
A17: Truncated transcripts (>=32,700 chars) | B17: =COUNTIF(Transcripts!F:F,"Y") -> 23
A18: Rows held out in Unassigned_QA | B18: =COUNTA(Unassigned_QA!A:A)-1 -> 58
A20: Sheets
A21: QA_Master - one row per QA pair, sorted by video index. Video_Assignment says how sure the video link is.
A22: Videos - all listed video rows with status, QA count, batches and flags.
A23: Transcripts - one row per video that has a transcript (source text used for generation). Chars and Truncated columns are formulas.
A24: Channel_Summary - per-channel counts (formulas). Unassigned_QA - 58 consolidated rows that could not be placed.
A26: Method and assumptions
A27: 1. Batch rows were joined to the Videos list by exact title (whitespace-normalised); all 423 batch titles matched. Where a title is listed twice, the index was chosen by the batch's video-index range.
A28: 2. Consolidated rows 476-530 (sheet row numbers; positions 475-529) match no batch file. They fit videos 79-89 exactly (11 videos x 5 rows) and their questions follow the titles in order. Assumed to be missing batch 12.
A29: 3. Consolidated rows 1916-1965 (50 rows) match no batch file. They form 10 blocks of 5 rows for 11 candidate videos (581-591, all from Captain Kareem Khaled's channel). Which video lacks a block could not be determined, so no video is assigned.
A30: 4. 58 consolidated rows near videos 23-28 could not be explained (extra, regenerated or misplaced output) and are kept out of QA_Master.
A31: 5. Video IDs are read from the watch?v= URLs. Channel handles and playlist link come from the channel sheet; the channel name is blank for Dr. Hadara in the source.
A32: 6. Processed_Twice = the same title has QA from two batches (10 QA pairs). Repeated_Question = identical question text appears more than once in QA_Master. Exact_Duplicate_Later_Copy = same question and answer as an earlier row.
A33: 7. No rows were deleted; duplicates are flagged only.

Sheet QA_Master
A1: QA_ID | B1: Video_Index | C1: Video_ID | D1: Video_URL | E1: Video_Title | F1: Channel (Dr) | G1: Channel_Name | H1: Channel_URL | I1: Batch | J1: Question | K1: Answer | L1: Video_Assignment | M1: Pair_Source | N1: Processed_Twice | O1: Repeated_Question | P1: Exact_Duplicate_Later_Copy | Q1: Transcript_Truncated | R1: Note
A2: QA-0001 | B2: 1 | C2: BE85vJQel4Q | D2: https://www.youtube.com/watch?v=BE85vJQel4Q | E2: لماذا يتباطأ فقدان الوزن في الشتاء؟ الحقيقة التي لم يُخبِرك بها أحد | F2: د. كريم علي | G2: فِكر تاني | H2: https://www.youtube.com/@fekrtany | I2: 1 | J2: ما هي الأسباب الرئيسية لفشل فقدان الوزن كما تم توضيحه في السياق، وكيف تؤثر هذه الأسباب على الجسم؟ | K2: الأسباب الرئيسية لفشل فقدان الوزن تشمل مقاومة الأنسولين، الالتهاب، التوتر والقلق، ونقص النوم. مقاومة الأنسولين تعني أن الجسم لا يستطيع حرق الدهون حتى لو كان الشخص يأكل قليلاً، حيث أن ارتفاع الأنسولين يمنع حرق الدهون. الالتهاب يجعل الجسم في حالة دفاع مستمرة، مما يؤدي إلى تخزين الدهون بدلاً من حرقها. التوتر والقلق يزيدان من مستويات الكورتيزول، مما يعيق امتصاص العناصر الغذائية ويؤدي إلى تخزين الدهون، خاصة في منطقة البطن. نقص النوم يؤثر على هرمونات الجوع والشبع، مما يزيد من الرغبة في تناول الطعام ليلاً ويؤدي إلى تخزين الدهون بدلاً من حرقها. | L2: Confirmed (title match) | M2: Batch output file | N2: N | O2: N | P2: N | Q2: N
A3: QA-0002 | B3: 1 | C3: BE85vJQel4Q | D3: https://www.youtube.com/watch?v=BE85vJQel4Q | E3: لماذا يتباطأ فقدان الوزن في الشتاء؟ الحقيقة التي لم يُخبِرك بها أحد | F3: د. كريم علي | G3: فِكر تاني | H3: https://www.youtube.com/@fekrtany | I3: 1 | J3: كيف يمكن أن تؤثر عادات الأكل السيئة، مثل تناول الطعام في وقت متأخر من الليل، على عملية فقدان الوزن؟ | K3: تناول الطعام في وقت متأخر من الليل يمكن أن يؤدي إلى تخزين الدهون، حتى لو كانت الأطعمة صحية مثل اللحم المشوي والخضروات. عندما يأكل الشخص في وقت متأخر، فإن الجسم قد يخزن هذه الأطعمة كدهون بدلاً من حرقها، مما يجعل جهود فقدان الوزن غير فعالة. لذلك، من المهم أن يتم تناول الطعام في أوقات مناسبة، مثل تناول الطعام بعد ساعتين من الاستيقاظ والتوقف عن الأكل قبل ثلاث ساعات من النوم. | L3: Confirmed (title match) | M3: Batch output file | N3: N | O3: N | P3: N | Q3: N
A4: QA-0003 | B4: 1 | C4: BE85vJQel4Q | D4: https://www.youtube.com/watch?v=BE85vJQel4Q | E4: لماذا يتباطأ فقدان الوزن في الشتاء؟ الحقيقة التي لم يُخبِرك بها أحد | F4: د. كريم علي | G4: فِكر تاني | H4: https://www.youtube.com/@fekrtany | I4: 1 | J4: ما هي الحلول المقترحة لإدارة الوزن بشكل فعال، وكيف يمكن أن تؤثر هذه الحلول على الجسم؟ | K4: الحلول المقترحة لإدارة الوزن تشمل: 1- ضبط توقيت الوجبات، حيث يجب تناول الطعام بعد ساعتين من الاستيقاظ والتوقف عن الأكل قبل ثلاث ساعات من النوم. 2- تهدئة الجهاز العصبي من خلال الاسترخاء. 3- تحسين جودة النوم، حيث أن النوم الجيد هو المفتاح الرئيسي. 4- تنشيط الميتوكوندريا من خلال تناول الطعام بشكل صحيح والحصول على المعادن والفيتامينات. 5- تجنب صدمة الجسم من خلال عدم اتباع حميات قاسية. هذه الحلول تساعد في جعل الجسم يشعر بالأمان، مما يؤدي إلى تنشيط حرق الدهون وانخفاض الوزن بشكل مستدام. | L4: Confirmed (title match) | M4: Batch output file | N4: N | O4: N | P4: N | Q4: N
A5: QA-0004 | B5: 1 | C5: BE85vJQel4Q | D5: https://www.youtube.com/watch?v=BE85vJQel4Q | E5: لماذا يتباطأ فقدان الوزن في الشتاء؟ الحقيقة التي لم يُخبِرك بها أحد | F5: د. كريم علي | G5: فِكر تاني | H5: https://www.youtube.com/@fekrtany | I5: 1 | J5: كيف يؤثر الكورتيزول على الجسم في سياق فقدان الوزن، وما هي العواقب المحتملة لارتفاع مستوياته؟ | K5: الكورتيزول هو هرمون يفرز في حالات التوتر، وعندما تكون مستوياته مرتفعة بشكل دائم، فإن الجسم يبقى في حالة خطر، مما يؤدي إلى عدم امتصاص العناصر الغذائية بشكل صحيح. هذا يمكن أن يؤدي إلى تكسير العضلات والعظام، وزيادة تخزين الدهون، خاصة في منطقة البطن. الأشخاص الذين يعانون من مستويات عالية من الكورتيزول قد يجدون صعوبة في فقدان الوزن، حتى مع اتباع نظام غذائي وممارسة الرياضة، مما يؤدي إلى استمرار وجود الدهون في الجسم. | L5: Confirmed (title match) | M5: Batch output file | N5: N | O5: N | P5: N | Q5: N
A6: QA-0005 | B6: 1 | C6: BE85vJQel4Q | D6: https://www.youtube.com/watch?v=BE85vJQel4Q | E6: لماذا يتباطأ فقدان الوزن في الشتاء؟ الحقيقة التي لم يُخبِرك بها أحد | F6: د. كريم علي | G6: فِكر تاني | H6: https://www.youtube.com/@fekrtany | I6: 1 | J6: ما هي العلاقة بين النوم وفقدان الوزن، وكيف يمكن أن يؤثر نقص النوم على الهرمونات المتعلقة بالجوع والشبع؟ | K6: النوم الجيد له تأثير كبير على فقدان الوزن، حيث أن نقص النوم يمكن أن يؤدي إلى اختلال في هرمونات الجوع والشبع. عندما يكون النوم سيئاً، فإن الشخص قد يشعر بالجوع أكثر ويكون لديه رغبة قوية في تناول الطعام ليلاً، مما يؤدي إلى زيادة استهلاك السعرات الحرارية وتخزين الدهون. لذلك، تحسين جودة النوم يمكن أن يساعد في تنظيم هذه الهرمونات، مما يسهل عملية فقدان الوزن. | L6: Confirmed (title match) | M6: Batch output file | N6: N | O6: N | P6: N | Q6: N
A7: QA-0006 | B7: 2 | C7: X6oFPkaSVfk | D7: https://www.youtube.com/watch?v=X6oFPkaSVfk | E7: لماذا لا يهدأ جسدك؟ الجهاز العصبي أولًا” | F7: د. كريم علي | G7: فِكر تاني | H7: https://www.youtube.com/@fekrtany | I7: 1 | J7: ما هي العلاقة بين وضع الجهاز العصبي في وضع البقاء وتأثيره على فقدان الوزن والصحة العقلية؟ | K7: وضع الجهاز العصبي في وضع البقاء يؤثر بشكل كبير على فقدان الوزن والصحة العقلية. عندما يكون الجهاز العصبي في وضع البقاء، فإن الجسم يدخل في حالة من التوتر الشديد، مما يمنع فقدان الوزن حتى مع اتباع نظام غذائي صحي وممارسة الرياضة. في هذه الحالة، لا يستطيع الجسم بناء العضلات أو العظام، كما أن المزاج لا يتحسن، حتى مع تناول المكملات أو القيام بأنشطة مريحة. لذلك، من الضروري معالجة وضع الجهاز العصبي لضمان تحسين الصحة العامة. | L7: Confirmed (title match) | M7: Batch output file | N7: N | O7: N | P7: N | Q7: N
A8: QA-0007 | B8: 2 | C8: X6oFPkaSVfk | D8: https://www.youtube.com/watch?v=X6oFPkaSVfk | E8: لماذا لا يهدأ جسدك؟ الجهاز العصبي أولًا” | F8: د. كريم علي | G8: فِكر تاني | H8: https://www.youtube.com/@fekrtany | I8: 1 | J8: كيف يمكن للأفراد الخروج من وضع الخطر وتحقيق السلام الداخلي وفقًا للنص؟ | K8: يمكن للأفراد الخروج من وضع الخطر وتحقيق السلام الداخلي من خلال عدة خطوات. أولاً، يجب عليهم الجلوس مع أنفسهم وتحديد مصادر القلق، مثل الضغوطات في العمل أو العلاقات. ثانياً، يجب عليهم استخدام الورق والقلم لكتابة ما يزعجهم والعمل على إصلاحه أو تغييره. ثالثاً، من المهم حماية النوم والحصول على قسط كافٍ منه، بالإضافة إلى الحفاظ على الكتلة العضلية من خلال ممارسة الرياضة. وأخيرًا، يمكن استخدام مكملات مثل المغنيسيوم والفيتامين D، وكذلك الاسترخاء في حمام دافئ مع زيوت أساسية مثل زيت اللافندر لتحقيق الاسترخاء والهدوء. | L8: Confirmed (title match) | M8: Batch output file | N8: N | O8: N | P8: N | Q8: N
A9: QA-0008 | B9: 2 | C9: X6oFPkaSVfk | D9: https://www.youtube.com/watch?v=X6oFPkaSVfk | E9: لماذا لا يهدأ جسدك؟ الجهاز العصبي أولًا” | F9: د. كريم علي | G9: فِكر تاني | H9: https://www.youtube.com/@fekrtany | I9: 1 | J9: ما هي القواعد الثلاث التي يجب اتباعها في السنة الجديدة لتحسين الصحة العقلية والجسدية؟ | K9: القواعد الثلاث التي يجب اتباعها في السنة الجديدة لتحسين الصحة العقلية والجسدية تشمل: 1. تباطؤ الوتيرة: يجب على الأفراد تقليل سرعتهم في الحياة اليومية والابتعاد عن المحتوى السريع والضغوطات. 2. التركيز على الداخل: يجب على الأفراد العمل على تحقيق السلام الداخلي وعدم محاولة إصلاح العالم الخارجي. 3. الخروج من وضع الخطر: يجب تحديد مصادر القلق والقلق والعمل على معالجتها، سواء من خلال تغيير نمط الحياة أو تحسين العلاقات. | L9: Confirmed (title match) | M9: Batch output file | N9: N | O9: N | P9: N | Q9: N
A10: QA-0009 | B10: 2 | C10: X6oFPkaSVfk | D10: https://www.youtube.com/watch?v=X6oFPkaSVfk | E10: لماذا لا يهدأ جسدك؟ الجهاز العصبي أولًا” | F10: د. كريم علي | G10: فِكر تاني | H10: https://www.youtube.com/@fekrtany | I10: 1 | J10: كيف يؤثر التوتر المستمر على قدرة الجسم على الشفاء والتجدد؟ | K10: التوتر المستمر يؤثر سلبًا على قدرة الجسم على الشفاء والتجدد. عندما يكون الجسم في حالة تهديد، فإنه لا يستطيع الشفاء أو التجدد بشكل فعال. هذا يعني أن الجسم لا يمكنه فقدان الوزن أو تحقيق التوازن الهرموني أو تحسين الصحة العقلية. لذلك، من الضروري معالجة مصادر التوتر والقلق لضمان أن يكون الجهاز العصبي في حالة هدوء، مما يسمح للجسم بالشفاء والتجدد. | L10: Confirmed (title match) | M10: Batch output file | N10: N | O10: N | P10: N | Q10: N
A11: QA-0010 | B11: 2 | C11: X6oFPkaSVfk | D11: https://www.youtube.com/watch?v=X6oFPkaSVfk | E11: لماذا لا يهدأ جسدك؟ الجهاز العصبي أولًا” | F11: د. كريم علي | G11: فِكر تاني | H11: https://www.youtube.com/@fekrtany | I11: 1 | J11: ما هي أهمية النوم الجيد وكيف يمكن تحقيقه وفقًا للنص؟ | K11: النوم الجيد مهم جدًا لأنه يساعد في تهدئة الجهاز العصبي ويعزز الصحة العامة. لتحقيق نوم جيد، يُنصح بالنوم في غرفة مظلمة من الساعة 10 مساءً حتى 4 صباحًا، حيث لا يوجد بديل لهذا. النوم الجيد يساعد في تقليل التوتر والقلق، مما يساهم في تحسين المزاج والصحة العقلية. بالإضافة إلى ذلك، الحفاظ على الكتلة العضلية وممارسة الرياضة يمكن أن يساعد أيضًا في تحسين جودة النوم. | L11: Confirmed (title match) | M11: Batch output file | N11: N | O11: N | P11: N | Q11: N
A12: QA-0011 | B12: 3 | C12: V3SGExIImWM | D12: https://www.youtube.com/watch?v=V3SGExIImWM | E12: د.كريم علي | 5 أسرار لإعادة بناء العظام والتخلص من الهشاشة | F12: د. كريم علي | G12: فِكر تاني | H12: https://www.youtube.com/@fekrtany | I12: 1 | J12: ما هي العوامل التي تؤدي إلى ضعف العظام وكيف يمكن أن تؤثر العادات اليومية على صحة العظام لدى الأشخاص في الأربعينيات والخمسينيات والستينيات والسبعينيات والثمانينيات؟ | K12: تؤدي العوامل مثل الخوف من الحركة، الاعتماد الكلي على الكالسيوم، وعدم ممارسة الرياضة إلى ضعف العظام. الخوف من الحركة يجعل الأشخاص يتجنبون النشاط البدني، مما يؤدي إلى ضعف العظام. الاعتماد على مكملات الكالسيوم، مثل كربونات الكالسيوم، يمكن أن يسبب مشاكل صحية مثل تصلب المفاصل وحصوات الكلى. كما أن عدم ممارسة الرياضة، خاصة في صالة الألعاب الرياضية، يمنع بناء العضلات، مما يؤدي إلى فقدان العظام. لذلك، من المهم تناول نظام غذائي متوازن وممارسة الرياضة بانتظام للحفاظ على صحة العظام. | L12: Confirmed (title match) | M12: Batch output file | N12: N | O12: N | P12: N | Q12: N
A13: QA-0012 | B13: 3 | C13: V3SGExIImWM | D13: https://www.youtube.com/watch?v=V3SGExIImWM | E13: د.كريم علي | 5 أسرار لإعادة بناء العظام والتخلص من الهشاشة | F13: د. كريم علي | G13: فِكر تاني | H13: https://www.youtube.com/@fekrtany | I13: 1 | J13: كيف يؤثر توازن الكالسيوم والمغنيسيوم وفيتامين د على صحة العظام، وما هي الشروط اللازمة لتحقيق هذا التوازن؟ | K13: توازن الكالسيوم والمغنيسيوم وفيتامين د ضروري لصحة العظام. فيتامين د يساعد على امتصاص الكالسيوم في الجسم، ولكن يجب أن يؤخذ مع فيتامين ك2 لضمان بقاء الكالسيوم في العظام والأسنان. المغنيسيوم يلعب دورًا مهمًا في منع ارتفاع مستويات الكالسيوم بشكل مفرط، مما يساعد على تحقيق التوازن المطلوب. إذا تم تناول فيتامين د مع فيتامين ك2 والمغنيسيوم، فإن ذلك يعزز صحة العظام ويقلل من خطر الإصابة بهشاشة العظام. | L13: Confirmed (title match) | M13: Batch output file | N13: N | O13: N | P13: N | Q13: N
... A821: QA-0820 | B821: 266 | C821: XO1T8ERJx20 | D821: https://www.youtube.com/watch?v=XO1T8ERJx20 | E821: كيف تتجنب الإصابة بمرض فقد العضلات | علاج ضمور وفقد العضلات | Sarcopenia | F821: د. حازم طارق | G821: Muscle Clinic | H821: https://www.youtube.com/@muscleclinicpt | I821: 20 | J821: كيف يمكن أن تؤثر العوامل البيئية والاجتماعية على انتشار مرض الساركوبيني بين الأفراد، خاصة في الفئات العمرية المتقدمة؟ | K821: العوامل البيئية والاجتماعية تؤثر بشكل كبير على انتشار مرض الساركوبيني بين الأفراد، خاصة في الفئات العمرية المتقدمة. 1. نمط الحياة: العوامل مثل قلة الحركة بسبب نمط الحياة المكتبي تؤدي إلى زيادة خطر الإصابة بالساركوبيني. 2. التغذية: الوصول إلى غذاء صحي ومتوازن يعتمد على البيئة الاجتماعية والاقتصادية، حيث أن سوء التغذية يمكن أن يؤدي إلى ضعف العضلات. 3. الدعم الاجتماعي: الأفراد الذين لديهم دعم اجتماعي أقل قد يكونون أقل قدرة على ممارسة النشاط البدني أو اتباع نظام غذائي صحي. 4. التعليم والتوعية: مستوى التعليم يؤثر على وعي الأفراد بمخاطر الساركوبيني وأهمية الوقاية والعلاج. هذه العوامل مجتمعة تؤدي إلى زيادة انتشار الساركوبيني بين كبار السن، مما يستدعي الحاجة إلى استراتيجيات وقائية وتوعوية فعالة. | L821: Confirmed (title match) | M821: Batch output file | N821: N | O821: N | P821: N | Q821: N
A822: QA-0821 | B822: 271 | C822: gV-pw2CpnV8 | D822: https://www.youtube.com/watch?v=gV-pw2CpnV8&list=PLxUr7SJD6QG_bkLlouV194NEjAjnEHhgr | E822: ما هي الهرمونات | F822: د. مصطفى هدارة | H822: https://www.youtube.com/@DrHaddara | I822: 21 | J822: كيف تتواصل الخلايا مع بعضها البعض عبر الهرمونات، وما هي الآلية التي تستخدمها لتحقيق ذلك؟ | K822: تتواصل الخلايا مع بعضها البعض عبر الهرمونات من خلال إفراز مواد كيميائية تُصنع داخل الخلايا، حيث تقوم الخلايا التي تنتج الهرمونات بإفرازها في الدم. هذه المواد تحتوي على شفرة أو كود خاص يُقرأ بواسطة الأنسجة الأخرى، مما يسمح لها بتنفيذ الأوامر المحددة. على سبيل المثال، المخ يرسل أوامر إلى الكبد والكلة والمعدة والبنكرياس، ولكن بما أنه لا يوجد عصب مباشر بين هذه الأنسجة، فإنها تتواصل عن طريق إفراز الهرمونات التي تحمل التعليمات اللازمة. | L822: Confirmed (title match) | M822: Batch output file | N822: N | O822: N | P822: N | Q822: N
A823: QA-0822 | B823: 271 | C823: gV-pw2CpnV8 | D823: https://www.youtube.com/watch?v=gV-pw2CpnV8&list=PLxUr7SJD6QG_bkLlouV194NEjAjnEHhgr | E823: ما هي الهرمونات | F823: د. مصطفى هدارة | H823: https://www.youtube.com/@DrHaddara | I823: 21 | J823: ما هي الوظائف المختلفة للهرمونات مثل الإنسولين والجلوكاجون، وكيف تؤثر على مستويات السكر في الدم؟ | K823: الإنسولين والجلوكاجون هما هرمونان يعملان بشكل متضاد للحفاظ على مستويات السكر في الدم. الإنسولين يُفرز عندما تكون مستويات السكر مرتفعة، حيث يقوم بفتح بوابات الخلايا في الكبد والعضلات لتخزين السكر على شكل جلايكوجين، كما يُخزن الدهون في الخلايا الدهنية ويمنع حرقها. بالمقابل، الجلوكاجون يُفرز عندما تنخفض مستويات السكر، حيث يعمل على رفع السكر في الدم من خلال تحفيز الكبد على إطلاق الجلايكوجين. هذا التوازن بين الإنسولين والجلوكاجون يساعد في الحفاظ على مستويات السكر ضمن نطاق صحي. | L823: Confirmed (title match) | M823: Batch output file | N823: N | O823: N | P823: N | Q823: N
A824: QA-0823 | B824: 271 | C824: gV-pw2CpnV8 | D824: https://www.youtube.com/watch?v=gV-pw2CpnV8&list=PLxUr7SJD6QG_bkLlouV194NEjAjnEHhgr | E824: ما هي الهرمونات | F824: د. مصطفى هدارة | H824: https://www.youtube.com/@DrHaddara | I824: 21 | J824: كيف تؤثر الهرمونات على عملية الأيض، وما هي العوامل التي يمكن أن تعطل هذه العملية؟ | K824: تؤثر الهرمونات على عملية الأيض من خلال تنظيم مستويات الطاقة والشعور بالجوع والشبع. على سبيل المثال، هرمون اللبتين يُفرز من الخلايا الدهنية ليخبر المخ بالتوقف عن تناول الطعام عندما تكون الدهون مخزنة بشكل كافٍ، بينما هرمون الجريلين يُفرز من المعدة ليحفز الشعور بالجوع. إذا تم تناول الطعام في أوقات غير مناسبة أو بشكل مفرط، فإن ذلك يمكن أن يؤدي إلى اضطرابات في نظام الأيض، مما يسبب مشاكل مثل السمنة أو الأمراض الأيضية. | L824: Confirmed (title match) | M824: Batch output file | N824: N | O824: N | P824: N | Q824: N
A825: QA-0824 | B825: 271 | C825: gV-pw2CpnV8 | D825: https://www.youtube.com/watch?v=gV-pw2CpnV8&list=PLxUr7SJD6QG_bkLlouV194NEjAjnEHhgr | E825: ما هي الهرمونات | F825: د. مصطفى هدارة | H825: https://www.youtube.com/@DrHaddara | I825: 21 | J825: كيف يمكن أن تؤدي الهرمونات إلى نتائج مختلفة في أنسجة مختلفة، وما هو دور المستقبلات في هذه العملية؟ | K825: يمكن أن تؤدي الهرمونات إلى نتائج مختلفة في أنسجة مختلفة بسبب وجود مستقبلات خاصة في كل نوع من الخلايا. كل هرمون يحمل شفرة معينة تُفسرها الخلايا بناءً على نوع المستقبلات الموجودة فيها. على سبيل المثال، هرمون النمو يمكن أن يُحفز بناء العضلات في مكان، بينما يمكن أن يُحفز حرق الدهون في مكان آخر. هذا الاختلاف في الاستجابة يعتمد على نوع الخلايا والمستقبلات التي تتفاعل مع الهرمون. | L825: Confirmed (title match) | M825: Batch output file | N825: N | O825: N | P825: N | Q825: N
A826: QA-0825 | B826: 271 | C826: gV-pw2CpnV8 | D826: https://www.youtube.com/watch?v=gV-pw2CpnV8&list=PLxUr7SJD6QG_bkLlouV194NEjAjnEHhgr | E826: ما هي الهرمونات | F826: د. مصطفى هدارة | H826: https://www.youtube.com/@DrHaddara | I826: 21 | J826: ما هي العلاقة بين الهرمونات والشعور بالجوع والشبع، وكيف تؤثر هذه العلاقة على سلوك الأكل؟ | K826: العلاقة بين الهرمونات والشعور بالجوع والشبع تتجلى من خلال توازن هرمونات مثل اللبتين والجريلين. اللبتين يُفرز من الخلايا الدهنية ليشير إلى المخ بضرورة التوقف عن الأكل عندما تكون الدهون كافية، بينما الجريلين يُفرز من المعدة ليحفز الشعور بالجوع. عندما يحدث خلل في هذه الهرمونات، مثل تناول الطعام في أوقات غير مناسبة أو بشكل مفرط، يمكن أن يؤدي ذلك إلى اضطرابات في سلوك الأكل، مما يسبب زيادة الوزن أو السمنة. | L826: Confirmed (title match) | M826: Batch output file | N826: N | O826: N | P826: N | Q826: N
A827: QA-0826 | B827: 272 | C827: 1Iv7-G813Cg | D827: https://www.youtube.com/watch?v=1Iv7-G813Cg&list=PLxUr7SJD6QG_bkLlouV194NEjAjnEHhgr&index=2 | E827: الهرمونات و توزيع الدهون | F827: د. مصطفى هدارة | H827: https://www.youtube.com/@DrHaddara | I827: 21 | J827: كيف تؤثر الهرمونات المختلفة على توزيع الدهون في الجسم، وما هي الأنماط المختلفة للسمنة المرتبطة بالهرمونات؟ | K827: الهرمونات تلعب دوراً مهماً في توزيع الدهون في الجسم، حيث توجد هرمونات تبني الدهون وأخرى تحرقها. على سبيل المثال، الإنسولين هو الهرمون الأكثر شهرة في زيادة الوزن، حيث يركز الدهون في منطقة البطن. بينما السمنة الناتجة عن قصور الغدة الدرقية تؤدي إلى توزيع الدهون في الجسم بشكل عام، مما يسبب أعراضاً مثل قلة النشاط والانتفاخات. كما أن زيادة الكورتيزون، الناتجة عن الضغط النفسي المزمن، تؤدي أيضاً إلى تجمع الدهون في مناطق معينة مثل الوجه والرقبة. وبالتالي، تختلف الأنماط المرتبطة بالسمنة حسب نوع الهرمون المعني. | L827: Confirmed (title match) | M827: Batch output file | N827: N | O827: N | P827: N | Q827: N
A828: QA-0827 | B828: 272 | C828: 1Iv7-G813Cg | D828: https://www.youtube.com/watch?v=1Iv7-G813Cg&list=PLxUr7SJD6QG_bkLlouV194NEjAjnEHhgr&index=2 | E828: الهرمونات و توزيع الدهون | F828: د. مصطفى هدارة | H828: https://www.youtube.com/@DrHaddara | I828: 21 | J828: ما هي العلاقة بين مقاومة الإنسولين والنظام الغذائي الكيتوني، وكيف يمكن أن يساعد هذا النظام في معالجة السمنة؟ | K828: مقاومة الإنسولين هي حالة تؤدي إلى تجمع الدهون في منطقة البطن، حيث يحتاج الأشخاص الذين يعانون من هذه الحالة إلى اتباع نظام غذائي كيتوني. النظام الكيتوني يساعد في تقليل مستويات الإنسولين في الجسم، مما يؤدي إلى تحسين مقاومة الإنسولين وبالتالي تقليل الدهون المتراكمة في البطن. الأبحاث تشير إلى أن النظام الكيتوني فعال في معالجة هذه المشكلة، حيث يساهم في تحويل الجسم إلى حالة حرق الدهون بدلاً من تخزينها. | L828: Confirmed (title match) | M828: Batch output file | N828: N | O828: N | P828: N | Q828: N
A829: QA-0828 | B829: 272 | C829: 1Iv7-G813Cg | D829: https://www.youtube.com/watch?v=1Iv7-G813Cg&list=PLxUr7SJD6QG_bkLlouV194NEjAjnEHhgr&index=2 | E829: الهرمونات و توزيع الدهون | F829: د. مصطفى هدارة | H829: https://www.youtube.com/@DrHaddara | I829: 21 | J829: كيف يمكن أن تؤثر العوامل الوراثية والتغذية على مستويات الاستروجين في الرجال، وما هي النتائج المحتملة لذلك؟ | K829: مستويات الاستروجين في الرجال يمكن أن تتأثر بالعوامل الوراثية والتغذية. بعض الأطعمة تحتوي على مواد شبيهة بالاستروجين، مما قد يؤدي إلى زيادة مستويات هذا الهرمون في الجسم. عندما يحدث هذا، يمكن أن يتجمع الدهون في مناطق معينة مثل الحوض والفخذين، مما يعطي مظهراً غير مرغوب فيه. لذلك، يُنصح الرجال الذين يعانون من تجمع الدهون في هذه المناطق بتجنب الأطعمة التي تحتوي على استروجين زائد. | L829: Confirmed (title match) | M829: Batch output file | N829: N | O829: N | P829: N | Q829: N
A830: QA-0829 | B830: 272 | C830: 1Iv7-G813Cg | D830: https://www.youtube.com/watch?v=1Iv7-G813Cg&list=PLxUr7SJD6QG_bkLlouV194NEjAjnEHhgr&index=2 | E830: الهرمونات و توزيع الدهون | F830: د. مصطفى هدارة | H830: https://www.youtube.com/@DrHaddara | I830: 21 | J830: ما هي الفروقات بين أنواع السمنة المختلفة وكيف يمكن أن تؤثر على اختيار النظام الغذائي المناسب لكل فرد؟ | K830: تختلف أنواع السمنة بناءً على الهرمونات المعنية، مثل سمنة الإنسولين وسمنة الغدة الدرقية وسمنة الكورتيزون. كل نوع من هذه الأنواع يتطلب نهجاً مختلفاً في النظام الغذائي. على سبيل المثال، الأشخاص الذين يعانون من سمنة الإنسولين قد يستفيدون من النظام الكيتوني، بينما الأشخاص الذين يعانون من قصور الغدة الدرقية قد يحتاجون إلى استراتيجيات مختلفة. لذا، من المهم أن نفهم أن النظام الغذائي الذي يناسب شخصاً ما قد لا يناسب شخصاً آخر، ويجب أن يتم تخصيصه بناءً على نوع السمنة والهرمونات المعنية. | L830: Confirmed (title match) | M830: Batch output file | N830: N | O830: N | P830: N | Q830: N
A831: QA-0830 | B831: 272 | C831: 1Iv7-G813Cg | D831: https://www.youtube.com/watch?v=1Iv7-G813Cg&list=PLxUr7SJD6QG_bkLlouV194NEjAjnEHhgr&index=2 | E831: الهرمونات و توزيع الدهون | F831: د. مصطفى هدارة | H831: https://www.youtube.com/@DrHaddara | I831: 21 | J831: كيف يؤثر الضغط النفسي المزمن على مستويات الكورتيزون وتوزيع الدهون في الجسم؟ | K831: الضغط النفسي المزمن يؤدي إلى زيادة مستويات الكورتيزون في الجسم، وهو هرمون مهم للحياة السليمة. عندما تزداد مستويات الكورتيزون، يمكن أن تتجمع الدهون في مناطق معينة مثل الوجه والرقبة، مما يؤدي إلى مظهر غير صحي. كما أن النوم السيء يمكن أن يزيد من مستويات الكورتيزون، مما يزيد من تأثير الضغط النفسي على توزيع الدهون. لذلك، من المهم إدارة الضغط النفسي والنوم الجيد للحفاظ على مستويات الكورتيزون ضمن الحدود الطبيعية. | L831: Confirmed (title match) | M831: Batch output file | N831: N | O831: N | P831: N | Q831: N
A832: QA-0831 | B832: 273 | C832: el2d6IIpQ3E | D832: https://www.youtube.com/watch?v=el2d6IIpQ3E&list=PLxUr7SJD6QG_bkLlouV194NEjAjnEHhgr&index=3 | E832: متي نستخدم الاعشاب | F832: د. مصطفى هدارة | H832: https://www.youtube.com/@DrHaddara | I832: 22 | J832: ما هي العلاقة بين التغذية السليمة وظهور الأمراض المزمنة مثل السكر والضغط؟ | K832: التغذية السليمة تلعب دوراً حاسماً في الوقاية من الأمراض المزمنة مثل السكر والضغط. حيث أن 80% من هذه الأمراض لها أسباب غذائية عميقة، تتعلق بتناول أطعمة ضارة بكميات كبيرة ومتكررة، في حين يتم حرمان الجسم من الأطعمة المفيدة الغنية بالعناصر الغذائية. إذا استمر الشخص في تناول الأطعمة الضارة لفترة طويلة، فإن ذلك قد يؤدي إلى ظهور الأمراض. لذا، من الضروري أن يتم التركيز على تحسين التغذية أولاً قبل التفكير في استخدام الأعشاب أو العلاجات الأخرى. | L832: Confirmed (title match) | M832: Batch output file | N832: N | O832: N | P832: N | Q832: N
A833: QA-0832 | B833: 273 | C833: el2d6IIpQ3E | D833: https://www.youtube.com/watch?v=el2d6IIpQ3E&list=PLxUr7SJD6QG_bkLlouV194NEjAjnEHhgr&index=3 | E833: متي نستخدم الاعشاب | F833: د. مصطفى هدارة | H833: https://www.youtube.com/@DrHaddara | I833: 22 | J833: كيف يمكن أن يؤثر تناول الأطعمة الضارة على الجسم مقارنة بتناول الأطعمة المفيدة؟ | K833: تناول الأطعمة الضارة يؤثر سلباً على الجسم من خلال زيادة احتمالية الإصابة بالأمراض المزمنة، حيث أن هذه الأطعمة تفتقر إلى العناصر الغذائية الضرورية وتسبب تراكم السموم في الجسم. بالمقابل، تناول الأطعمة المفيدة يساعد في تعزيز الصحة العامة، حيث تحتوي على الفيتامينات والمعادن التي تدعم وظائف الجسم وتساعد في الوقاية من الأمراض. لذلك، يجب على الأفراد الامتناع عن الأطعمة الضارة والتركيز على الأطعمة الصحية لتحقيق توازن غذائي. | L833: Confirmed (title match) | M833: Batch output file | N833: N | O833: N | P833: N | Q833: N
... A896: QA-0895 | B896: 303 | C896: 8GOXy6VrIJM | D896: https://www.youtube.com/watch?v=8GOXy6VrIJM | E896: التخلص من شحوم الجسم، حرق الدهون الجزء الثاني | F896: د. مصطفى هدارة | H896: https://www.youtube.com/@DrHaddara | I896: 23 | J896: ما هي الهرمونات الرئيسية التي تؤثر على حرق الدهون، وكيف يمكن أن تؤثر مستوياتها على نجاح النظام الغذائي؟ | K896: الهرمونات الرئيسية التي تؤثر على حرق الدهون تشمل الأنسولين والثيروكسين. الأنسولين يلعب دورًا في تنظيم مستويات السكر في الدم، وعندما تكون هناك مقاومة للأنسولين، يصبح من الصعب حرق الدهون. الثيروكسين، وهو هرمون الغدة الدرقية، مهم أيضًا لحرق الدهون، ونقصه يمكن أن يعيق هذه العملية. لضمان نجاح النظام الغذائي، يجب ضبط مستويات هذه الهرمونات من خلال التغذية السليمة والنشاط البدني. | L896: Confirmed (title match) | M896: Batch output file | N896: N | O896: N | P896: N | Q896: N
A897: QA-0896 | B897: 304 | C897: -g960XrPEZM | D897: https://www.youtube.com/watch?v=-g960XrPEZM&list=PL90W1ZUHSNiQiI1BVLP5GuIXxf6hr9Rln&index=1 | E897: اساسيات التغذية | F897: د. محمود ثابت | G897: دايت بدون حرمان | H897: https://youtube.com/playlist?list=PL90W1ZUHSNiQiI1BVLP5GuIXxf6hr9Rln&si=G_UimDsDy12ttC7G | I897: 23 | J897: ما هي المبادئ الأساسية التي تقوم عليها التغذية العلاجية وكيف تؤثر على صحة الفرد؟ | K897: التغذية العلاجية تعتمد على عدة مبادئ أساسية تشمل توفير نظام غذائي متوازن يحتوي على جميع العناصر الغذائية الضرورية مثل الكربوهيدرات، البروتينات، الدهون، الفيتامينات، والمعادن. هذه العناصر يجب أن تكون متوفرة بكميات مثالية، حيث أن التغذية السليمة تساهم في تحسين الصحة العامة، وتعزيز المناعة، والوقاية من الأمراض المزمنة مثل السكري وارتفاع ضغط الدم. كما أن التغذية العلاجية تستخدم كوسيلة علاجية لتخفيف أعراض الأمراض، مثل تنظيم مستوى السكر في الدم لمرضى السكري، مما يقلل من المضاعفات الصحية المرتبطة بالمرض. | L897: Confirmed (title match) | M897: Batch output file | N897: N | O897: N | P897: N | Q897: Y
A898: QA-0897 | B898: 304 | C898: -g960XrPEZM | D898: https://www.youtube.com/watch?v=-g960XrPEZM&list=PL90W1ZUHSNiQiI1BVLP5GuIXxf6hr9Rln&index=1 | E898: اساسيات التغذية | F898: د. محمود ثابت | G898: دايت بدون حرمان | H898: https://youtube.com/playlist?list=PL90W1ZUHSNiQiI1BVLP5GuIXxf6hr9Rln&si=G_UimDsDy12ttC7G | I898: 23 | J898: كيف يتم حساب السعرات الحرارية المطلوبة للجسم وما هي العوامل المؤثرة في ذلك؟ | K898: حساب السعرات الحرارية المطلوبة للجسم يعتمد على معادلات معينة مثل معادلة هاريس بنديكت، التي تأخذ في الاعتبار عدة عوامل مثل الجنس، الوزن، الطول، والعمر. يتم حساب إجمالي إنفاق الطاقة من خلال ثلاثة مكونات رئيسية: استهلاك الطاقة أثناء الراحة، الطاقة المطلوبة لهضم الطعام، والطاقة الناتجة عن النشاط البدني. كلما زادت مستويات النشاط البدني، زادت الحاجة للسعرات الحرارية. كما أن العوامل البيئية مثل درجة الحرارة تؤثر أيضًا على معدل الأيض الأساسي. | L898: Confirmed (title match) | M898: Batch output file | N898: N | O898: N | P898: N | Q898: Y
A899: QA-0898 | B899: 304 | C899: -g960XrPEZM | D899: https://www.youtube.com/watch?v=-g960XrPEZM&list=PL90W1ZUHSNiQiI1BVLP5GuIXxf6hr9Rln&index=1 | E899: اساسيات التغذية | F899: د. محمود ثابت | G899: دايت بدون حرمان | H899: https://youtube.com/playlist?list=PL90W1ZUHSNiQiI1BVLP5GuIXxf6hr9Rln&si=G_UimDsDy12ttC7G | I899: 23 | J899: ما الفرق بين التغذية السليمة وسوء التغذية، وما هي العواقب المحتملة لكل منهما؟ | K899: التغذية السليمة تعني تناول نظام غذائي متوازن يحتوي على جميع العناصر الغذائية بكميات مناسبة، مما يساهم في الحفاظ على الصحة العامة والوقاية من الأمراض. أما سوء التغذية فيحدث عندما يكون النظام الغذائي غير متوازن أو غير كافٍ، مما يؤدي إلى مشاكل صحية مثل النحافة أو السمنة، وأيضًا أمراض مثل الأنيميا. العواقب المحتملة لسوء التغذية تشمل ضعف المناعة، زيادة خطر الإصابة بالأمراض المزمنة، وتأثيرات سلبية على النمو والتطور، خاصة عند الأطفال. | L899: Confirmed (title match) | M899: Batch output file | N899: N | O899: N | P899: N | Q899: Y
A900: QA-0899 | B900: 304 | C900: -g960XrPEZM | D900: https://www.youtube.com/watch?v=-g960XrPEZM&list=PL90W1ZUHSNiQiI1BVLP5GuIXxf6hr9Rln&index=1 | E900: اساسيات التغذية | F900: د. محمود ثابت | G900: دايت بدون حرمان | H900: https://youtube.com/playlist?list=PL90W1ZUHSNiQiI1BVLP5GuIXxf6hr9Rln&si=G_UimDsDy12ttC7G | I900: 23 | J900: كيف تؤثر الكربوهيدرات على مستوى السكر في الدم وما هي الأنواع المختلفة منها؟ | K900: الكربوهيدرات تلعب دورًا حيويًا في تنظيم مستوى السكر في الدم، حيث تتحلل إلى جلوكوز الذي يستخدم كمصدر للطاقة. هناك نوعان رئيسيان من الكربوهيدرات: الكربوهيدرات البسيطة، التي تتحلل بسرعة وتؤدي إلى ارتفاع سريع في مستوى السكر في الدم، والكربوهيدرات المعقدة، التي تتحلل ببطء وتساعد في الحفاظ على مستوى السكر ثابتًا. من المهم اختيار الكربوهيدرات ذات المؤشر الجلايسيمي المنخفض، مثل الحبوب الكاملة والخضروات، لتجنب الارتفاعات المفاجئة في مستوى السكر. | L900: Confirmed (title match) | M900: Batch output file | N900: N | O900: N | P900: N | Q900: Y
A901: QA-0900 | B901: 304 | C901: -g960XrPEZM | D901: https://www.youtube.com/watch?v=-g960XrPEZM&list=PL90W1ZUHSNiQiI1BVLP5GuIXxf6hr9Rln&index=1 | E901: اساسيات التغذية | F901: د. محمود ثابت | G901: دايت بدون حرمان | H901: https://youtube.com/playlist?list=PL90W1ZUHSNiQiI1BVLP5GuIXxf6hr9Rln&si=G_UimDsDy12ttC7G | I901: 23 | J901: ما هي أهمية الفيتامينات والمعادن في النظام الغذائي وكيف تؤثر على العمليات الحيوية في الجسم؟ | K901: الفيتامينات والمعادن تلعب دورًا أساسيًا في تنظيم العمليات الحيوية في الجسم، حيث تعمل كعوامل مساعدة للإنزيمات وتساهم في العديد من الوظائف الحيوية مثل النمو، التمثيل الغذائي، وصحة الجهاز المناعي. على سبيل المثال، فيتامين د ضروري لصحة العظام، بينما فيتامين سي يعزز المناعة. نقص الفيتامينات والمعادن يمكن أن يؤدي إلى مشاكل صحية خطيرة مثل فقر الدم، ضعف العظام، واضطرابات في الجهاز العصبي. لذلك، من الضروري تناول كميات كافية من هذه العناصر الغذائية لضمان صحة جيدة. | L901: Confirmed (title match) | M901: Batch output file | N901: N | O901: N | P901: N | Q901: Y
A902: QA-0901 | B902: 305 | C902: sIPfEqyxMB8 | D902: https://www.youtube.com/watch?v=sIPfEqyxMB8&list=PL90W1ZUHSNiQiI1BVLP5GuIXxf6hr9Rln&index=2 | E902: التخطيط الغذائي | F902: د. محمود ثابت | G902: دايت بدون حرمان | H902: https://youtube.com/playlist?list=PL90W1ZUHSNiQiI1BVLP5GuIXxf6hr9Rln&si=G_UimDsDy12ttC7G | I902: 23 | J902: ما هي العناصر الأساسية التي يجب أن يتضمنها النظام الغذائي السليم وكيف تؤثر كل منها على الصحة العامة؟ | K902: النظام الغذائي السليم يجب أن يتضمن العناصر الغذائية الرئيسية مثل الكربوهيدرات، البروتينات، والدهون، بالإضافة إلى العناصر الغذائية الفرعية مثل الفيتامينات والمعادن. الكربوهيدرات تمثل 55% من النظام الغذائي، وتوفر الطاقة اللازمة للجسم. البروتينات تمثل 15-25% وتساعد في بناء الأنسجة وإصلاحها. الدهون يجب أن تكون 25-30% من النظام الغذائي، مع التركيز على الدهون غير المشبعة. الماء أيضًا عنصر أساسي، حيث يجب تناوله بكميات كافية للحفاظ على الترطيب. اتباع نظام غذائي متوازن يساعد في الوقاية من أمراض سوء التغذية وأمراض مزمنة مثل السكري وأمراض القلب. | L902: Confirmed (title match) | M902: Batch output file | N902: N | O902: N | P902: N | Q902: Y
A903: QA-0902 | B903: 305 | C903: sIPfEqyxMB8 | D903: https://www.youtube.com/watch?v=sIPfEqyxMB8&list=PL90W1ZUHSNiQiI1BVLP5GuIXxf6hr9Rln&index=2 | E903: التخطيط الغذائي | F903: د. محمود ثابت | G903: دايت بدون حرمان | H903: https://youtube.com/playlist?list=PL90W1ZUHSNiQiI1BVLP5GuIXxf6hr9Rln&si=G_UimDsDy12ttC7G | I903: 23 | J903: كيف يمكن أن يؤثر عدم التوازن في النظام الغذائي على صحة الأفراد، وما هي الأشكال المختلفة لسوء التغذية؟ | K903: عدم التوازن في النظام الغذائي يمكن أن يؤدي إلى عدة أشكال من سوء التغذية، مثل الهزال، التقزم، ونقص الوزن. الهزال هو انخفاض الوزن بالنسبة للطول، بينما التقزم هو قصر القامة بالنسبة للعمر. نقص الوزن يشير إلى انخفاض الوزن بالنسبة للعمر. بالإضافة إلى ذلك، يمكن أن يؤدي نقص المغذيات الدقيقة مثل الفيتامينات والمعادن إلى مشاكل صحية مثل الأنيميا وعوز اليود. من جهة أخرى، الإفراط في تناول السعرات الحرارية يمكن أن يؤدي إلى السمنة، مما يزيد من خطر الإصابة بأمراض مزمنة مثل السكري وأمراض القلب. | L903: Confirmed (title match) | M903: Batch output file | N903: N | O903: N | P903: N | Q903: Y
A904: QA-0903 | B904: 305 | C904: sIPfEqyxMB8 | D904: https://www.youtube.com/watch?v=sIPfEqyxMB8&list=PL90W1ZUHSNiQiI1BVLP5GuIXxf6hr9Rln&index=2 | E904: التخطيط الغذائي | F904: د. محمود ثابت | G904: دايت بدون حرمان | H904: https://youtube.com/playlist?list=PL90W1ZUHSNiQiI1BVLP5GuIXxf6hr9Rln&si=G_UimDsDy12ttC7G | I904: 23 | J904: ما هي التوصيات الغذائية التي وضعتها منظمة الصحة العالمية فيما يتعلق بالسعرات الحرارية ونسب الدهون والسكر في النظام الغذائي؟ | K904: منظمة الصحة العالمية توصي بأن تكون السعرات الحرارية متوازنة ومناسبة للجسم، حيث يجب أن تتناسب مع احتياجات الطاقة. نسبة الدهون في النظام الغذائي يجب ألا تتجاوز 30% من إجمالي السعرات الحرارية، مع تحديد الدهون المشبعة بألا تتجاوز 10%. كما يجب تقليل الدهون المتحولة إلى أقل من 1% من إجمالي السعرات. بالنسبة للسكريات، يجب أن تكون أقل من 10%، ويفضل أن تكون في حدود 5%. الملح أيضًا يجب أن يكون محدودًا لأقل من 5 جرام يوميًا، أي ما يعادل 2 جرام من الصوديوم. | L904: Confirmed (title match) | M904: Batch output file | N904: N | O904: N | P904: N | Q904: Y
A905: QA-0904 | B905: 305 | C905: sIPfEqyxMB8 | D905: https://www.youtube.com/watch?v=sIPfEqyxMB8&list=PL90W1ZUHSNiQiI1BVLP5GuIXxf6hr9Rln&index=2 | E905: التخطيط الغذائي | F905: د. محمود ثابت | G905: دايت بدون حرمان | H905: https://youtube.com/playlist?list=PL90W1ZUHSNiQiI1BVLP5GuIXxf6hr9Rln&si=G_UimDsDy12ttC7G | I905: 23 | J905: كيف يمكن تصميم نظام غذائي متوازن يتناسب مع احتياجات الفرد، وما هي الخطوات الأساسية لتحقيق ذلك؟ | K905: لتصميم نظام غذائي متوازن، يجب أولاً حساب السعرات الحرارية المطلوبة بناءً على العمر، الوزن، الطول، والنشاط البدني. بعد ذلك، يتم تحديد نسب المغذيات الكبرى المطلوبة مثل الكربوهيدرات، البروتينات، والدهون. يجب توزيع الوجبات على مدار اليوم بحيث تشمل ثلاث وجبات رئيسية ووجبتين خفيفتين. من المهم اختيار الأطعمة التي تتناسب مع المعايير الغذائية وتكون متوافقة مع العادات الاجتماعية والاقتصادية للفرد. يجب أيضًا مراعاة التنوع والتوازن في الأطعمة لضمان الحصول على جميع العناصر الغذائية اللازمة. | L905: Confirmed (title match) | M905: Batch output file | N905: N | O905: N | P905: N | Q905: Y
A906: QA-0905 | B906: 305 | C906: sIPfEqyxMB8 | D906: https://www.youtube.com/watch?v=sIPfEqyxMB8&list=PL90W1ZUHSNiQiI1BVLP5GuIXxf6hr9Rln&index=2 | E906: التخطيط الغذائي | F906: د. محمود ثابت | G906: دايت بدون حرمان | H906: https://youtube.com/playlist?list=PL90W1ZUHSNiQiI1BVLP5GuIXxf6hr9Rln&si=G_UimDsDy12ttC7G | I906: 23 | J906: ما هي الفوائد الصحية للرضاعة الطبيعية وكيف تساهم في الوقاية من السمنة والأمراض المزمنة؟ | K906: الرضاعة الطبيعية تعزز النمو والمناعة لدى الأطفال، وتحسن من تطور المخ. كما أنها تساهم في الوقاية من السمنة والأمراض المزمنة مثل السكري وأمراض القلب. الرضاعة الطبيعية توفر التغذية المثالية للطفل في الأشهر الأولى من حياته، مما يساعد في بناء نظام مناعي قوي. بالإضافة إلى ذلك، تشير الدراسات إلى أن الأطفال الذين يرضعون طبيعياً يكونون أقل عرضة للإصابة بالسمنة في مراحل لاحقة من حياتهم، مما يقلل من مخاطر الأمراض المرتبطة بالسمنة. | L906: Confirmed (title match) | M906: Batch output file | N906: N | O906: N | P906: N | Q906: Y
A907: QA-0906 | B907: 306 | C907: n4b4yuWK8zI | D907: https://www.youtube.com/watch?v=n4b4yuWK8zI&list=PL90W1ZUHSNiQiI1BVLP5GuIXxf6hr9Rln&index=3 | E907: تصميم النظام الغذائي | F907: د. محمود ثابت | G907: دايت بدون حرمان | H907: https://youtube.com/playlist?list=PL90W1ZUHSNiQiI1BVLP5GuIXxf6hr9Rln&si=G_UimDsDy12ttC7G | I907: 23 | J907: كيف يمكن حساب السعرات الحرارية اللازمة لشخص معين مع مراعاة نشاطه اليومي، وما هي الخطوات التي يجب اتباعها لتعديل مستوى السعرات حسب الأهداف المختلفة مثل فقدان الوزن أو زيادته؟ | K907: لحساب السعرات الحرارية اللازمة لشخص معين، يجب أولاً استخدام معادلة هاريس بنديكت لحساب معدل الأيض الأساسي (BMR) بناءً على الوزن والطول والعمر. بعد ذلك، يتم ضرب الناتج في معامل النشاط اليومي، والذي يعتمد على مستوى النشاط (مثل العمل المكتبي أو النشاط الخفيف). إذا كان الهدف هو فقدان الوزن، يتم تقليل السعرات الحرارية بمقدار معين، بينما إذا كان الهدف هو زيادة الوزن، يتم زيادة السعرات. أما إذا كان الهدف هو تثبيت الوزن، فيتم الحفاظ على السعرات كما هي. | L907: Confirmed (title match) | M907: Batch output file | N907: N | O907: N | P907: N | Q907: N
A908: QA-0907 | B908: 306 | C908: n4b4yuWK8zI | D908: https://www.youtube.com/watch?v=n4b4yuWK8zI&list=PL90W1ZUHSNiQiI1BVLP5GuIXxf6hr9Rln&index=3 | E908: تصميم النظام الغذائي | F908: د. محمود ثابت | G908: دايت بدون حرمان | H908: https://youtube.com/playlist?list=PL90W1ZUHSNiQiI1BVLP5GuIXxf6hr9Rln&si=G_UimDsDy12ttC7G | I908: 23 | J908: ما هي النسب الموصى بها للمغذيات الكبرى في النظام الغذائي، وكيف يمكن تحويل هذه النسب إلى كميات بالجرامات لتلبية احتياجات الطاقة اليومية لشخص معين؟ | K908: النسب الموصى بها للمغذيات الكبرى هي 55% كربوهيدرات، 20% بروتين، و25% دهون. لتحويل هذه النسب إلى كميات بالجرامات، يتم أولاً حساب إجمالي السعرات الحرارية المطلوبة يومياً. ثم يتم حساب السعرات لكل مجموعة غذائية بناءً على النسب المذكورة. بعد ذلك، يتم تحويل السعرات إلى جرامات عن طريق قسمة السعرات على 4 للكربوهيدرات والبروتين، و9 للدهون. على سبيل المثال، إذا كانت الحاجة اليومية 1580 كيلو كالوري، فإن 55% منها كربوهيدرات تعني 869 كيلو كالوري، مما يعادل حوالي 300 جرام كربوهيدرات. | L908: Confirmed (title match) | M908: Batch output file | N908: N | O908: N | P908: N | Q908: N
... A941: QA-0940 | B941: 312 | C941: 88LVHQJz7gI | D941: https://www.youtube.com/watch?v=88LVHQJz7gI&list=PL90W1ZUHSNiQiI1BVLP5GuIXxf6hr9Rln&index=9 | E941: تغذية مرضي الغدة الدرقية و مرضي الجهاز الهضمي | F941: د. محمود ثابت | G941: دايت بدون حرمان | H941: https://youtube.com/playlist?list=PL90W1ZUHSNiQiI1BVLP5GuIXxf6hr9Rln&si=G_UimDsDy12ttC7G | I941: 23 | J941: ما هي المضاعفات المحتملة لفرط نشاط الغدة الدرقية وكيف يمكن أن تؤثر على صحة القلب والعظام؟ | K941: فرط نشاط الغدة الدرقية يمكن أن يؤدي إلى مضاعفات خطيرة مثل مشاكل في القلب، بما في ذلك زيادة معدل ضربات القلب، الرجفان الأذيني، وفشل القلب الاحتقاني. هذه الحالات تحدث نتيجة لزيادة الضغط على القلب بسبب النشاط المفرط. بالإضافة إلى ذلك، يمكن أن يؤدي فرط النشاط إلى هشاشة العظام بسبب تأثير الهرمونات على توازن الكالسيوم في الجسم، مما يزيد من خطر الكسور. لذلك، من المهم مراقبة مستويات الهرمونات وعلاج أي خلل لتجنب هذه المضاعفات. | L941: Confirmed (title match) | M941: Batch output file | N941: N | O941: N | P941: N | Q941: Y
A942: QA-0941 | B942: 313 | C942: hPNcngQcCMg | D942: https://www.youtube.com/watch?v=hPNcngQcCMg&list=PL90W1ZUHSNiQiI1BVLP5GuIXxf6hr9Rln&index=10 | E942: النظام الغذائي لمريض السكر | F942: د. محمود ثابت | G942: دايت بدون حرمان | H942: https://youtube.com/playlist?list=PL90W1ZUHSNiQiI1BVLP5GuIXxf6hr9Rln&si=G_UimDsDy12ttC7G | I942: 23 | J942: ما هي الأسباب الرئيسية التي تؤدي إلى الإصابة بمرض السكر، وكيف تختلف بين النوع الأول والنوع الثاني؟ | K942: مرض السكر يحدث نتيجة غياب أو تناقص إفراز هرمون الأنسولين أو تراجع قدرة الخلايا على استخدامه. النوع الأول (ديابيتس تايب 1) يظهر عادة في الأطفال ويكون بسبب عدم إفراز الأنسولين من خلايا بيتا في البنكرياس منذ الولادة، مما يتطلب حقن الأنسولين مدى الحياة. أما النوع الثاني (ديابيتس تايب 2) فيحدث بسبب ضعف أو قلة إفراز الأنسولين، حيث قد يكون الأنسولين موجودًا ولكن الخلايا تقاومه، وغالبًا ما يرتبط بالسمنة ونمط الحياة غير الصحي. لذا، النوع الأول يعتمد كليًا على الأنسولين، بينما النوع الثاني يمكن تجنبه أو التحكم فيه من خلال تغييرات في نمط الحياة. | L942: Confirmed (title match) | M942: Batch output file | N942: Y | O942: Y | P942: N | Q942: Y | R942: title listed more than once; chosen by batch range
A943: QA-0942 | B943: 313 | C943: hPNcngQcCMg | D943: https://www.youtube.com/watch?v=hPNcngQcCMg&list=PL90W1ZUHSNiQiI1BVLP5GuIXxf6hr9Rln&index=10 | E943: النظام الغذائي لمريض السكر | F943: د. محمود ثابت | G943: دايت بدون حرمان | H943: https://youtube.com/playlist?list=PL90W1ZUHSNiQiI1BVLP5GuIXxf6hr9Rln&si=G_UimDsDy12ttC7G | I943: 23 | J943: كيف يمكن لمريض السكر أن يتجنب المضاعفات الصحية المرتبطة بالمرض، وما هي العوامل التي تؤثر على مستوى السكر في الدم؟ | K943: لتجنب المضاعفات الصحية المرتبطة بمرض السكر، يجب على المريض اتباع نظام غذائي صحي ومتوازن، وممارسة النشاط البدني بانتظام. العوامل التي تؤثر على مستوى السكر في الدم تشمل تناول الكربوهيدرات، نوعية الطعام (مثل المؤشر الجلايسيمي)، والوزن، والنشاط البدني. يجب على المريض قياس مستوى السكر بانتظام، وتوزيع الوجبات بشكل منتظم لتجنب ارتفاع السكر. كما أن العناية بالقدمين وتجنب الإصابات أمر ضروري، حيث أن مريض السكر معرض لمشاكل القدم السكري. | L943: Confirmed (title match) | M943: Batch output file | N943: Y | O943: N | P943: N | Q943: Y | R943: title listed more than once; chosen by batch range
A944: QA-0943 | B944: 313 | C944: hPNcngQcCMg | D944: https://www.youtube.com/watch?v=hPNcngQcCMg&list=PL90W1ZUHSNiQiI1BVLP5GuIXxf6hr9Rln&index=10 | E944: النظام الغذائي لمريض السكر | F944: د. محمود ثابت | G944: دايت بدون حرمان | H944: https://youtube.com/playlist?list=PL90W1ZUHSNiQiI1BVLP5GuIXxf6hr9Rln&si=G_UimDsDy12ttC7G | I944: 23 | J944: ما هي الفروق الأساسية بين أعراض مرض السكر وأعراض السكر الكاذب، وكيف يمكن التمييز بينهما؟ | K944: أعراض مرض السكر تشمل العطش المتكرر، التعب، زيادة الوزن، وكثرة التبول، بينما أعراض السكر الكاذب (ديابيتس انبس) تشمل فقدان الوزن مع العطش وكثرة التبول، ولكن لا يوجد ارتفاع في مستوى السكر في الدم. التمييز بينهما يعتمد على ملاحظة الوزن: إذا كان الوزن يزيد مع الأعراض، فهذا يشير إلى مرض السكر، أما إذا كان الوزن ينقص، فهذا يشير إلى السكر الكاذب. السكر الكاذب يحدث بسبب عدم قدرة الكلى على تخزين الماء، بينما مرض السكر يحدث بسبب ارتفاع مستوى السكر في الدم. | L944: Confirmed (title match) | M944: Batch output file | N944: Y | O944: N | P944: N | Q944: Y | R944: title listed more than once; chosen by batch range
A945: QA-0944 | B945: 313 | C945: hPNcngQcCMg | D945: https://www.youtube.com/watch?v=hPNcngQcCMg&list=PL90W1ZUHSNiQiI1BVLP5GuIXxf6hr9Rln&index=10 | E945: النظام الغذائي لمريض السكر | F945: د. محمود ثابت | G945: دايت بدون حرمان | H945: https://youtube.com/playlist?list=PL90W1ZUHSNiQiI1BVLP5GuIXxf6hr9Rln&si=G_UimDsDy12ttC7G | I945: 23 | J945: كيف يؤثر النشاط البدني على مستوى السكر في الدم لدى مرضى السكر، وما هي الاحتياطات التي يجب اتخاذها قبل ممارسة الرياضة؟ | K945: النشاط البدني يساعد على خفض مستوى السكر والدهون في الدم، ويقلل من مقاومة خلايا الأنسولين، مما يعزز من فعالية الأنسولين في الجسم. قبل ممارسة الرياضة، يجب قياس مستوى السكر في الدم، والتأكد من أنه في مستوى آمن. من الضروري أيضًا استشارة الطبيب حول نوعية الرياضة المناسبة، وتجنب ممارسة الرياضة في أوقات ذروة تأثير الأنسولين. يجب على المريض أن يحمل وجبة خفيفة أو مشروب سكري في حال حدوث هبوط في مستوى السكر أثناء التمرين. | L945: Confirmed (title match) | M945: Batch output file | N945: Y | O945: N | P945: N | Q945: Y | R945: title listed more than once; chosen by batch range
A946: QA-0945 | B946: 313 | C946: hPNcngQcCMg | D946: https://www.youtube.com/watch?v=hPNcngQcCMg&list=PL90W1ZUHSNiQiI1BVLP5GuIXxf6hr9Rln&index=10 | E946: النظام الغذائي لمريض السكر | F946: د. محمود ثابت | G946: دايت بدون حرمان | H946: https://youtube.com/playlist?list=PL90W1ZUHSNiQiI1BVLP5GuIXxf6hr9Rln&si=G_UimDsDy12ttC7G | I946: 23 | J946: ما هي أهمية النظام الغذائي لمريض السكر، وكيف يمكن تصميم خطة غذائية مناسبة له؟ | K946: النظام الغذائي لمريض السكر مهم للحفاظ على مستوى السكر في الدم، وتجنب المضاعفات، وتقليل الحاجة للأدوية. يجب تصميم خطة غذائية تأخذ في الاعتبار حساب الكربوهيدرات، وتوزيع الوجبات على مدار اليوم، واختيار الأطعمة ذات المؤشر الجلايسيمي المنخفض. يجب أن تشمل الوجبات البروتينات الصحية، الدهون المفيدة، والخضروات، مع تجنب الأطعمة الغنية بالسكريات والدهون المتحولة. كما يجب أن يكون هناك مرونة في النظام الغذائي، بحيث يتمكن المريض من تناول مجموعة متنوعة من الأطعمة دون حرمان. | L946: Confirmed (title match) | M946: Batch output file | N946: Y | O946: N | P946: N | Q946: Y | R946: title listed more than once; chosen by batch range
A947: QA-0946 | B947: 314 | C947: OWIvDsek7MU | D947: https://www.youtube.com/watch?v=OWIvDsek7MU&list=PL90W1ZUHSNiQiI1BVLP5GuIXxf6hr9Rln&index=11 | E947: السمنة و متلازمة التمثيل الغذائي | F947: د. محمود ثابت | G947: دايت بدون حرمان | H947: https://youtube.com/playlist?list=PL90W1ZUHSNiQiI1BVLP5GuIXxf6hr9Rln&si=G_UimDsDy12ttC7G | I947: 23 | J947: ما هي العوامل المختلفة التي تؤدي إلى السمنة وكيف تؤثر على الصحة العامة للفرد؟ | K947: تتعدد العوامل التي تؤدي إلى السمنة، منها العوامل الوراثية والبيئية والنفسية. العوامل الوراثية تشمل الجينات التي قد تجعل بعض الأفراد أكثر عرضة لزيادة الوزن. أما العوامل البيئية فتتعلق بنمط الحياة، مثل توافر الأطعمة الغنية بالسعرات الحرارية وقلة النشاط البدني. العوامل النفسية تلعب دورًا أيضًا، حيث يمكن أن يؤدي التوتر والقلق إلى زيادة تناول الطعام. هذه العوامل مجتمعة تؤدي إلى تراكم الدهون في الجسم، مما يزيد من خطر الإصابة بأمراض القلب، ارتفاع ضغط الدم، داء السكري من النوع الثاني، وبعض أنواع السرطان. | L947: Confirmed (title match) | M947: Batch output file | N947: N | O947: N | P947: N | Q947: Y
A948: QA-0947 | B948: 314 | C948: OWIvDsek7MU | D948: https://www.youtube.com/watch?v=OWIvDsek7MU&list=PL90W1ZUHSNiQiI1BVLP5GuIXxf6hr9Rln&index=11 | E948: السمنة و متلازمة التمثيل الغذائي | F948: د. محمود ثابت | G948: دايت بدون حرمان | H948: https://youtube.com/playlist?list=PL90W1ZUHSNiQiI1BVLP5GuIXxf6hr9Rln&si=G_UimDsDy12ttC7G | I948: 23 | J948: كيف يتم تشخيص السمنة وما هي المعايير المستخدمة لتحديد مستوياتها المختلفة؟ | K948: يتم تشخيص السمنة باستخدام عدة معايير، منها مؤشر كتلة الجسم (BMI) الذي يقيس الوزن بالنسبة للطول. يُعتبر الشخص بدينًا إذا كان مؤشر كتلة الجسم لديه 30 أو أكثر. بالإضافة إلى ذلك، يتم استخدام قياسات محيط الخصر، حيث يجب أن يكون أقل من 95 سم للرجال وأقل من 80 سم للنساء. هناك أيضًا تصنيفات أخرى مثل تصنيف السمنة إلى ثلاث فئات: الفئة الأولى (30-35)، الفئة الثانية (35-40)، والفئة الثالثة (أكثر من 40) والتي تُعرف بالسمنة المفرطة أو القاتلة. | L948: Confirmed (title match) | M948: Batch output file | N948: N | O948: N | P948: N | Q948: Y
A949: QA-0948 | B949: 314 | C949: OWIvDsek7MU | D949: https://www.youtube.com/watch?v=OWIvDsek7MU&list=PL90W1ZUHSNiQiI1BVLP5GuIXxf6hr9Rln&index=11 | E949: السمنة و متلازمة التمثيل الغذائي | F949: د. محمود ثابت | G949: دايت بدون حرمان | H949: https://youtube.com/playlist?list=PL90W1ZUHSNiQiI1BVLP5GuIXxf6hr9Rln&si=G_UimDsDy12ttC7G | I949: 23 | J949: ما هي الآثار الصحية المحتملة للسمنة على الجسم وكيف تؤثر على جودة الحياة؟ | K949: السمنة تؤدي إلى مجموعة من الآثار الصحية السلبية، منها زيادة خطر الإصابة بأمراض القلب، السكتات الدماغية، وارتفاع مستويات الكوليسترول. كما أنها ترتبط بمشاكل صحية مثل داء السكري من النوع الثاني، متلازمة الأيض، وبعض أنواع السرطان. بالإضافة إلى ذلك، تؤثر السمنة على جودة الحياة من خلال تقليل القدرة على الحركة، زيادة الشعور بالتعب، وتسبب مشاكل نفسية مثل الاكتئاب والقلق. هذه العوامل مجتمعة تؤدي إلى تدهور الصحة العامة وتقليل متوسط العمر المتوقع. | L949: Confirmed (title match) | M949: Batch output file | N949: N | O949: N | P949: N | Q949: Y
A950: QA-0949 | B950: 314 | C950: OWIvDsek7MU | D950: https://www.youtube.com/watch?v=OWIvDsek7MU&list=PL90W1ZUHSNiQiI1BVLP5GuIXxf6hr9Rln&index=11 | E950: السمنة و متلازمة التمثيل الغذائي | F950: د. محمود ثابت | G950: دايت بدون حرمان | H950: https://youtube.com/playlist?list=PL90W1ZUHSNiQiI1BVLP5GuIXxf6hr9Rln&si=G_UimDsDy12ttC7G | I950: 23 | J950: كيف يمكن معالجة السمنة بشكل فعال وما هي الاستراتيجيات التي يجب اتباعها لتحقيق نتائج مستدامة؟ | K950: معالجة السمنة تتطلب اتباع استراتيجيات متعددة تشمل تعديل السلوك الغذائي، زيادة النشاط البدني، وتقديم الدعم النفسي. يجب على الأفراد اتباع نظام غذائي متوازن يحتوي على الخضروات والفواكه والحبوب الكاملة، مع تقليل الدهون والسكريات. من المهم أيضًا ممارسة النشاط البدني بانتظام، مثل المشي لمدة 30 دقيقة يوميًا. بالإضافة إلى ذلك، يجب تقديم الدعم النفسي للمساعدة في تغيير العادات السلوكية المرتبطة بتناول الطعام. في بعض الحالات، قد تكون الأدوية أو الجراحة ضرورية، ولكن يجب أن تكون تحت إشراف طبي دقيق. | L950: Confirmed (title match) | M950: Batch output file | N950: N | O950: N | P950: N | Q950: Y
A951: QA-0950 | B951: 314 | C951: OWIvDsek7MU | D951: https://www.youtube.com/watch?v=OWIvDsek7MU&list=PL90W1ZUHSNiQiI1BVLP5GuIXxf6hr9Rln&index=11 | E951: السمنة و متلازمة التمثيل الغذائي | F951: د. محمود ثابت | G951: دايت بدون حرمان | H951: https://youtube.com/playlist?list=PL90W1ZUHSNiQiI1BVLP5GuIXxf6hr9Rln&si=G_UimDsDy12ttC7G | I951: 23 | J951: ما هي العلاقة بين الهرمونات والسمنة وكيف تؤثر على تنظيم الشهية والتمثيل الغذائي؟ | K951: الهرمونات تلعب دورًا حيويًا في تنظيم الشهية والتمثيل الغذائي. هرمون الليبتين، الذي يُفرز من الخلايا الدهنية، يساعد في تقليل الشهية وزيادة حرق الدهون. بينما هرمون الجريلين، الذي يُفرز عندما تكون المعدة فارغة، يزيد من الشهية. في حالة السمنة، قد يحدث خلل في هذه الهرمونات، حيث يمكن أن يرتفع مستوى الجريلين ويقل مستوى الليبتين، مما يؤدي إلى زيادة الشهية وتراكم الدهون. كما أن مقاومة الأنسولين، التي ترتبط بالسمنة، تؤثر على كيفية استخدام الجسم للجلوكوز، مما يزيد من خطر الإصابة بأمراض مثل السكري. | L951: Confirmed (title match) | M951: Batch output file | N951: N | O951: N | P951: N | Q951: Y
A952: QA-0951 | B952: 315 | C952: E_mKYIIGa8M | D952: https://www.youtube.com/watch?v=E_mKYIIGa8M&list=PL90W1ZUHSNiQiI1BVLP5GuIXxf6hr9Rln&index=12 | E952: الانظمة الغذائية المختلفة | F952: د. محمود ثابت | G952: دايت بدون حرمان | H952: https://youtube.com/playlist?list=PL90W1ZUHSNiQiI1BVLP5GuIXxf6hr9Rln&si=G_UimDsDy12ttC7G | I952: 23 | J952: ما هي الأنظمة الغذائية المختلفة التي تم تناولها في المحاضرة، وما هي الفوائد والأضرار المرتبطة بكل منها؟ | K952: تم تناول عدة أنظمة غذائية في المحاضرة، منها: 1. **النظام النباتي (فيجان وفيجيتيريان)**: - **الفوائد**: يقلل من الإصابة بأمراض القلب والسكري وبعض أنواع السرطان. - **الأضرار**: نقص في الحديد وفيتامين ب12، مما يؤدي إلى فقر الدم، بالإضافة إلى مشاكل هرمونية مثل تساقط الشعر. 2. **النظام منخفض الكربوهيدرات (لو كارب)**: - **الفوائد**: يساعد في إنقاص الوزن، ويقلل من مستويات السكر في الدم. - **الأضرار**: قد يؤدي إلى الإمساك ونقص العناصر الغذائية. 3. **نظام باليو (رجل الكهف)**: - **الفوائد**: يعتمد على الأطعمة الطبيعية، مما يعزز الصحة العامة. - **الأضرار**: نقص في الألياف والفيتامينات بسبب استبعاد الحبوب والبقوليات. 4. **الكيتو دايت**: - **الفوائد**: يساعد في فقدان الوزن ويستخدم كعلاج لبعض الأمراض العصبية. - **الأضرار**: قد يسبب نقص المغذيات وزيادة الكوليسترول الضار. 5. **نظام البحر الأبيض المتوسط**: - **الفوائد**: يحسن صحة القلب ويقلل من خطر الأمراض المزمنة. - **الأضرار**: قد يؤدي إلى زيادة الوزن إذا تم تناول الدهون بكميات كبيرة. | L952: Confirmed (title match) | M952: Batch output file | N952: N | O952: N | P952: N | Q952: Y
A953: QA-0952 | B953: 315 | C953: E_mKYIIGa8M | D953: https://www.youtube.com/watch?v=E_mKYIIGa8M&list=PL90W1ZUHSNiQiI1BVLP5GuIXxf6hr9Rln&index=12 | E953: الانظمة الغذائية المختلفة | F953: د. محمود ثابت | G953: دايت بدون حرمان | H953: https://youtube.com/playlist?list=PL90W1ZUHSNiQiI1BVLP5GuIXxf6hr9Rln&si=G_UimDsDy12ttC7G | I953: 23 | J953: كيف يؤثر النظام الغذائي النباتي على الصحة العامة، وما هي المخاطر المحتملة المرتبطة به؟ | K953: النظام الغذائي النباتي له تأثيرات إيجابية وسلبية على الصحة العامة. - **الإيجابيات**: 1. **فقدان الوزن**: يساعد في تقليل الوزن بسبب انخفاض السعرات الحرارية. 2. **تحسين صحة القلب**: يقلل من مستويات الكوليسترول الضار. 3. **تقليل خطر الإصابة ببعض الأمراض**: مثل السكري من النوع الثاني وبعض أنواع السرطان. - **السلبيات**: 1. **نقص المغذيات**: مثل الحديد وفيتامين ب12، مما قد يؤدي إلى فقر الدم. 2. **مشاكل هرمونية**: مثل عدم انتظام الدورة الشهرية وتساقط الشعر. 3. **اضطرابات هضمية**: مثل الإمساك بسبب نقص الألياف. 4. **تسرب الأمعاء**: نتيجة لتناول أطعمة تحتوي على بكتيريا ضارة. | L953: Confirmed (title match) | M953: Batch output file | N953: N | O953: N | P953: N | Q953: Y
A954: QA-0953 | B954: 315 | C954: E_mKYIIGa8M | D954: https://www.youtube.com/watch?v=E_mKYIIGa8M&list=PL90W1ZUHSNiQiI1BVLP5GuIXxf6hr9Rln&index=12 | E954: الانظمة الغذائية المختلفة | F954: د. محمود ثابت | G954: دايت بدون حرمان | H954: https://youtube.com/playlist?list=PL90W1ZUHSNiQiI1BVLP5GuIXxf6hr9Rln&si=G_UimDsDy12ttC7G | I954: 23 | J954: ما هي الفروقات الرئيسية بين الأنظمة الغذائية المختلفة مثل الكيتو واللو كارب والباليو، وكيف تؤثر هذه الفروقات على النتائج الصحية؟ | K954: الأنظمة الغذائية المختلفة مثل الكيتو واللو كارب والباليو تختلف في مكوناتها ونسب العناصر الغذائية. 1. **الكيتو دايت**: - **النسبة**: 70% دهون، 20% بروتين، 10% كربوهيدرات. - **التأثير**: يدخل الجسم في حالة الكيتوزية، مما يساعد في حرق الدهون كمصدر رئيسي للطاقة. 2. **اللو كارب**: - **النسبة**: 25-40% كربوهيدرات، 30-40% بروتين، 30-40% دهون. - **التأثير**: يقلل من مستويات السكر في الدم ويعزز فقدان الوزن، لكنه قد يسبب نقص في الألياف. 3. **نظام باليو**: - **النسبة**: 20% كربوهيدرات، 50% دهون، 30% بروتين. - **التأثير**: يعتمد على الأطعمة الطبيعية، مما يعزز الصحة العامة، لكنه قد يؤدي إلى نقص في الألياف والفيتامينات بسبب استبعاد الحبوب والبقوليات. الفروقات في النسب تؤثر على كيفية استجابة الجسم لكل نظام، مما يؤدي إلى نتائج صحية مختلفة. | L954: Confirmed (title match) | M954: Batch output file | N954: N | O954: N | P954: N | Q954: Y
A955: QA-0954 | B955: 315 | C955: E_mKYIIGa8M | D955: https://www.youtube.com/watch?v=E_mKYIIGa8M&list=PL90W1ZUHSNiQiI1BVLP5GuIXxf6hr9Rln&index=12 | E955: الانظمة الغذائية المختلفة | F955: د. محمود ثابت | G955: دايت بدون حرمان | H955: https://youtube.com/playlist?list=PL90W1ZUHSNiQiI1BVLP5GuIXxf6hr9Rln&si=G_UimDsDy12ttC7G | I955: 23 | J955: كيف يمكن أن يؤثر الصيام المتقطع على الصحة العامة، وما هي الفوائد والمخاطر المرتبطة به؟ | K955: الصيام المتقطع له تأثيرات متعددة على الصحة العامة. - **الفوائد**: 1. **فقدان الوزن**: يساعد في تقليل السعرات الحرارية المتناولة. 2. **تحسين مستويات السكر**: يقلل من مقاومة الأنسولين. 3. **تعزيز الصحة العقلية**: قد يحسن من وظائف الدماغ ويقلل من خطر الأمراض العصبية. 4. **تقليل الالتهابات**: يساعد في تقليل الالتهابات المرتبطة بالعديد من الأمراض. - **المخاطر**: 1. **صعوبة الالتزام**: قد يكون من الصعب على بعض الأشخاص الالتزام بفترات الصيام. 2. **نقص العناصر الغذائية**: إذا لم يتم تناول وجبات متوازنة خلال فترات الأكل. 3. **تأثيرات سلبية على الطاقة**: قد يشعر البعض بالتعب أو الإرهاق خلال فترات الصيام. | L955: Confirmed (title match) | M955: Batch output file | N955: N | O955: N | P955: N | Q955: Y
A956: QA-0955 | B956: 315 | C956: E_mKYIIGa8M | D956: https://www.youtube.com/watch?v=E_mKYIIGa8M&list=PL90W1ZUHSNiQiI1BVLP5GuIXxf6hr9Rln&index=12 | E956: الانظمة الغذائية المختلفة | F956: د. محمود ثابت | G956: دايت بدون حرمان | H956: https://youtube.com/playlist?list=PL90W1ZUHSNiQiI1BVLP5GuIXxf6hr9Rln&si=G_UimDsDy12ttC7G | I956: 23 | J956: ما هي العوامل التي تؤثر على اختيار النظام الغذائي المناسب للفرد، وكيف يمكن أن تتداخل هذه العوامل مع الصحة العامة؟ | K956: اختيار النظام الغذائي المناسب يعتمد على عدة عوامل تؤثر على الصحة العامة. 1. **الأهداف الصحية**: مثل فقدان الوزن، تحسين مستويات السكر، أو تعزيز الصحة العامة. 2. **الحالة الصحية الحالية**: مثل وجود أمراض مزمنة أو حساسية غذائية. 3. **الأسلوب الحياتي**: مدى النشاط البدني والجدول الزمني اليومي. 4. **التفضيلات الغذائية**: مثل الرغبة في تناول الأطعمة النباتية أو الحيوانية. 5. **الدعم الاجتماعي**: وجود دعم من الأصدقاء أو العائلة يمكن أن يؤثر على الالتزام بالنظام الغذائي. هذه العوامل تتداخل مع الصحة العامة من خلال التأثير على قدرة الفرد على الالتزام بالنظام الغذائي، مما يؤثر على النتائج الصحية على المدى الطويل. | L956: Confirmed (title match) | M956: Batch output file | N956: N | O956: N | P956: N | Q956: Y
A957: QA-0956 | B957: 317 | C957: 9zwbC0GeTHo | D957: https://www.youtube.com/watch?v=9zwbC0GeTHo&list=PL90W1ZUHSNiQiI1BVLP5GuIXxf6hr9Rln&index=14 | E957: التغذية العلاجية لمرضي الاورام | F957: د. محمود ثابت | G957: دايت بدون حرمان | H957: https://youtube.com/playlist?list=PL90W1ZUHSNiQiI1BVLP5GuIXxf6hr9Rln&si=G_UimDsDy12ttC7G | I957: 23 | J957: ما هي العلاقة بين النظام الغذائي وزيادة خطر الإصابة بالسرطان، وكيف يمكن أن تؤثر العادات الغذائية على احتمالية الإصابة بهذا المرض؟ | K957: العلاقة بين النظام الغذائي وزيادة خطر الإصابة بالسرطان تتجلى في تأثير بعض الأطعمة على صحة الجسم. الأبحاث تشير إلى أن تناول أطعمة معينة، مثل اللحوم الحمراء والمعالجة، يمكن أن يزيد من خطر الإصابة بسرطان القولون، بينما تناول الأطعمة الغنية بالفواكه والخضروات وزيت الزيتون والأسماك، كما هو الحال في النظام الغذائي لمنطقة البحر الأحمر، يمكن أن يقلل من خطر الإصابة بسرطان الثدي. بالتالي، اتباع نظام غذائي صحي ومتوازن يمكن أن يكون له تأثير وقائي كبير على المدى الطويل، خاصة في حالة وجود تاريخ عائلي للسرطان. | L957: Confirmed (title match) | M957: Batch output file | N957: N | O957: N | P957: N | Q957: Y
A958: QA-0957 | B958: 317 | C958: 9zwbC0GeTHo | D958: https://www.youtube.com/watch?v=9zwbC0GeTHo&list=PL90W1ZUHSNiQiI1BVLP5GuIXxf6hr9Rln&index=14 | E958: التغذية العلاجية لمرضي الاورام | F958: د. محمود ثابت | G958: دايت بدون حرمان | H958: https://youtube.com/playlist?list=PL90W1ZUHSNiQiI1BVLP5GuIXxf6hr9Rln&si=G_UimDsDy12ttC7G | I958: 23 | J958: كيف يمكن أن تؤثر العوامل الوراثية والبيئية على احتمالية الإصابة بالسرطان، وما هي النسبة التي يمكن التحكم فيها من خلال النظام الغذائي؟ | K958: العوامل الوراثية والبيئية تلعب دورًا كبيرًا في احتمالية الإصابة بالسرطان، حيث تشير الأبحاث إلى أن حوالي 30% من أسباب الإصابة بالسرطان لا يمكن تلافيها، مثل العوامل الوراثية والبيئية. ومع ذلك، هناك نسبة كبيرة من العوامل التي يمكن التحكم فيها، حيث يمكن للنظام الغذائي أن يؤثر بشكل كبير على صحة الفرد. من خلال اتباع نظام غذائي صحي، يمكن تقليل خطر الإصابة بالسرطان بشكل ملحوظ، مما يبرز أهمية التغذية في الوقاية من هذا المرض. | L958: Confirmed (title match) | M958: Batch output file | N958: N | O958: N | P958: N | Q958: Y
... A971: QA-0970 | B971: 319 | C971: 1Bemm6YGWyg | D971: https://www.youtube.com/watch?v=1Bemm6YGWyg&list=PL90W1ZUHSNiQiI1BVLP5GuIXxf6hr9Rln&index=16 | E971: التغذبة والجمال | F971: د. محمود ثابت | G971: دايت بدون حرمان | H971: https://youtube.com/playlist?list=PL90W1ZUHSNiQiI1BVLP5GuIXxf6hr9Rln&si=G_UimDsDy12ttC7G | I971: 23 | J971: ما هي النصائح الأساسية للعناية بالأظافر وكيف يمكن أن تعكس صحة الجسم العامة؟ | K971: العناية بالأظافر تتطلب ترطيب الجلد المحيط بها، استخدام صابون متعادل، وتجنب التعرض للمواد الكيميائية القاسية. يجب أيضًا تناول نظام غذائي متوازن يحتوي على البروتينات، الفيتامينات، والمعادن الضرورية مثل البيوتين والزنك. صحة الأظافر تعكس صحة الجسم العامة، حيث أن الأظافر الضعيفة أو المتكسرة قد تشير إلى نقص في التغذية أو وجود مشاكل صحية داخلية. | L971: Confirmed (title match) | M971: Batch output file | N971: N | O971: N | P971: N | Q971: Y
A972: QA-0971 | B972: 320 | C972: 1i2RmroF2Wc | D972: https://www.youtube.com/watch?v=1i2RmroF2Wc&list=PL90W1ZUHSNiQiI1BVLP5GuIXxf6hr9Rln&index=17 | E972: تصميم النظام الغذائي - ازاي تعمل نظام غذائي بطريقة الحصص و البدائل الغذائية | F972: د. محمود ثابت | G972: دايت بدون حرمان | H972: https://youtube.com/playlist?list=PL90W1ZUHSNiQiI1BVLP5GuIXxf6hr9Rln&si=G_UimDsDy12ttC7G | I972: 23 | J972: ما هي الخطوات الأساسية التي يجب اتباعها عند تصميم نظام غذائي يدوي، وكيف يتم حساب السعرات الحرارية والمغذيات الكبرى وفقًا لحالة الشخص؟ | K972: عند تصميم نظام غذائي يدوي، يجب اتباع عدة خطوات أساسية: أولاً، يتم حساب السعرات الحرارية اللازمة للشخص مع مراعاة مستوى نشاطه اليومي. بعد ذلك، يتم تعديل مستوى السعرات الحرارية بناءً على احتياجات الشخص، سواء كان يحتاج إلى فقدان الوزن، زيادة الوزن، أو الحفاظ على الوزن. ثم يتم حساب نسب المغذيات الكبرى (الكربوهيدرات، البروتينات، والدهون) والكميات المطلوبة منها. بعد ذلك، يتم اختيار الحصص والمجموعات الغذائية بناءً على السعرات الحرارية المطلوبة، وأخيرًا يتم توزيع الأطعمة المختارة على الوجبات اليومية. على سبيل المثال، إذا كان لدينا رجل عمره 45 سنة، وزنه 72 كغم، وطوله 167 سم، يتم حساب السعرات الحرارية باستخدام معادلة معينة، ثم يتم تحديد نسب المغذيات الكبرى بناءً على احتياجاته. | L972: Confirmed (title match) | M972: Batch output file | N972: Y | O972: N | P972: N | Q972: N | R972: title listed more than once; chosen by batch range
A973: QA-0972 | B973: 320 | C973: 1i2RmroF2Wc | D973: https://www.youtube.com/watch?v=1i2RmroF2Wc&list=PL90W1ZUHSNiQiI1BVLP5GuIXxf6hr9Rln&index=17 | E973: تصميم النظام الغذائي - ازاي تعمل نظام غذائي بطريقة الحصص و البدائل الغذائية | F973: د. محمود ثابت | G973: دايت بدون حرمان | H973: https://youtube.com/playlist?list=PL90W1ZUHSNiQiI1BVLP5GuIXxf6hr9Rln&si=G_UimDsDy12ttC7G | I973: 23 | J973: كيف يمكن استخدام برنامج Excel في تصميم النظام الغذائي، وما هي الخطوات التي يجب اتباعها لضمان دقة الحسابات؟ | K973: يمكن استخدام برنامج Excel في تصميم النظام الغذائي من خلال إدخال البيانات الأساسية مثل العمر، الوزن، الطول، ومستوى النشاط. الخطوات التي يجب اتباعها تشمل: أولاً، إدخال البيانات في الخانات المخصصة، حيث يتم حساب معدل الأيض الأساسي (BMR) تلقائيًا. بعد ذلك، يتم تحديد مستوى النشاط اليومي، مما يؤثر على السعرات الحرارية المطلوبة. يمكن تعديل السعرات حسب الهدف (فقدان، زيادة، أو الحفاظ على الوزن) من خلال إدخال الأرقام المناسبة. بعد ذلك، يتم حساب نسب المغذيات الكبرى وتحويل السعرات الحرارية إلى جرامات. يجب التأكد من دقة الأرقام المدخلة ومراجعة الحسابات لضمان الحصول على نظام غذائي متوازن. | L973: Confirmed (title match) | M973: Batch output file | N973: Y | O973: N | P973: N | Q973: N | R973: title listed more than once; chosen by batch range
A974: QA-0973 | B974: 320 | C974: 1i2RmroF2Wc | D974: https://www.youtube.com/watch?v=1i2RmroF2Wc&list=PL90W1ZUHSNiQiI1BVLP5GuIXxf6hr9Rln&index=17 | E974: تصميم النظام الغذائي - ازاي تعمل نظام غذائي بطريقة الحصص و البدائل الغذائية | F974: د. محمود ثابت | G974: دايت بدون حرمان | H974: https://youtube.com/playlist?list=PL90W1ZUHSNiQiI1BVLP5GuIXxf6hr9Rln&si=G_UimDsDy12ttC7G | I974: 23 | J974: ما هي العلاقة بين النشاط البدني ومتطلبات السعرات الحرارية، وكيف يؤثر ذلك على تصميم النظام الغذائي؟ | K974: النشاط البدني له تأثير كبير على متطلبات السعرات الحرارية، حيث أن الأشخاص الذين يمارسون نشاطًا بدنيًا بانتظام يحتاجون إلى سعرات حرارية أكثر مقارنةً بالأشخاص غير النشطين. في حالة الرجل المذكور في المحاضرة، حيث يمارس المشي ثلاث مرات أسبوعيًا، يتم تصنيفه كنشط نسبيًا، مما يتطلب زيادة في السعرات الحرارية. لذلك، عند تصميم النظام الغذائي، يجب مراعاة مستوى النشاط البدني لتحديد السعرات الحرارية المناسبة، مما يؤثر على توزيع المغذيات الكبرى. على سبيل المثال، إذا كان الهدف هو الحفاظ على الوزن، يجب حساب السعرات الحرارية بناءً على النشاط البدني لضمان تلبية احتياجات الجسم. | L974: Confirmed (title match) | M974: Batch output file | N974: Y | O974: N | P974: N | Q974: N | R974: title listed more than once; chosen by batch range
A975: QA-0974 | B975: 320 | C975: 1i2RmroF2Wc | D975: https://www.youtube.com/watch?v=1i2RmroF2Wc&list=PL90W1ZUHSNiQiI1BVLP5GuIXxf6hr9Rln&index=17 | E975: تصميم النظام الغذائي - ازاي تعمل نظام غذائي بطريقة الحصص و البدائل الغذائية | F975: د. محمود ثابت | G975: دايت بدون حرمان | H975: https://youtube.com/playlist?list=PL90W1ZUHSNiQiI1BVLP5GuIXxf6hr9Rln&si=G_UimDsDy12ttC7G | I975: 23 | J975: كيف يمكن توزيع الأطعمة على مدار اليوم لضمان توازن النظام الغذائي، وما هي الاعتبارات التي يجب أخذها في الحسبان؟ | K975: لتوزيع الأطعمة على مدار اليوم وضمان توازن النظام الغذائي، يجب مراعاة عدة اعتبارات: أولاً، يجب توزيع الحصص الغذائية بشكل متوازن بين الوجبات الرئيسية والوجبات الخفيفة. على سبيل المثال، يمكن تناول وجبة فطور غنية بالبروتين والكربوهيدرات، مثل طبق فول مع بيضة مسلوقة وكوب من اللبن. ثانياً، يجب مراعاة تنوع الأطعمة لضمان الحصول على جميع العناصر الغذائية اللازمة. ثالثاً، يجب أن تتناسب الكميات مع احتياجات الشخص، مثل تناول 300 جرام من الكربوهيدرات و109 جرام من البروتين يوميًا. وأخيرًا، يجب أن تكون الوجبات متناسبة مع أوقات النشاط والراحة، مما يساعد على تحسين مستويات الطاقة والأداء طوال اليوم. | L975: Confirmed (title match) | M975: Batch output file | N975: Y | O975: N | P975: N | Q975: N | R975: title listed more than once; chosen by batch range
A976: QA-0975 | B976: 320 | C976: 1i2RmroF2Wc | D976: https://www.youtube.com/watch?v=1i2RmroF2Wc&list=PL90W1ZUHSNiQiI1BVLP5GuIXxf6hr9Rln&index=17 | E976: تصميم النظام الغذائي - ازاي تعمل نظام غذائي بطريقة الحصص و البدائل الغذائية | F976: د. محمود ثابت | G976: دايت بدون حرمان | H976: https://youtube.com/playlist?list=PL90W1ZUHSNiQiI1BVLP5GuIXxf6hr9Rln&si=G_UimDsDy12ttC7G | I976: 23 | J976: ما هي أهمية استخدام بدائل غذائية في تصميم النظام الغذائي، وكيف يمكن أن تسهم في تحقيق الأهداف الغذائية؟ | K976: استخدام بدائل غذائية في تصميم النظام الغذائي له أهمية كبيرة، حيث يوفر مرونة في اختيار الأطعمة ويساعد على تحقيق الأهداف الغذائية بشكل أكثر فعالية. بدائل غذائية تسمح بتغيير المكونات دون التأثير على القيمة الغذائية، مما يسهل على الشخص الالتزام بالنظام الغذائي. على سبيل المثال، يمكن استبدال 100 جرام من اللحوم بـ 100 جرام من صدور الدجاج أو البيض، مما يضمن الحصول على نفس الكمية من البروتين. كما أن استخدام بدائل غذائية يساعد في تجنب الملل من النظام الغذائي، مما يزيد من احتمالية الالتزام به على المدى الطويل. بالإضافة إلى ذلك، يمكن أن تساعد البدائل الغذائية في تلبية الاحتياجات الخاصة للأفراد، مثل الحساسية أو تفضيلات الطعام. | L976: Confirmed (title match) | M976: Batch output file | N976: Y | O976: N | P976: N | Q976: N | R976: title listed more than once; chosen by batch range
A977: QA-0976 | B977: 321 | C977: Rrja55i3SW0 | D977: https://www.youtube.com/watch?v=Rrja55i3SW0&list=PL90W1ZUHSNiQiI1BVLP5GuIXxf6hr9Rln&index=18 | E977: التعامل مع الحالات في العيادة | F977: د. محمود ثابت | G977: دايت بدون حرمان | H977: https://youtube.com/playlist?list=PL90W1ZUHSNiQiI1BVLP5GuIXxf6hr9Rln&si=G_UimDsDy12ttC7G | I977: 23 | J977: كيف يتم تقييم الحالة الغذائية للمريض عند دخوله العيادة، وما هي الخطوات التي يجب اتباعها لضمان تقديم خطة علاجية فعالة؟ | K977: عند دخول المريض إلى العيادة، يتم تقييم حالته الغذائية من خلال عدة خطوات مدروسة. أولاً، يتم استقبال المريض بطريقة ودية لكسر حاجز الخوف، مما يسهل التواصل. بعد ذلك، يقوم الأخصائي بتقييم الحالة من جوانب جسمانية وصحية ونفسية. يتم مناقشة التقييم مع المريض لضمان فهمه للوضع، ويجب أن يتضمن ذلك شرحاً مفصلاً عن المعلومات الغذائية السابقة. بعد ذلك، يتم تحديد الأهداف العلاجية بالتعاون مع المريض، حيث يجب أن يوافق على كل هدف. ثم يتم وضع خطة غذائية بناءً على المعطيات التي تم جمعها، مع ضرورة شرحها بشكل كامل للمريض. المتابعة الدقيقة بعد ذلك تكون كل ست إلى ثمان أسابيع، مع إمكانية التواصل عبر وسائل التواصل الاجتماعي لحل أي مشكلات تظهر في الوقت المناسب. | L977: Confirmed (title match) | M977: Batch output file | N977: N | O977: N | P977: N | Q977: Y
A978: QA-0977 | B978: 321 | C978: Rrja55i3SW0 | D978: https://www.youtube.com/watch?v=Rrja55i3SW0&list=PL90W1ZUHSNiQiI1BVLP5GuIXxf6hr9Rln&index=18 | E978: التعامل مع الحالات في العيادة | F978: د. محمود ثابت | G978: دايت بدون حرمان | H978: https://youtube.com/playlist?list=PL90W1ZUHSNiQiI1BVLP5GuIXxf6hr9Rln&si=G_UimDsDy12ttC7G | I978: 23 | J978: ما هي العوامل التي تؤثر على استقرار الوزن وكيف يمكن التغلب على هذه المشكلة خلال عملية فقدان الوزن؟ | K978: استقرار الوزن يحدث عندما يتوقف الوزن عن التغيير رغم الالتزام بالنظام الغذائي. من العوامل التي تؤثر على ذلك هي فقدان الكتلة العضلية، حيث أن العضلات تلعب دوراً مهماً في حرق السعرات الحرارية. عندما يفقد الجسم الجلايكوجين، يتم إطلاق الماء، مما قد يؤدي إلى زيادة الوزن. للتغلب على هذه المشكلة، يجب مراجعة العادات الغذائية والسجلات الخاصة بالمريض، والتأكد من عدم تخفيف القواعد المتبعة. يمكن زيادة مستوى النشاط البدني، مثل ممارسة الرياضة الهوائية المعتدلة، أو تغيير نمط الرياضة لزيادة الكتلة العضلية. كما يجب تعديل النظام الغذائي ليتناسب مع الوزن الجديد، مع التأكيد على أهمية الحفاظ على الوزن الجديد وتجنب الانتكاسات. | L978: Confirmed (title match) | M978: Batch output file | N978: N | O978: N | P978: N | Q978: Y
A979: QA-0978 | B979: 321 | C979: Rrja55i3SW0 | D979: https://www.youtube.com/watch?v=Rrja55i3SW0&list=PL90W1ZUHSNiQiI1BVLP5GuIXxf6hr9Rln&index=18 | E979: التعامل مع الحالات في العيادة | F979: د. محمود ثابت | G979: دايت بدون حرمان | H979: https://youtube.com/playlist?list=PL90W1ZUHSNiQiI1BVLP5GuIXxf6hr9Rln&si=G_UimDsDy12ttC7G | I979: 23 | J979: كيف يمكن للأخصائي التغذية تحديد الأهداف العلاجية المناسبة للمريض، وما هي المعايير التي يجب مراعاتها لضمان تحقيق هذه الأهداف؟ | K979: لتحديد الأهداف العلاجية المناسبة، يجب على الأخصائي التغذية استخدام طريقة SMART، حيث يجب أن تكون الأهداف محددة، قابلة للقياس، قابلة للتحقيق، واقعية، ومحددة زمنياً. يجب أن يتضمن ذلك تحديد الوزن المستهدف، مثل فقدان 10 كيلوغرامات في فترة معينة، مع التأكد من أن هذه الأهداف تتناسب مع الحالة الصحية للمريض. يجب أيضاً مراعاة العوامل النفسية والاجتماعية، مثل مدى تقبل المريض للنظام الغذائي، والظروف الاقتصادية والاجتماعية التي قد تؤثر على التزامه. من المهم أن يوافق المريض على الأهداف المحددة، وأن يتم تقديم الدعم النفسي له خلال العملية لتحقيق النجاح. | L979: Confirmed (title match) | M979: Batch output file | N979: N | O979: N | P979: N | Q979: Y
A980: QA-0979 | B980: 321 | C980: Rrja55i3SW0 | D980: https://www.youtube.com/watch?v=Rrja55i3SW0&list=PL90W1ZUHSNiQiI1BVLP5GuIXxf6hr9Rln&index=18 | E980: التعامل مع الحالات في العيادة | F980: د. محمود ثابت | G980: دايت بدون حرمان | H980: https://youtube.com/playlist?list=PL90W1ZUHSNiQiI1BVLP5GuIXxf6hr9Rln&si=G_UimDsDy12ttC7G | I980: 23 | J980: ما هي أهمية التحفيز المستمر والدعم النفسي في عملية تعديل السلوك الغذائي، وكيف يمكن للأخصائي التغذية تطبيق ذلك؟ | K980: التحفيز المستمر والدعم النفسي يعتبران جزءاً أساسياً من تعديل السلوك الغذائي، حيث يساعدان المريض على الشعور بالأمان والدعم خلال رحلته. يمكن للأخصائي التغذية تطبيق ذلك من خلال تقديم نصائح إيجابية، والاستماع لمشاعر المريض دون حكم، وتجنب اللوم عند حدوث تقصير. يجب أن يتم توضيح أن الأخطاء جزء من العملية، وأن هناك دائماً حلول. من خلال عرض نماذج إيجابية وتقديم الدعم، يمكن للأخصائي تعزيز الالتزام وتحفيز المريض على تحقيق أهدافه. كما يجب أن يتم توجيه المريض نحو كيفية التعامل مع العقبات والمشكلات التي قد تواجهه، مما يسهل عليه تجاوزها. | L980: Confirmed (title match) | M980: Batch output file | N980: N | O980: N | P980: N | Q980: Y
A981: QA-0980 | B981: 321 | C981: Rrja55i3SW0 | D981: https://www.youtube.com/watch?v=Rrja55i3SW0&list=PL90W1ZUHSNiQiI1BVLP5GuIXxf6hr9Rln&index=18 | E981: التعامل مع الحالات في العيادة | F981: د. محمود ثابت | G981: دايت بدون حرمان | H981: https://youtube.com/playlist?list=PL90W1ZUHSNiQiI1BVLP5GuIXxf6hr9Rln&si=G_UimDsDy12ttC7G | I981: 23 | J981: كيف يتم استخدام التحاليل الطبية في تقييم الحالة الغذائية للمريض، وما هي التحاليل الأساسية التي يجب إجراؤها؟ | K981: التحاليل الطبية تلعب دوراً مهماً في تقييم الحالة الغذائية، حيث تساعد في فهم مدى صحة الجسم وقدرته على التمثيل الغذائي. من التحاليل الأساسية التي يجب إجراؤها تشمل صورة الدم الكاملة، تحليل السكر التراكمي، تحليل البول، وتحليل البراز. هذه التحاليل تعطي انطباعاً عن مكونات الدم، وظائف الكلى، وطريقة الهضم. بناءً على نتائج هذه التحاليل، يمكن تحديد ما إذا كان المريض يعاني من سوء التغذية أو أي مشاكل صحية أخرى. كما يمكن استخدام التحاليل لتحديد الحاجة إلى تحاليل إضافية حسب الحالة المرضية، مثل تحاليل وظائف الكبد أو الغدة الدرقية، مما يساعد في وضع خطة غذائية مناسبة. | L981: Confirmed (title match) | M981: Batch output file | N981: N | O981: N | P981: N | Q981: Y
A982: QA-0981 | B982: 322 | C982: lCZ3v5mFbrk | D982: https://www.youtube.com/watch?v=lCZ3v5mFbrk&list=PL90W1ZUHSNiQiI1BVLP5GuIXxf6hr9Rln&index=19 | E982: التغذية المعوية و الوريدية .... متي يتم استخدامها - الحسابات - المشاكل و كيفية الحل | F982: د. محمود ثابت | G982: دايت بدون حرمان | H982: https://youtube.com/playlist?list=PL90W1ZUHSNiQiI1BVLP5GuIXxf6hr9Rln&si=G_UimDsDy12ttC7G | I982: 23 | J982: ما هي الحالات التي تستدعي استخدام التغذية المعوية أو الوريدية، وما الفرق بينهما من حيث طريقة الإيصال والاحتياجات الغذائية؟ | K982: تستدعي استخدام التغذية المعوية في حالات عدم قدرة المريض على تناول الطعام عن طريق الفم بسبب مشاكل في الجهاز الهضمي، مثل ضعف الهضم أو صعوبة البلع. يتم إيصال التغذية المعوية عبر أنبوب يتم تركيبه إما عن طريق الفم أو الأنف إلى المعدة أو الأمعاء. أما التغذية الوريدية، فتستخدم في حالات فشل الجهاز الهضمي الكامل أو عندما لا يمكن استخدام الجهاز الهضمي، مثل حالات الانسداد المعوي أو الغيبوبة. يتم إيصال التغذية الوريدية مباشرة إلى مجرى الدم عبر قسطرة، مما يتطلب تركيبات غذائية دقيقة تحتوي على الجلوكوز، البروتينات، والدهون، بالإضافة إلى الفيتامينات والمعادن. | L982: Confirmed (title match) | M982: Batch output file | N982: N | O982: N | P982: N | Q982: Y
A983: QA-0982 | B983: 322 | C983: lCZ3v5mFbrk | D983: https://www.youtube.com/watch?v=lCZ3v5mFbrk&list=PL90W1ZUHSNiQiI1BVLP5GuIXxf6hr9Rln&index=19 | E983: التغذية المعوية و الوريدية .... متي يتم استخدامها - الحسابات - المشاكل و كيفية الحل | F983: د. محمود ثابت | G983: دايت بدون حرمان | H983: https://youtube.com/playlist?list=PL90W1ZUHSNiQiI1BVLP5GuIXxf6hr9Rln&si=G_UimDsDy12ttC7G | I983: 23 | J983: ما هي المخاطر والمضاعفات المحتملة المرتبطة بالتغذية المعوية، وكيف يمكن تجنبها؟ | K983: تشمل المخاطر المرتبطة بالتغذية المعوية احتمال دخول التغذية إلى الجهاز التنفسي مما يؤدي إلى التهاب رئوي، بالإضافة إلى انسداد الأنبوب أو هجرته. لتجنب هذه المضاعفات، يجب التأكد من تركيب الأنبوب بشكل صحيح ومراقبة تدفق التغذية بعناية. كما يجب الحفاظ على نظافة الفم والأنبوب لتقليل خطر العدوى. في حالة وجود أي علامات على صعوبة في البلع أو ارتجاع، يجب تعديل طريقة الإيصال أو استخدام التغذية الوريدية بدلاً من المعوية. | L983: Confirmed (title match) | M983: Batch output file | N983: N | O983: N | P983: N | Q983: Y
A984: QA-0983 | B984: 322 | C984: lCZ3v5mFbrk | D984: https://www.youtube.com/watch?v=lCZ3v5mFbrk&list=PL90W1ZUHSNiQiI1BVLP5GuIXxf6hr9Rln&index=19 | E984: التغذية المعوية و الوريدية .... متي يتم استخدامها - الحسابات - المشاكل و كيفية الحل | F984: د. محمود ثابت | G984: دايت بدون حرمان | H984: https://youtube.com/playlist?list=PL90W1ZUHSNiQiI1BVLP5GuIXxf6hr9Rln&si=G_UimDsDy12ttC7G | I984: 23 | J984: كيف يتم تحديد الاحتياجات الغذائية للمريض عند استخدام التغذية الوريدية، وما العوامل التي تؤثر على هذه الاحتياجات؟ | K984: تحديد الاحتياجات الغذائية للمريض عند استخدام التغذية الوريدية يعتمد على عدة عوامل، منها وزن المريض، حالته الصحية، مستوى النشاط، ونوع المرض. يتم حساب السعرات الحرارية المطلوبة باستخدام معادلات قياسية مثل معادلة هاريس بنديكت. كما يجب مراعاة أي حالات طبية خاصة مثل الفشل الكلوي أو الكبدي، حيث تتطلب تعديل نسب البروتين والسوائل. بالإضافة إلى ذلك، يجب مراقبة مستويات الإلكتروليتات والفيتامينات في الدم لضمان تلبية احتياجات الجسم بشكل متوازن. | L984: Confirmed (title match) | M984: Batch output file | N984: N | O984: N | P984: N | Q984: Y
A985: QA-0984 | B985: 322 | C985: lCZ3v5mFbrk | D985: https://www.youtube.com/watch?v=lCZ3v5mFbrk&list=PL90W1ZUHSNiQiI1BVLP5GuIXxf6hr9Rln&index=19 | E985: التغذية المعوية و الوريدية .... متي يتم استخدامها - الحسابات - المشاكل و كيفية الحل | F985: د. محمود ثابت | G985: دايت بدون حرمان | H985: https://youtube.com/playlist?list=PL90W1ZUHSNiQiI1BVLP5GuIXxf6hr9Rln&si=G_UimDsDy12ttC7G | I985: 23 | J985: ما هي متلازمة إعادة التغذية، وما الأعراض التي قد تظهر نتيجة لها؟ | K985: متلازمة إعادة التغذية تحدث عندما يتم استئناف التغذية بعد فترة طويلة من الحرمان، مما يؤدي إلى اضطراب في كيمياء الجسم. الأعراض تشمل ضعف العضلات، صعوبة في التنفس، دوخة، عدم تركيز، ونوبات من التشنجات. كما قد تظهر مشاكل في القلب نتيجة نقص الإلكتروليتات مثل البوتاسيوم والمغنيزيوم. لذلك، يجب مراقبة مستويات الإلكتروليتات بعناية عند إعادة التغذية وتقديم الدعم الغذائي بشكل تدريجي. | L985: Confirmed (title match) | M985: Batch output file | N985: N | O985: N | P985: N | Q985: Y
A986: QA-0985 | B986: 322 | C986: lCZ3v5mFbrk | D986: https://www.youtube.com/watch?v=lCZ3v5mFbrk&list=PL90W1ZUHSNiQiI1BVLP5GuIXxf6hr9Rln&index=19 | E986: التغذية المعوية و الوريدية .... متي يتم استخدامها - الحسابات - المشاكل و كيفية الحل | F986: د. محمود ثابت | G986: دايت بدون حرمان | H986: https://youtube.com/playlist?list=PL90W1ZUHSNiQiI1BVLP5GuIXxf6hr9Rln&si=G_UimDsDy12ttC7G | I986: 23 | J986: ما هي التركيبات المختلفة للتغذية المعوية، وكيف يتم اختيار التركيبة المناسبة لكل مريض؟ | K986: تتضمن التركيبات المختلفة للتغذية المعوية التركيبات القياسية، التركيبات شبه العنصرية، والتركيبات المتخصصة. يتم اختيار التركيبة المناسبة بناءً على حالة الجهاز الهضمي للمريض، احتياجاته الغذائية، والخصائص الفيزيائية للتركيبة مثل محتوى الألياف والسعرات الحرارية. يجب أن تكون التركيبة متوازنة وتلبي احتياجات المريض من المغذيات الكبرى والصغرى، مع مراعاة أي قيود صحية أو حالات طبية خاصة قد تؤثر على الهضم والامتصاص. | L986: Confirmed (title match) | M986: Batch output file | N986: N | O986: N | P986: N | Q986: Y
A987: QA-0986 | B987: 323 | C987: -GjI8b0jDdw | D987: https://www.youtube.com/watch?v=-GjI8b0jDdw&list=PL90W1ZUHSNiQiI1BVLP5GuIXxf6hr9Rln&index=20 | E987: تغذية مرض التصلب اللويحي | F987: د. محمود ثابت | G987: دايت بدون حرمان | H987: https://youtube.com/playlist?list=PL90W1ZUHSNiQiI1BVLP5GuIXxf6hr9Rln&si=G_UimDsDy12ttC7G | I987: 24 | J987: ما هي العلاقة بين النظام الغذائي لمرضى التصلب اللويحي المتعدد وتقليل عدد مرات الانتكاسات والأعراض المرافقة للمرض؟ | K987: أثبتت الدراسات أن النظام الغذائي يلعب دوراً هاماً في تقليل عدد مرات الانتكاسات وخطر الإصابة بمضاعفات مرضية نتيجة للتصلب اللويحي المتعدد. حيث أن اتباع نظام غذائي صحي يعزز من صحة الجهاز المناعي ويقلل من شدة الأعراض المرافقة للمرض. على سبيل المثال، أظهرت دراسة أجريت على 7000 شخص مصاب بالتصلب المتعدد أن النظام الغذائي الصحي قلل الاكتئاب بنسبة 50% والتعب والإرهاق بنسبة 30%، كما قلل الألم بنسبة 40% مقارنةً بالأشخاص الذين اتبعوا نظاماً غذائياً غير صحي. | L987: Confirmed (title match) | M987: Batch output file | N987: N | O987: N | P987: N | Q987: N
A988: QA-0987 | B988: 323 | C988: -GjI8b0jDdw | D988: https://www.youtube.com/watch?v=-GjI8b0jDdw&list=PL90W1ZUHSNiQiI1BVLP5GuIXxf6hr9Rln&index=20 | E988: تغذية مرض التصلب اللويحي | F988: د. محمود ثابت | G988: دايت بدون حرمان | H988: https://youtube.com/playlist?list=PL90W1ZUHSNiQiI1BVLP5GuIXxf6hr9Rln&si=G_UimDsDy12ttC7G | I988: 24 | J988: كيف يؤثر تناول الأطعمة الغنية بالبروبيوتيك والبريبايوتكس على صحة مرضى التصلب اللويحي المتعدد؟ | K988: تناول الأطعمة الغنية بالبروبيوتيك والبريبايوتكس يعزز من أعداد البكتيريا النافعة في الجهاز الهضمي، مما يساعد في تحسين صحة الجهاز المناعي. هذه الأطعمة، مثل اللبن الزبادي والثوم والبصل، تساهم في تقليل التطورات السلبية للمرض، خاصة تلك المتعلقة بالدماغ والنخاع الشوكي. الدراسات تشير إلى أن إدخال هذه الأطعمة في النظام الغذائي يمكن أن يؤدي إلى نتائج أفضل في إدارة الأعراض وتحسين جودة الحياة للمرضى. | L988: Confirmed (title match) | M988: Batch output file | N988: N | O988: N | P988: N | Q988: N
... A1006: QA-1005 | B1006: 326 | C1006: 6IFV3i7UcjU | D1006: https://www.youtube.com/watch?v=6IFV3i7UcjU&list=PL90W1ZUHSNiQiI1BVLP5GuIXxf6hr9Rln&index=23 | E1006: تغذية اطفال متلازمة داون | F1006: د. محمود ثابت | G1006: دايت بدون حرمان | H1006: https://youtube.com/playlist?list=PL90W1ZUHSNiQiI1BVLP5GuIXxf6hr9Rln&si=G_UimDsDy12ttC7G | I1006: 24 | J1006: ما هي العلاقة بين السمنة ومرض السكري من النوع الأول لدى أطفال متلازمة داون، وكيف يمكن إدارة هذه الحالة بشكل فعال؟ | K1006: السمنة ومرض السكري من النوع الأول مرتبطان بشكل وثيق لدى أطفال متلازمة داون، حيث أن زيادة الوزن قد تؤدي إلى تفاقم أعراض السكري. لإدارة هذه الحالة بشكل فعال، يجب اتباع نظام غذائي متوازن يحتوي على سعرات حرارية محسوبة، مع التركيز على الأطعمة الصحية مثل الفواكه والخضروات والحبوب الكاملة. بالإضافة إلى ذلك، يجب ممارسة النشاط البدني بانتظام، ومراقبة مستويات السكر في الدم لضمان السيطرة على الحالة. | L1006: Confirmed (title match) | M1006: Batch output file | N1006: N | O1006: N | P1006: N | Q1006: N
A1007: QA-1006 | B1007: 327 | C1007: 3wdgQZOFgO8 | D1007: https://www.youtube.com/watch?v=3wdgQZOFgO8&list=PL90W1ZUHSNiQiI1BVLP5GuIXxf6hr9Rln&index=24 | E1007: تغذية مريض الانيميا - المشكلة و الحل | F1007: د. محمود ثابت | G1007: دايت بدون حرمان | H1007: https://youtube.com/playlist?list=PL90W1ZUHSNiQiI1BVLP5GuIXxf6hr9Rln&si=G_UimDsDy12ttC7G | I1007: 24 | J1007: ما هي الأسباب المختلفة لفقر الدم وكيف يمكن تصنيفها بناءً على العوامل المسببة لها؟ | K1007: فقر الدم يمكن تصنيفه إلى عدة أنواع بناءً على الأسباب المسببة له. من أبرز هذه الأنواع: 1. **فقر الدم الناتج عن نقص الحديد**: يحدث بسبب نقص الحديد في النظام الغذائي، مما يؤثر على قدرة نخاع العظام على إنتاج الهيموجلوبين. 2. **فقر الدم الناتج عن نقص الفيتامينات**: يتطلب الجسم الفيتامينات مثل الفوليك أسيد وفيتامين ب12 لإنتاج خلايا دم حمراء سليمة. 3. **فقر الدم الناتج عن الأمراض المزمنة**: مثل السرطان أو التهاب المفاصل الروماتويدي، حيث تؤدي هذه الأمراض إلى نقص إنتاج كرات الدم الحمراء. 4. **فقر الدم الانحلالي**: يحدث عندما يتم تدمير خلايا الدم الحمراء بمعدل أسرع من قدرة نخاع العظام على إنتاجها. 5. **فقر الدم المرتبط بنخاع العظام**: مثل اللوكيميا، حيث يفشل نخاع العظام في إنتاج كميات كافية من كرات الدم الحمراء. | L1007: Confirmed (title match) | M1007: Batch output file | N1007: Y | O1007: Y | P1007: N | Q1007: N | R1007: title listed more than once; chosen by batch range
A1008: QA-1007 | B1008: 327 | C1008: 3wdgQZOFgO8 | D1008: https://www.youtube.com/watch?v=3wdgQZOFgO8&list=PL90W1ZUHSNiQiI1BVLP5GuIXxf6hr9Rln&index=24 | E1008: تغذية مريض الانيميا - المشكلة و الحل | F1008: د. محمود ثابت | G1008: دايت بدون حرمان | H1008: https://youtube.com/playlist?list=PL90W1ZUHSNiQiI1BVLP5GuIXxf6hr9Rln&si=G_UimDsDy12ttC7G | I1008: 24 | J1008: كيف يؤثر نقص الحديد على النساء الحوامل وما هي الاحتياجات الغذائية الخاصة بهن خلال فترة الحمل؟ | K1008: نقص الحديد يؤثر بشكل كبير على النساء الحوامل، حيث يمكن أن يؤدي إلى ولادة مبكرة أو انخفاض وزن الطفل عند الولادة. خلال فترة الحمل، تحتاج المرأة إلى 27 ملغرام من الحديد يومياً لتعويض الدم المفقود خلال فترة النفاس ولتلبية احتياجات الجنين المتزايدة. بالإضافة إلى الحديد، تحتاج الحوامل أيضاً إلى الفوليك أسيد وفيتامين ب12 لضمان نمو صحي للجنين. يجب أن يكون النظام الغذائي متوازناً وغنياً بالأطعمة التي تحتوي على الحديد والفيتامينات الضرورية. | L1008: Confirmed (title match) | M1008: Batch output file | N1008: Y | O1008: N | P1008: N | Q1008: N | R1008: title listed more than once; chosen by batch range
A1009: QA-1008 | B1009: 327 | C1009: 3wdgQZOFgO8 | D1009: https://www.youtube.com/watch?v=3wdgQZOFgO8&list=PL90W1ZUHSNiQiI1BVLP5GuIXxf6hr9Rln&index=24 | E1009: تغذية مريض الانيميا - المشكلة و الحل | F1009: د. محمود ثابت | G1009: دايت بدون حرمان | H1009: https://youtube.com/playlist?list=PL90W1ZUHSNiQiI1BVLP5GuIXxf6hr9Rln&si=G_UimDsDy12ttC7G | I1009: 24 | J1009: ما هي العلامات والأعراض التي تشير إلى وجود فقر الدم، وكيف يمكن أن تؤثر على حياة الشخص اليومية؟ | K1009: علامات فقر الدم تشمل: 1. **التعب الشديد**: مما يؤثر على القدرة على العمل والقيام بالأنشطة اليومية. 2. **ضيق التنفس**: خاصة أثناء ممارسة الرياضة أو الأنشطة البدنية. 3. **الدوخة والدوار**: نتيجة نقص الأكسجين الواصل إلى المخ. 4. **شحوب البشرة**: حيث يصبح لون الجلد شاحباً، مما يدل على نقص كرات الدم الحمراء. 5. **سرعة ضربات القلب**: نتيجة محاولة الجسم تعويض نقص الأكسجين. هذه الأعراض يمكن أن تؤثر بشكل كبير على جودة الحياة، حيث يعاني الشخص من ضعف في التركيز والنشاط. | L1009: Confirmed (title match) | M1009: Batch output file | N1009: Y | O1009: N | P1009: N | Q1009: N | R1009: title listed more than once; chosen by batch range
A1010: QA-1009 | B1010: 327 | C1010: 3wdgQZOFgO8 | D1010: https://www.youtube.com/watch?v=3wdgQZOFgO8&list=PL90W1ZUHSNiQiI1BVLP5GuIXxf6hr9Rln&index=24 | E1010: تغذية مريض الانيميا - المشكلة و الحل | F1010: د. محمود ثابت | G1010: دايت بدون حرمان | H1010: https://youtube.com/playlist?list=PL90W1ZUHSNiQiI1BVLP5GuIXxf6hr9Rln&si=G_UimDsDy12ttC7G | I1010: 24 | J1010: كيف يمكن تحسين امتصاص الحديد في النظام الغذائي، وما هي الأطعمة التي يجب تجنبها لتحقيق ذلك؟ | K1010: لتحسين امتصاص الحديد في النظام الغذائي، يجب تناول الأطعمة الغنية بالحديد مع الأطعمة التي تحتوي على فيتامين سي، مثل الحمضيات والفلفل الأحمر. من المهم أيضاً تجنب تناول الشاي والقهوة والمشروبات التي تحتوي على الكالسيوم في نفس الوقت مع الأطعمة الغنية بالحديد، حيث أن هذه المشروبات تقلل من امتصاص الحديد. الأطعمة التي تحتوي على الأوكزاليت، مثل الشوكولاتة والبقدونس، يجب تناولها بحذر لأنها قد تعيق امتصاص الحديد. يجب أن يكون هناك فاصل زمني بين تناول الحديد وهذه الأطعمة لتحقيق أفضل امتصاص. | L1010: Confirmed (title match) | M1010: Batch output file | N1010: Y | O1010: Y | P1010: N | Q1010: N | R1010: title listed more than once; chosen by batch range
A1011: QA-1010 | B1011: 327 | C1011: 3wdgQZOFgO8 | D1011: https://www.youtube.com/watch?v=3wdgQZOFgO8&list=PL90W1ZUHSNiQiI1BVLP5GuIXxf6hr9Rln&index=24 | E1011: تغذية مريض الانيميا - المشكلة و الحل | F1011: د. محمود ثابت | G1011: دايت بدون حرمان | H1011: https://youtube.com/playlist?list=PL90W1ZUHSNiQiI1BVLP5GuIXxf6hr9Rln&si=G_UimDsDy12ttC7G | I1011: 24 | J1011: ما هي الاحتياجات اليومية من الحديد حسب الفئات العمرية المختلفة، وكيف تختلف بين الرجال والنساء؟ | K1011: الاحتياجات اليومية من الحديد تختلف حسب الفئة العمرية والجنس: 1. **الأطفال من 7 إلى 12 شهراً**: 11 ملغرام. 2. **الأطفال من سنة إلى 3 سنوات**: 7 ملغرام. 3. **الأطفال من 4 إلى 8 سنوات**: 10 ملغرام. 4. **الأطفال من 9 إلى 13 سنة**: 8 ملغرام. 5. **المراهقون**: 11 ملغرام للأولاد و15 ملغرام للبنات بسبب بدء الدورة الشهرية. 6. **الرجال من 19 إلى 50 سنة**: 8 ملغرام. 7. **النساء فوق 51 سنة**: 8 ملغرام. 8. **النساء الحوامل**: 27 ملغرام. هذه الاختلافات تعكس احتياجات الجسم المتزايدة للحديد في مراحل معينة مثل الحمل أو فترة النمو. | L1011: Confirmed (title match) | M1011: Batch output file | N1011: Y | O1011: N | P1011: N | Q1011: N | R1011: title listed more than once; chosen by batch range
A1012: QA-1011 | B1012: 328 | C1012: OYwJ-anracI | D1012: https://www.youtube.com/watch?v=OYwJ-anracI&list=PL90W1ZUHSNiQiI1BVLP5GuIXxf6hr9Rln&index=25 | E1012: تغذية مرضي الفيبروميالجيا | F1012: د. محمود ثابت | G1012: دايت بدون حرمان | H1012: https://youtube.com/playlist?list=PL90W1ZUHSNiQiI1BVLP5GuIXxf6hr9Rln&si=G_UimDsDy12ttC7G | I1012: 24 | J1012: ما هي العوامل التي تؤدي إلى زيادة حساسية الجسم للألم في مرض الفايبرو ماليجيا، وكيف تؤثر هذه العوامل على الحالة النفسية للمريض؟ | K1012: تتعدد العوامل التي تؤدي إلى زيادة حساسية الجسم للألم في مرض الفايبرو ماليجيا، ومن أبرزها التغيرات في الدماغ والحبل الشوكي، حيث تترجم هذه التغيرات الإشارات الطبيعية للألم إلى إشارات حادة. كما أن هناك عوامل وراثية تلعب دورًا في زيادة خطر الإصابة، بالإضافة إلى حالات العدوى والإجهاد النفسي الشديد. هذه العوامل تؤدي إلى شعور المريض بالألم المستمر، مما ينعكس سلبًا على حالته النفسية، حيث يعاني من الاكتئاب والقلق، مما يزيد من حدة الأعراض ويجعل التعامل مع المرض أكثر صعوبة. | L1012: Confirmed (title match) | M1012: Batch output file | N1012: N | O1012: N | P1012: N | Q1012: N
A1013: QA-1012 | B1013: 328 | C1013: OYwJ-anracI | D1013: https://www.youtube.com/watch?v=OYwJ-anracI&list=PL90W1ZUHSNiQiI1BVLP5GuIXxf6hr9Rln&index=25 | E1013: تغذية مرضي الفيبروميالجيا | F1013: د. محمود ثابت | G1013: دايت بدون حرمان | H1013: https://youtube.com/playlist?list=PL90W1ZUHSNiQiI1BVLP5GuIXxf6hr9Rln&si=G_UimDsDy12ttC7G | I1013: 24 | J1013: كيف يمكن أن يؤثر تغيير نمط الحياة والسلوكيات الغذائية على تحسين حالة مرضى الفايبرو ماليجيا، وما هي النصائح العامة التي يمكن اتباعها لتحقيق ذلك؟ | K1013: تغيير نمط الحياة والسلوكيات الغذائية يمكن أن يؤثر بشكل إيجابي على تحسين حالة مرضى الفايبرو ماليجيا من خلال تقليل التوتر والألم. من النصائح العامة التي يمكن اتباعها: ممارسة الرياضة الخفيفة وتمارين الاسترخاء، الابتعاد عن مصادر الضغط النفسي، تناول نظام غذائي صحي متوازن يشمل الخضروات والفواكه والحبوب الكاملة، وتقليل تناول السكريات والملح. كما يُنصح بتقسيم الوجبات على مدار اليوم للحفاظ على مستويات طاقة ثابتة، والابتعاد عن الأطعمة التي تسبب زيادة الالتهابات مثل الوجبات السريعة واللحوم المصنعة. | L1013: Confirmed (title match) | M1013: Batch output file | N1013: N | O1013: N | P1013: N | Q1013: N
A1014: QA-1013 | B1014: 328 | C1014: OYwJ-anracI | D1014: https://www.youtube.com/watch?v=OYwJ-anracI&list=PL90W1ZUHSNiQiI1BVLP5GuIXxf6hr9Rln&index=25 | E1014: تغذية مرضي الفيبروميالجيا | F1014: د. محمود ثابت | G1014: دايت بدون حرمان | H1014: https://youtube.com/playlist?list=PL90W1ZUHSNiQiI1BVLP5GuIXxf6hr9Rln&si=G_UimDsDy12ttC7G | I1014: 24 | J1014: ما هي العلاقة بين الفايبرو ماليجيا والتغيرات الهرمونية لدى النساء، وكيف تؤثر هذه التغيرات على أعراض المرض؟ | K1014: تظهر العلاقة بين الفايبرو ماليجيا والتغيرات الهرمونية لدى النساء بشكل واضح، حيث تؤثر التغيرات الهرمونية خلال الدورة الشهرية، فترة الحمل، وانقطاع الطمث على حساسية الجسم للألم. انخفاض مستوى هرمون الاستروجين، على سبيل المثال، يزيد من حساسية الألم ويؤدي إلى تفاقم الأعراض. كما أن التغيرات الهرمونية تؤثر على الحالة النفسية، مما يجعل النساء أكثر عرضة للاكتئاب والقلق، وبالتالي يزيد من حدة الأعراض المرتبطة بالفايبرو ماليجيا. | L1014: Confirmed (title match) | M1014: Batch output file | N1014: N | O1014: N | P1014: N | Q1014: N
A1015: QA-1014 | B1015: 328 | C1015: OYwJ-anracI | D1015: https://www.youtube.com/watch?v=OYwJ-anracI&list=PL90W1ZUHSNiQiI1BVLP5GuIXxf6hr9Rln&index=25 | E1015: تغذية مرضي الفيبروميالجيا | F1015: د. محمود ثابت | G1015: دايت بدون حرمان | H1015: https://youtube.com/playlist?list=PL90W1ZUHSNiQiI1BVLP5GuIXxf6hr9Rln&si=G_UimDsDy12ttC7G | I1015: 24 | J1015: كيف يمكن أن تؤثر العوامل النفسية والاجتماعية على تطور مرض الفايبرو ماليجيا، وما هي الاستراتيجيات التي يمكن استخدامها للتعامل مع هذه العوامل؟ | K1015: تؤثر العوامل النفسية والاجتماعية بشكل كبير على تطور مرض الفايبرو ماليجيا، حيث أن الضغوط النفسية والحزن يمكن أن تؤدي إلى تفاقم الأعراض. الاستراتيجيات التي يمكن استخدامها للتعامل مع هذه العوامل تشمل ممارسة تمارين الاسترخاء، الانخراط في أنشطة اجتماعية، وتغيير نمط الحياة لتقليل التوتر. كما يُنصح بالبحث عن الدعم النفسي من الأصدقاء والعائلة، والمشاركة في مجموعات دعم لمشاركة التجارب والخبرات، مما يساعد على تحسين الحالة النفسية ويقلل من حدة الأعراض. | L1015: Confirmed (title match) | M1015: Batch output file | N1015: N | O1015: N | P1015: N | Q1015: N
A1016: QA-1015 | B1016: 328 | C1016: OYwJ-anracI | D1016: https://www.youtube.com/watch?v=OYwJ-anracI&list=PL90W1ZUHSNiQiI1BVLP5GuIXxf6hr9Rln&index=25 | E1016: تغذية مرضي الفيبروميالجيا | F1016: د. محمود ثابت | G1016: دايت بدون حرمان | H1016: https://youtube.com/playlist?list=PL90W1ZUHSNiQiI1BVLP5GuIXxf6hr9Rln&si=G_UimDsDy12ttC7G | I1016: 24 | J1016: ما هي الأطعمة التي يجب تجنبها في النظام الغذائي لمرضى الفايبرو ماليجيا، وكيف تؤثر هذه الأطعمة على الأعراض؟ | K1016: يجب على مرضى الفايبرو ماليجيا تجنب الأطعمة التي قد تزيد من الالتهابات أو تسبب تفاقم الأعراض، مثل الوجبات السريعة، اللحوم المصنعة، الأطعمة الغنية بالسكريات والدهون المشبعة، والملونات الصناعية. هذه الأطعمة تؤدي إلى زيادة الالتهابات في الجسم، مما يزيد من حدة الألم والتعب. من المهم التركيز على تناول الأطعمة الصحية مثل الخضروات والفواكه والحبوب الكاملة، حيث تساعد هذه الأطعمة في تحسين الحالة العامة وتقليل الأعراض. | L1016: Confirmed (title match) | M1016: Batch output file | N1016: N | O1016: N | P1016: N | Q1016: N
A1017: QA-1016 | B1017: 329 | C1017: tKiduJLqJ2g | D1017: https://www.youtube.com/watch?v=tKiduJLqJ2g&list=PL90W1ZUHSNiQiI1BVLP5GuIXxf6hr9Rln&index=26 | E1017: غذية مرضى السكري النوع 1 و 2 | حساب الكارب و جرعات الإنسولين بالتفصيل + تطبيق عملي! | F1017: د. محمود ثابت | G1017: دايت بدون حرمان | H1017: https://youtube.com/playlist?list=PL90W1ZUHSNiQiI1BVLP5GuIXxf6hr9Rln&si=G_UimDsDy12ttC7G | I1017: 24 | J1017: ما هو الفرق بين المؤشر الجلايسيمي والحمل الجلايسيمي، وكيف يؤثر كل منهما على مستويات السكر في الدم لمريض السكر؟ | K1017: المؤشر الجلايسيمي هو نظام تصنيف للأطعمة التي تحتوي على كربوهيدرات، حيث يقيس سرعة تحلل الكربوهيدرات ومدى تأثيرها على مستوى الجلوكوز في الدم مقارنةً بنفس الكمية من الجلوكوز النقي. بينما الحمل الجلايسيمي يعبر عن مقدار الزيادة في مستوى الجلوكوز في الدم نتيجة تناول كمية معينة من الطعام. إذا كان المؤشر الجلايسيمي مرتفعًا، فهذا يعني أن الطعام يتحلل بسرعة ويرفع مستوى السكر في الدم بشكل سريع، مما يؤدي إلى إفراز الأنسولين بشكل كبير. أما الحمل الجلايسيمي، فيعطي فكرة عن مقدار التغيير في مستوى الجلوكوز في الدم بناءً على كمية الطعام المتناولة، مما يساعد في تحديد مدى ملاءمة الطعام لمريض السكر. | L1017: Confirmed (title match) | M1017: Batch output file | N1017: N | O1017: N | P1017: N | Q1017: Y
A1018: QA-1017 | B1018: 329 | C1018: tKiduJLqJ2g | D1018: https://www.youtube.com/watch?v=tKiduJLqJ2g&list=PL90W1ZUHSNiQiI1BVLP5GuIXxf6hr9Rln&index=26 | E1018: غذية مرضى السكري النوع 1 و 2 | حساب الكارب و جرعات الإنسولين بالتفصيل + تطبيق عملي! | F1018: د. محمود ثابت | G1018: دايت بدون حرمان | H1018: https://youtube.com/playlist?list=PL90W1ZUHSNiQiI1BVLP5GuIXxf6hr9Rln&si=G_UimDsDy12ttC7G | I1018: 24 | J1018: كيف يمكن لمريض السكر اختيار الأطعمة المناسبة بناءً على المؤشر الجلايسيمي والحمل الجلايسيمي، وما هي العوامل التي يجب مراعاتها عند اتخاذ هذا القرار؟ | K1018: عند اختيار الأطعمة، يجب على مريض السكر مراعاة المؤشر الجلايسيمي والحمل الجلايسيمي للأطعمة. الأطعمة ذات المؤشر الجلايسيمي المنخفض (أقل من 55) تعتبر مناسبة، حيث تساعد في الحفاظ على مستويات السكر في الدم مستقرة. بينما الأطعمة ذات المؤشر الجلايسيمي المرتفع (أكثر من 70) يجب تجنبها لأنها ترفع مستوى السكر بسرعة. يجب أيضًا مراعاة كمية الكربوهيدرات في الطعام، حيث أن الحمل الجلايسيمي يعكس مقدار الزيادة في مستوى السكر بناءً على الكمية المتناولة. لذا، يجب على المريض اختيار الأطعمة التي تحتوي على مؤشر جلايسيمي منخفض وحمل جلايسيمي مقبول، مع الأخذ في الاعتبار احتياجاته الغذائية ونمط حياته. | L1018: Confirmed (title match) | M1018: Batch output file | N1018: N | O1018: N | P1018: N | Q1018: Y
A1019: QA-1018 | B1019: 329 | C1019: tKiduJLqJ2g | D1019: https://www.youtube.com/watch?v=tKiduJLqJ2g&list=PL90W1ZUHSNiQiI1BVLP5GuIXxf6hr9Rln&index=26 | E1019: غذية مرضى السكري النوع 1 و 2 | حساب الكارب و جرعات الإنسولين بالتفصيل + تطبيق عملي! | F1019: د. محمود ثابت | G1019: دايت بدون حرمان | H1019: https://youtube.com/playlist?list=PL90W1ZUHSNiQiI1BVLP5GuIXxf6hr9Rln&si=G_UimDsDy12ttC7G | I1019: 24 | J1019: ما هي أهمية النظام الغذائي المتوازن لمريض السكر، وكيف يمكن أن يؤثر على مستوى السكر في الدم وصحة المريض بشكل عام؟ | K1019: النظام الغذائي المتوازن لمريض السكر مهم جدًا لأنه يساعد في الحفاظ على مستويات السكر في الدم ضمن الحدود الطبيعية، مما يقلل من خطر حدوث مضاعفات مثل غيبوبة السكر أو القدم السكري. من خلال تناول وجبات صحية في أوقات منتظمة، يمكن للمريض تنظيم إفراز الأنسولين وتحسين استجابة الجسم للأنسولين. كما أن النظام الغذائي المتوازن يساهم في الحفاظ على وزن صحي، مما يقلل من الحاجة إلى الأدوية ويقلل من تكاليف العلاج. بالإضافة إلى ذلك، يساعد النظام الغذائي الجيد في تحسين الحالة النفسية للمريض ويعزز من جودة حياته. | L1019: Confirmed (title match) | M1019: Batch output file | N1019: N | O1019: N | P1019: N | Q1019: Y
A1020: QA-1019 | B1020: 329 | C1020: tKiduJLqJ2g | D1020: https://www.youtube.com/watch?v=tKiduJLqJ2g&list=PL90W1ZUHSNiQiI1BVLP5GuIXxf6hr9Rln&index=26 | E1020: غذية مرضى السكري النوع 1 و 2 | حساب الكارب و جرعات الإنسولين بالتفصيل + تطبيق عملي! | F1020: د. محمود ثابت | G1020: دايت بدون حرمان | H1020: https://youtube.com/playlist?list=PL90W1ZUHSNiQiI1BVLP5GuIXxf6hr9Rln&si=G_UimDsDy12ttC7G | I1020: 24 | J1020: كيف يمكن لمريض السكر حساب الكربوهيدرات في نظامه الغذائي، وما هي الخطوات الأساسية التي يجب اتباعها لتحقيق ذلك؟ | K1020: لحساب الكربوهيدرات، يجب على مريض السكر أولاً تحديد احتياجاته اليومية من السعرات الحرارية بناءً على العمر، الوزن، الطول، ومستوى النشاط. بعد ذلك، يتم حساب نسبة الكربوهيدرات المطلوبة، حيث يُفضل أن تكون حوالي 50% من إجمالي السعرات. يتم تحويل السعرات الحرارية إلى جرامات كربوهيدرات (1 جرام كربوهيدرات = 4 سعرات حرارية). بعد ذلك، يجب توزيع الكربوهيدرات على الوجبات الرئيسية والوجبات الخفيفة، مع مراعاة المؤشر الجلايسيمي للأطعمة. يجب أيضًا مراقبة مستويات السكر في الدم بعد الوجبات لضبط الكميات حسب الحاجة. | L1020: Confirmed (title match) | M1020: Batch output file | N1020: N | O1020: N | P1020: N | Q1020: Y
A1021: QA-1020 | B1021: 329 | C1021: tKiduJLqJ2g | D1021: https://www.youtube.com/watch?v=tKiduJLqJ2g&list=PL90W1ZUHSNiQiI1BVLP5GuIXxf6hr9Rln&index=26 | E1021: غذية مرضى السكري النوع 1 و 2 | حساب الكارب و جرعات الإنسولين بالتفصيل + تطبيق عملي! | F1021: د. محمود ثابت | G1021: دايت بدون حرمان | H1021: https://youtube.com/playlist?list=PL90W1ZUHSNiQiI1BVLP5GuIXxf6hr9Rln&si=G_UimDsDy12ttC7G | I1021: 24 | J1021: ما هي العوامل التي تؤثر على اختيار الأطعمة لمريض السكر، وكيف يمكن أن تساعد هذه العوامل في تحسين إدارة المرض؟ | K1021: تؤثر عدة عوامل على اختيار الأطعمة لمريض السكر، منها المؤشر الجلايسيمي، الحمل الجلايسيمي، كمية الكربوهيدرات، واحتياجات المريض الغذائية. يجب على المريض اختيار الأطعمة ذات المؤشر الجلايسيمي المنخفض لتجنب ارتفاع سريع في مستويات السكر. كما يجب مراعاة الكميات المتناولة، حيث أن الحمل الجلايسيمي يساعد في تحديد التأثير الكلي للطعام على مستوى السكر. بالإضافة إلى ذلك، يجب أن يأخذ المريض في اعتباره نمط حياته، مستوى نشاطه، والأدوية التي يتناولها. من خلال مراعاة هذه العوامل، يمكن للمريض تحسين إدارة مرض السكر وتقليل المخاطر المرتبطة به. | L1021: Confirmed (title match) | M1021: Batch output file | N1021: N | O1021: N | P1021: N | Q1021: Y
A1022: QA-1021 | B1022: 330 | C1022: Yij3_j5p8Oo | D1022: https://www.youtube.com/watch?v=Yij3_j5p8Oo&list=PL90W1ZUHSNiQiI1BVLP5GuIXxf6hr9Rln&index=27 | E1022: ادوية السكر: كل ما تحتاج معرفته عن أدوية السكر والأنسولين شرح مبسط للمجموعات، الجرعات و طريقة العمل | F1022: د. محمود ثابت | G1022: دايت بدون حرمان | H1022: https://youtube.com/playlist?list=PL90W1ZUHSNiQiI1BVLP5GuIXxf6hr9Rln&si=G_UimDsDy12ttC7G | I1022: 24 | J1022: كيف يتم تحديد نوع العلاج المناسب لمرضى السكري من النوعين الأول والثاني، وما هي التقنيات الحديثة المستخدمة في كل نوع؟ | K1022: يتم تحديد نوع العلاج المناسب لمرضى السكري بناءً على نوع المرض وحالة المريض. بالنسبة لمرض السكري من النوع الأول، العلاج يعتمد على تعويض الأنسولين المفقود، حيث يتم استخدام الأنسولين العلاجي أو تقنيات مثل زراعة البنكرياس أو استخدام الخلايا الجذعية. أما بالنسبة لمرض السكري من النوع الثاني، فإن العلاج يتنوع حسب حالة المريض، حيث يمكن البدء بالأدوية، وفي بعض الحالات قد يتطلب الأمر جراحة السمنة. كما أن هناك تقنيات حديثة مثل الأنسولين طويل المفعول والقصير المفعول، والتي تُستخدم وفقًا لاحتياجات المريض. | L1022: Confirmed (title match) | M1022: Batch output file | N1022: N | O1022: N | P1022: N | Q1022: Y
A1023: QA-1022 | B1023: 330 | C1023: Yij3_j5p8Oo | D1023: https://www.youtube.com/watch?v=Yij3_j5p8Oo&list=PL90W1ZUHSNiQiI1BVLP5GuIXxf6hr9Rln&index=27 | E1023: ادوية السكر: كل ما تحتاج معرفته عن أدوية السكر والأنسولين شرح مبسط للمجموعات، الجرعات و طريقة العمل | F1023: د. محمود ثابت | G1023: دايت بدون حرمان | H1023: https://youtube.com/playlist?list=PL90W1ZUHSNiQiI1BVLP5GuIXxf6hr9Rln&si=G_UimDsDy12ttC7G | I1023: 24 | J1023: ما هي الأنواع المختلفة من الأنسولين، وكيف يتم حساب الجرعات المناسبة لكل نوع بناءً على سرعة تأثيره؟ | K1023: الأنسولين يُقسم إلى عدة أنواع بناءً على سرعة تأثيره: 1. الأنسولين السريع (Rapid-acting): يبدأ تأثيره خلال 5-15 دقيقة ويستمر لمدة 2-4 ساعات. 2. الأنسولين القصير (Short-acting): يبدأ تأثيره بعد 30 دقيقة ويستمر من 3-6 ساعات. 3. الأنسولين المتوسط (Intermediate-acting): يبدأ تأثيره بعد 2-4 ساعات ويستمر حتى 18 ساعة. 4. الأنسولين طويل المفعول (Long-acting): يبدأ تأثيره بعد ساعتين ويستمر حتى 24 ساعة. 5. الأنسولين فائق الطول (Ultra-long-acting): يبدأ تأثيره بعد 6 ساعات ويستمر حتى 36 ساعة. يتم حساب الجرعات بناءً على كمية الكربوهيدرات في الوجبة، حيث يُحسب مقدار الأنسولين المطلوب لكل 10-15 جرام من الكربوهيدرات. | L1023: Confirmed (title match) | M1023: Batch output file | N1023: N | O1023: N | P1023: N | Q1023: Y
... A1066: QA-1065 | B1066: 338 | C1066: OxzPri40GHI | D1066: https://www.youtube.com/watch?v=OxzPri40GHI&list=PL90W1ZUHSNiRIha75nEofrSjVOuPEd7iL&index=2 | E1066: اضطراب الاكل الانتقائي عند الاطفال | F1066: د. محمود ثابت | G1066: دايت بدون حرمان | H1066: https://youtube.com/playlist?list=PL90W1ZUHSNiQiI1BVLP5GuIXxf6hr9Rln&si=G_UimDsDy12ttC7G | I1066: 25 | J1066: ما هي العلاقة بين اضطراب الأكل الانتقائي ونمو الطفل، وكيف يمكن أن يؤثر ذلك على تطوره العقلي والجسدي؟ | K1066: تعتبر العلاقة بين اضطراب الأكل الانتقائي ونمو الطفل علاقة وثيقة، حيث أن هذا الاضطراب يمكن أن يؤثر سلبًا على التطور العقلي والجسدي للطفل بعدة طرق: 1. **نقص العناصر الغذائية**: إذا كان الطفل يرفض تناول مجموعة متنوعة من الأطعمة، فقد يؤدي ذلك إلى نقص في الفيتامينات والمعادن الضرورية لنموه. 2. **تأثير على النمو الجسدي**: قد يؤدي نقص التغذية إلى تأخر في النمو الجسدي، مثل قلة الوزن أو الطول مقارنة بأقرانه. 3. **تأثير على التطور العقلي**: التغذية السليمة تلعب دورًا مهمًا في التطور العقلي، ونقص العناصر الغذائية يمكن أن يؤثر على التركيز والقدرة على التعلم. 4. **المشاكل السلوكية**: الأطفال الذين يعانون من اضطراب الأكل الانتقائي قد يظهرون سلوكيات عصبية أو مزاجية، مما قد يؤثر على تفاعلاتهم الاجتماعية. لذلك، من المهم مراقبة نمو الطفل والتوجه إلى طبيب الأطفال إذا ظهرت أي مشاكل. | L1066: Confirmed (title match) | M1066: Batch output file | N1066: N | O1066: N | P1066: N | Q1066: N
A1067: QA-1066 | B1067: 339 | C1067: 1i2RmroF2Wc | D1067: https://www.youtube.com/watch?v=1i2RmroF2Wc&list=PL90W1ZUHSNiRIha75nEofrSjVOuPEd7iL&index=3 | E1067: تصميم النظام الغذائي - ازاي تعمل نظام غذائي بطريقة الحصص و البدائل الغذائية | F1067: د. محمود ثابت | G1067: دايت بدون حرمان | H1067: https://youtube.com/playlist?list=PL90W1ZUHSNiQiI1BVLP5GuIXxf6hr9Rln&si=G_UimDsDy12ttC7G | I1067: 25 | J1067: ما هي الخطوات الأساسية التي يجب اتباعها عند تصميم نظام غذائي يدوي، وكيف يتم حساب السعرات الحرارية والمغذيات الكبرى بناءً على الحالة الصحية والنشاط اليومي للفرد؟ | K1067: عند تصميم نظام غذائي يدوي، يجب اتباع عدة خطوات أساسية: أولاً، يتم حساب السعرات الحرارية اللازمة للشخص مع مراعاة نشاطه اليومي ودرجة نشاطه. ثانياً، يتم تعديل مستوى السعرات الحرارية بما يتوافق مع احتياجات الحالة، سواء كانت تحتاج إلى تخسيس أو زيادة أو تثبيت الوزن. بعد ذلك، يتم حساب نسب المغذيات الكبرى والكميات المطلوبة منها، حيث يتم تحويل السعرات الحرارية إلى جرامات. ثم يتم اختيار الحصص والمجموعات الغذائية بناءً على السعرات الحرارية المطلوبة، وأخيراً يتم توزيع الأطعمة المختارة على الوجبات اليومية. على سبيل المثال، إذا كان لدينا حالة لرجل عمره 45 سنة، وزنه 72 كغم وطوله 167 سم، يتم حساب السعرات الحرارية اللازمة له باستخدام معادلة معينة، ثم يتم تحديد نسب المغذيات الكبرى مثل الكربوهيدرات والبروتينات والدهون بناءً على احتياجاته. | L1067: Confirmed (title match) | M1067: Batch output file | N1067: Y | O1067: N | P1067: N | Q1067: N | R1067: title listed more than once; chosen by batch range
A1068: QA-1067 | B1068: 339 | C1068: 1i2RmroF2Wc | D1068: https://www.youtube.com/watch?v=1i2RmroF2Wc&list=PL90W1ZUHSNiRIha75nEofrSjVOuPEd7iL&index=3 | E1068: تصميم النظام الغذائي - ازاي تعمل نظام غذائي بطريقة الحصص و البدائل الغذائية | F1068: د. محمود ثابت | G1068: دايت بدون حرمان | H1068: https://youtube.com/playlist?list=PL90W1ZUHSNiQiI1BVLP5GuIXxf6hr9Rln&si=G_UimDsDy12ttC7G | I1068: 25 | J1068: كيف يمكن استخدام شيت الإكسل في تصميم النظام الغذائي، وما هي الخطوات التي يجب اتباعها لضمان دقة الحسابات وتوزيع الحصص الغذائية بشكل صحيح؟ | K1068: استخدام شيت الإكسل في تصميم النظام الغذائي يتطلب عدة خطوات لضمان دقة الحسابات. أولاً، يتم إدخال البيانات الأساسية مثل العمر، الجنس، الطول، والوزن، حيث يقوم الإكسل بحساب معدل الأيض الأساسي (BMR) تلقائيًا. بعد ذلك، يتم تحديد مستوى النشاط اليومي، مما يؤثر على السعرات الحرارية المطلوبة. إذا كان الهدف هو الحفاظ على الوزن، يتم ترك الخانة الخاصة بالتغييرات فارغة، أما إذا كان الهدف هو زيادة أو تقليل الوزن، يتم إدخال الأرقام المناسبة. بعد ذلك، يتم توزيع المغذيات الكبرى مثل الكربوهيدرات والبروتينات والدهون بناءً على النسب المحددة، ويتم إدخال الأطعمة المناسبة في الشيت. يجب التأكد من أن الأرقام المدخلة دقيقة وأن الحصص الغذائية موزعة بشكل متوازن على مدار اليوم، مما يساعد في تحقيق الأهداف الغذائية المطلوبة. | L1068: Confirmed (title match) | M1068: Batch output file | N1068: Y | O1068: N | P1068: N | Q1068: N | R1068: title listed more than once; chosen by batch range
A1069: QA-1068 | B1069: 339 | C1069: 1i2RmroF2Wc | D1069: https://www.youtube.com/watch?v=1i2RmroF2Wc&list=PL90W1ZUHSNiRIha75nEofrSjVOuPEd7iL&index=3 | E1069: تصميم النظام الغذائي - ازاي تعمل نظام غذائي بطريقة الحصص و البدائل الغذائية | F1069: د. محمود ثابت | G1069: دايت بدون حرمان | H1069: https://youtube.com/playlist?list=PL90W1ZUHSNiQiI1BVLP5GuIXxf6hr9Rln&si=G_UimDsDy12ttC7G | I1069: 25 | J1069: ما هي العلاقة بين النشاط البدني والسعرات الحرارية المطلوبة، وكيف يؤثر ذلك على تصميم النظام الغذائي للأفراد ذوي الأنشطة المختلفة؟ | K1069: العلاقة بين النشاط البدني والسعرات الحرارية المطلوبة هي علاقة مباشرة، حيث أن مستوى النشاط اليومي يؤثر بشكل كبير على كمية السعرات الحرارية التي يحتاجها الفرد. على سبيل المثال، الشخص الذي يمارس نشاطاً بدنياً معتدلاً مثل المشي ثلاث مرات في الأسبوع يحتاج إلى سعرات حرارية أكثر من شخص غير نشط. عند تصميم النظام الغذائي، يجب مراعاة هذه العوامل، حيث يتم حساب السعرات الحرارية بناءً على معدل الأيض الأساسي (BMR) ثم يتم ضربه في معامل النشاط. هذا يعني أن الأفراد النشطين يحتاجون إلى كميات أكبر من السعرات الحرارية، مما يتطلب تعديل نسب المغذيات الكبرى في النظام الغذائي لضمان تلبية احتياجاتهم الغذائية. | L1069: Confirmed (title match) | M1069: Batch output file | N1069: Y | O1069: N | P1069: N | Q1069: N | R1069: title listed more than once; chosen by batch range
A1070: QA-1069 | B1070: 339 | C1070: 1i2RmroF2Wc | D1070: https://www.youtube.com/watch?v=1i2RmroF2Wc&list=PL90W1ZUHSNiRIha75nEofrSjVOuPEd7iL&index=3 | E1070: تصميم النظام الغذائي - ازاي تعمل نظام غذائي بطريقة الحصص و البدائل الغذائية | F1070: د. محمود ثابت | G1070: دايت بدون حرمان | H1070: https://youtube.com/playlist?list=PL90W1ZUHSNiQiI1BVLP5GuIXxf6hr9Rln&si=G_UimDsDy12ttC7G | I1070: 25 | J1070: كيف يمكن تحويل السعرات الحرارية إلى جرامات للمغذيات الكبرى، وما هي النسب الموصى بها لكل من الكربوهيدرات والبروتينات والدهون في النظام الغذائي؟ | K1070: لتحويل السعرات الحرارية إلى جرامات للمغذيات الكبرى، يتم استخدام القيم التالية: 1 جرام من الكربوهيدرات يحتوي على 4 سعرات حرارية، 1 جرام من البروتين يحتوي على 4 سعرات حرارية، و1 جرام من الدهون يحتوي على 9 سعرات حرارية. بناءً على ذلك، إذا كانت النسبة الموصى بها هي 55% كربوهيدرات، 20% بروتين، و25% دهون، يمكن حساب الكميات المطلوبة لكل مغذي. على سبيل المثال، إذا كانت السعرات الحرارية اليومية المطلوبة هي 2182 كالوري، فإن 55% منها (1200 كالوري) ستكون كربوهيدرات، مما يعني 300 جرام كربوهيدرات (1200 ÷ 4). وبالمثل، يتم حساب البروتينات والدهون بناءً على النسب المحددة، مما يساعد في تصميم نظام غذائي متوازن. | L1070: Confirmed (title match) | M1070: Batch output file | N1070: Y | O1070: N | P1070: N | Q1070: N | R1070: title listed more than once; chosen by batch range
A1071: QA-1070 | B1071: 339 | C1071: 1i2RmroF2Wc | D1071: https://www.youtube.com/watch?v=1i2RmroF2Wc&list=PL90W1ZUHSNiRIha75nEofrSjVOuPEd7iL&index=3 | E1071: تصميم النظام الغذائي - ازاي تعمل نظام غذائي بطريقة الحصص و البدائل الغذائية | F1071: د. محمود ثابت | G1071: دايت بدون حرمان | H1071: https://youtube.com/playlist?list=PL90W1ZUHSNiQiI1BVLP5GuIXxf6hr9Rln&si=G_UimDsDy12ttC7G | I1071: 25 | J1071: ما هي أهمية تنويع الأطعمة في النظام الغذائي وكيف يمكن تحقيق ذلك من خلال اختيار بدائل غذائية مختلفة؟ | K1071: تنويع الأطعمة في النظام الغذائي مهم لأنه يضمن الحصول على مجموعة متنوعة من العناصر الغذائية الضرورية لصحة الجسم. لتحقيق ذلك، يمكن اختيار بدائل غذائية مختلفة تعطي نفس القيمة الغذائية. على سبيل المثال، بدلاً من تناول 100 جرام من اللحوم، يمكن استبدالها بـ 100 جرام من صدور الدجاج أو تناول البيض كمصدر بروتين. كما يمكن استبدال الأرز بالمكرونة أو الخضار المطبوخة بأنواع مختلفة من الفاصوليا. هذا التنوع لا يساعد فقط في تلبية الاحتياجات الغذائية، بل يجعل النظام الغذائي أكثر متعة ويقلل من الملل الناتج عن تناول نفس الأطعمة بشكل متكرر. | L1071: Confirmed (title match) | M1071: Batch output file | N1071: Y | O1071: N | P1071: N | Q1071: N | R1071: title listed more than once; chosen by batch range
A1072: QA-1071 | B1072: 340 | C1072: hPNcngQcCMg | D1072: https://www.youtube.com/watch?v=hPNcngQcCMg&list=PL90W1ZUHSNiRIha75nEofrSjVOuPEd7iL&index=4 | E1072: النظام الغذائي لمريض السكر | F1072: د. محمود ثابت | G1072: دايت بدون حرمان | H1072: https://youtube.com/playlist?list=PL90W1ZUHSNiQiI1BVLP5GuIXxf6hr9Rln&si=G_UimDsDy12ttC7G | I1072: 25 | J1072: ما هي الأسباب الرئيسية التي تؤدي إلى الإصابة بمرض السكر، وكيف تختلف بين النوع الأول والنوع الثاني؟ | K1072: تحدث الإصابة بمرض السكر نتيجة لغياب أو تناقص إفراز هرمون الأنسولين أو تراجع قدرة الخلايا على استخدامه. في النوع الأول، يكون غياب إفراز الأنسولين من خلايا بيتا في البنكرياس منذ الولادة، مما يتطلب حقن الأنسولين يومياً مدى الحياة. بينما في النوع الثاني، يكون هناك ضعف أو قلة في إفراز الأنسولين، حيث تفرز الخلايا الأنسولين ولكنها تقاومه، مما يؤدي إلى اضطراب مزمن في قدرة الجسم على استخدام السكر. النوع الأول غالباً ما يظهر في الأطفال، بينما النوع الثاني يظهر بشكل أكبر في الكبار، ويمكن تجنبه من خلال نمط حياة صحي. | L1072: Confirmed (title match) | M1072: Batch output file | N1072: Y | O1072: Y | P1072: N | Q1072: Y | R1072: title listed more than once; chosen by batch range
...

Sheet Videos
A1: Video_Index | B1: Video_URL | C1: Video_ID | D1: Video_Title | E1: Channel (Dr) | F1: Channel_Name | G1: Status | H1: QA_Rows | I1: Batches | J1: Listed_More_Than_Once | K1: Processed_Twice | L1: Transcript_Truncated
A2: 1 | B2: https://www.youtube.com/watch?v=BE85vJQel4Q | C2: BE85vJQel4Q | D2: لماذا يتباطأ فقدان الوزن في الشتاء؟ الحقيقة التي لم يُخبِرك بها أحد | E2: د. كريم علي | F2: فِكر تاني | G2: Has QA - batch output | H2: 5 | I2: 1 | J2: N | K2: N | L2: N
A3: 2 | B3: https://www.youtube.com/watch?v=X6oFPkaSVfk | C3: X6oFPkaSVfk | D3: لماذا لا يهدأ جسدك؟ الجهاز العصبي أولًا” | E3: د. كريم علي | F3: فِكر تاني | G3: Has QA - batch output | H3: 5 | I3: 1 | J3: N | K3: N | L3: N
A4: 3 | B4: https://www.youtube.com/watch?v=V3SGExIImWM | C4: V3SGExIImWM | D4: د.كريم علي | 5 أسرار لإعادة بناء العظام والتخلص من الهشاشة | E4: د. كريم علي | F4: فِكر تاني | G4: Has QA - batch output | H4: 5 | I4: 1 | J4: N | K4: N | L4: N
A5: 4 | B5: https://www.youtube.com/watch?v=KnDhFZ6N020 | C5: KnDhFZ6N020 | D5: فضيحة المكملات كيف تميز المكمل الحقيقي من المغشوش؟ | E5: د. كريم علي | F5: فِكر تاني | G5: Has QA - batch output | H5: 5 | I5: 1 | J5: N | K5: N | L5: N
A6: 5 | B6: https://www.youtube.com/watch?v=PHSTCRsiO4k | C6: PHSTCRsiO4k | D6: د.كريم علي | 6 خطوات لتجديد شباب البشرة | E6: د. كريم علي | F6: فِكر تاني | G6: Has QA - batch output | H6: 5 | I6: 1 | J6: N | K6: N | L6: N
A7: 6 | B7: https://www.youtube.com/watch?v=i7Ee3qB9rwM | C7: i7Ee3qB9rwM | D7: لماذا توقفتُ عن شرب الحليب؟ (قرار طبي عاجل) | E7: د. كريم علي | F7: فِكر تاني | G7: Has QA - batch output | H7: 5 | I7: 1 | J7: N | K7: N | L7: N
A8: 7 | B8: https://www.youtube.com/watch?v=9ZUNPpmGwTE | C8: 9ZUNPpmGwTE | D8: السكر الخفي: كيف يؤثر على صحتك دون أن تشعر / د كريم علي | E8: د. كريم علي | F8: فِكر تاني | G8: Has QA - batch output | H8: 5 | I8: 1 | J8: N | K8: N | L8: N
A9: 8 | B9: https://www.youtube.com/watch?v=dOUiUqMSUgE | C9: dOUiUqMSUgE | D9: د.كريم علي | الطريقة الأفضل لـ خسارة الوزن ( التكميم - الصيام المتقطع - الأطعمة الصحية ) | E9: د. كريم علي | F9: فِكر تاني | G9: Has QA - batch output | H9: 5 | I9: 1 | J9: N | K9: N | L9: N
A10: 9 | B10: https://www.youtube.com/watch?v=9IBlbA-a2dE | C10: 9IBlbA-a2dE | D10: لاتوجد طاقة وارهاق مستمر/ اليك مالاتعرفه والحلول النهائيه ! | E10: د. كريم علي | F10: فِكر تاني | G10: Has QA - batch output | H10: 5 | I10: 1 | J10: N | K10: N | L10: N
A11: 10 | B11: https://www.youtube.com/watch?v=ng56neAVFDA | C11: ng56neAVFDA | D11: د.كريم علي | عن صحة المرأة حقائق صادمة ونصائح من ذهب | حلقات مجمعة | E11: د. كريم علي | F11: فِكر تاني | G11: Has QA - batch output | H11: 5 | I11: 1 | J11: N | K11: N | L11: Y
A12: 11 | B12: https://www.youtube.com/watch?v=U7zwsWpj5tQ | C12: U7zwsWpj5tQ | D12: د.كريم علي | فوائد الأشعة تحت الحمراء للجسم والبشرة | E12: د. كريم علي | F12: فِكر تاني | G12: Has QA - batch output | H12: 5 | I12: 2 | J12: N | K12: N | L12: N
A13: 12 | B13: https://www.youtube.com/watch?v=9fTymymI2zg | C13: 9fTymymI2zg | D13: ! د.كريم علي | 4 أعشاب بهم قوة سحرية لصحتك وجمالك | E13: د. كريم علي | F13: فِكر تاني | G13: No QA found | H13: 0 | J13: N | K13: N
A14: 13 | B14: https://www.youtube.com/watch?v=YKhEpOz6SMM | C14: YKhEpOz6SMM | D14: د.كريم علي | حقيقة التطعيمات والتوحد ؟ خطر الفلورايد! | E14: د. كريم علي | F14: فِكر تاني | G14: Has QA - batch output | H14: 5 | I14: 2 | J14: N | K14: N | L14: N
A15: 14 | B15: https://www.youtube.com/watch?v=ky8zmoUjc4g | C15: ky8zmoUjc4g | D15: د.كريم علي | مشاكل البشرة وحلها من الجذور لإشراقة دائمة | E15: د. كريم علي | F15: فِكر تاني | G15: Has QA - batch output | H15: 5 | I15: 3 | J15: N | K15: N | L15: N
A16: 15 | B16: https://www.youtube.com/watch?v=PH6rzmmHas0 | C16: PH6rzmmHas0 | D16: د.كريم علي | خطة لـ شباب دائم لـ تعود 10 سنوات للوراء | E16: د. كريم علي | F16: فِكر تاني | G16: Has QA - batch output | H16: 5 | I16: 3 | J16: N | K16: N | L16: N
A17: 16 | B17: https://www.youtube.com/watch?v=fy808242vbU | C17: fy808242vbU | D17: د.كريم علي | أفضل نظام غذائي لـ شعر كثيف في شهر واحد | E17: د. كريم علي | F17: فِكر تاني | G17: Has QA - batch output | H17: 10 | I17: 4, 5 | J17: N | K17: Y | L17: N
A18: 17 | B18: https://www.youtube.com/watch?v=A5mYly5TQuI | C18: A5mYly5TQuI | D18: د.كريم علي | القولون وضحاياه وعلاقته بصحة جسدك ونفسيتك ( حلقات مجمعة ) | E18: د. كريم علي | F18: فِكر تاني | G18: Has QA - batch output | H18: 10 | I18: 4, 5 | J18: N | K18: Y | L18: N
A19: 18 | B19: https://www.youtube.com/watch?v=qwLArmauaBw | C19: qwLArmauaBw | D19: د.كريم علي | لـ شباب يدوم .. سر الأكسير الحقيقي ( حلقات مجمعة ) | E19: د. كريم علي | F19: فِكر تاني | G19: Has QA - batch output | H19: 5 | I19: 5 | J19: N | K19: N | L19: Y
A20: 19 | B20: https://www.youtube.com/watch?v=9Se3fHKcAJk | C20: 9Se3fHKcAJk | D20: أسرار الطعام الذي يغير مزاجك بسرعة! | E20: د. كريم علي | F20: فِكر تاني | G20: Has QA - batch output | H20: 5 | I20: 5 | J20: N | K20: N | L20: N
A21: 20 | B21: https://www.youtube.com/watch?v=zwkP_ycUmwc | C21: zwkP_ycUmwc | D21: أسرار الميثيلين بلو وفوائده المدهشة للجسم! | E21: د. كريم علي | F21: فِكر تاني | G21: Has QA - batch output | H21: 5 | I21: 5 | J21: N | K21: N | L21: N
A22: 21 | B22: https://www.youtube.com/watch?v=tUOdj3WgBIU | C22: tUOdj3WgBIU | D22: علاج السمنة في الاطفال والمراهقين ؟ اكتشف السبب وعلاج الآن! | E22: د. كريم علي | F22: فِكر تاني | G22: Has QA - batch output | H22: 5 | I22: 5 | J22: N | K22: N | L22: N
A23: 22 | B23: https://www.youtube.com/watch?v=Gb2b8VTogrk | C23: Gb2b8VTogrk | D23: ٧٠٪ من العرب عندهم نقص فيتامين دال! كيف نعالج نقصه بسهولة | E23: د. كريم علي | F23: فِكر تاني | G23: Has QA - batch output | H23: 5 | I23: 5 | J23: N | K23: N | L23: N
A24: 23 | B24: https://www.youtube.com/watch?v=f4sgHPYleOQ | C24: f4sgHPYleOQ | D24: هل الكوليسترول فعلاً خطر كما يقولون؟ مالا يقوله الاطباء | E24: د. كريم علي | F24: فِكر تاني | G24: Has QA - batch output | H24: 5 | I24: 5 | J24: N | K24: N | L24: N
A25: 24 | B25: https://www.youtube.com/watch?v=Ep5PDCI4DKA | C25: Ep5PDCI4DKA | D25: هل الأكل يمنع الحمل؟ اكتشفي الحقيقة الصادمة! | E25: د. كريم علي | F25: فِكر تاني | G25: Has QA - batch output | H25: 5 | I25: 5 | J25: N | K25: N | L25: N
A26: 25 | B26: https://www.youtube.com/watch?v=EIx577OqEik | C26: EIx577OqEik | D26: هل تعاني من هذه الأعراض؟ انتبه لصحة كبدك! | E26: د. كريم علي | F26: فِكر تاني | G26: No QA found | H26: 0 | J26: N | K26: N
A27: 26 | B27: https://www.youtube.com/watch?v=TQa-2yerhjc | C27: TQa-2yerhjc | D27: 5 أطعمة خطيرة في بيتك تدمر قلبك! | E27: د. كريم علي | F27: فِكر تاني | G27: No QA found | H27: 0 | J27: N | K27: N
A28: 27 | B28: https://www.youtube.com/watch?v=PaaprAiuRSA | C28: PaaprAiuRSA | D28: أسرار الجمال المزيف: ماذا يخفي سوق التجميل؟ | E28: د. كريم علي | F28: فِكر تاني | G28: No QA found | H28: 0 | J28: N | K28: N
A29: 28 | B29: https://www.youtube.com/watch?v=RJWtAjjdQzI | C29: RJWtAjjdQzI | D29: والديك في خطر والحل في يديك/ خطوات بسيطة لكبار السن | E29: د. كريم علي | F29: فِكر تاني | G29: Has QA - batch output | H29: 5 | I29: 6 | J29: N | K29: N | L29: N
A30: 29 | B30: https://www.youtube.com/watch?v=kGIO_OsDtLU | C30: kGIO_OsDtLU | D30: علاج دهون الكرش والاجناب /الأسباب العشرة الرئيسية وحلها | E30: د. كريم علي | F30: فِكر تاني | G30: No QA found | H30: 0 | J30: N | K30: N
A31: 30 | B31: https://www.youtube.com/watch?v=4CFEQ2NeVcs | C31: 4CFEQ2NeVcs | D31: انتبه لصحتك تعرف على علامات الخطر التي تهدد الكليتين | E31: د. كريم علي | F31: فِكر تاني | G31: Has QA - batch output | H31: 5 | I31: 6 | J31: N | K31: N | L31: N
A32: 31 | B32: https://www.youtube.com/watch?v=FmOmTBukUxM | C32: FmOmTBukUxM | D32: الكشري/ اكتشف كيف يصبح اكلة صحية ومغذية لكل الاسرة | E32: د. كريم علي | F32: فِكر تاني | G32: Has QA - batch output | H32: 5 | I32: 6 | J32: N | K32: N | L32: N
A33: 32 | B33: https://www.youtube.com/watch?v=vqvLTA0VvXM | C33: vqvLTA0VvXM | D33: هل تريدي وجه ناعم وصحي؟ جربي هذه النصائح الآن! | E33: د. كريم علي | F33: فِكر تاني | G33: Has QA - batch output | H33: 5 | I33: 6 | J33: N | K33: N | L33: N
A34: 33 | B34: https://www.youtube.com/watch?v=xS2zcKe3FYA | C34: xS2zcKe3FYA | D34: وداعا لمشاكل الدورة واعراض انقطاع الطمث مع مركب طبيعي واحد فقط | E34: د. كريم علي | F34: فِكر تاني | G34: Has QA - batch output | H34: 5 | I34: 6 | J34: N | K34: N | L34: N
A35: 34 | B35: https://www.youtube.com/watch?v=t5yWhD4CvZ4 | C35: t5yWhD4CvZ4 | D35: القولون ونهاية مشاكله/ ١٢ غذاء صديق للقولون وسهل الهضم | E35: د. كريم علي | F35: فِكر تاني | G35: Has QA - batch output | H35: 5 | I35: 6 | J35: N | K35: N | L35: N
A36: 35 | B36: https://www.youtube.com/watch?v=fHuk5ziIyOo | C36: fHuk5ziIyOo | D36: علاج السيلوليت النهائي مع هذه النصائح القيمة | E36: د. كريم علي | F36: فِكر تاني | G36: Has QA - batch output | H36: 5 | I36: 6 | J36: N | K36: N | L36: N
A37: 36 | B37: https://www.youtube.com/watch?v=ZzwlsEB7ziY | C37: ZzwlsEB7ziY | D37: خطة الحياة الصحية بعد رمضان/ ضاعف الفوائد و استمتع بحياتك | E37: د. كريم علي | F37: فِكر تاني | G37: Has QA - batch output | H37: 5 | I37: 6 | J37: N | K37: N | L37: N
A38: 37 | B38: https://www.youtube.com/watch?v=NxipJyNskH4 | C38: NxipJyNskH4 | D38: جسمك يحذرك من 20 نقص صحي يجب الانتباه له | E38: د. كريم علي | F38: فِكر تاني | G38: Has QA - batch output | H38: 5 | I38: 6 | J38: N | K38: N | L38: N
A39: 38 | B39: https://www.youtube.com/watch?v=YJbTgqTe-T0 | C39: YJbTgqTe-T0 | D39: عشر خطوات بسيطة لمفاصل جديدة وصحية هذا الشتاء | E39: د. كريم علي | F39: فِكر تاني | G39: Has QA - batch output | H39: 5 | I39: 7 | J39: N | K39: N | L39: N
A40: 39 | B40: https://www.youtube.com/watch?v=kpVMgNaORE8 | C40: kpVMgNaORE8 | D40: اخطاء الصيام المتقطع قد تزيد وزنك وتفشل محاولاتك/ الحلول | E40: د. كريم علي | F40: فِكر تاني | G40: Has QA - batch output | H40: 5 | I40: 7 | J40: N | K40: N | L40: N
A41: 40 | B41: https://www.youtube.com/watch?v=_GCHqAcui6Q | C41: _GCHqAcui6Q | D41: كبسولات القهوة/ لاتستخدمها قبل المشاهدة / دراسات جديدة صادمة | E41: د. كريم علي | F41: فِكر تاني | G41: Has QA - batch output | H41: 5 | I41: 7 | J41: N | K41: N | L41: N
A42: 41 | B42: https://www.youtube.com/watch?v=P0xQ9bA3pMI | C42: P0xQ9bA3pMI | D42: اخسر وزنك وارفع مناعتك بأربعة اطعمة رخيصة وفي كل بيت | E42: د. كريم علي | F42: فِكر تاني | G42: Has QA - batch output | H42: 5 | I42: 7 | J42: N | K42: N | L42: N
... A58: 57 | B58: https://www.youtube.com/watch?v=uaV-5J5SjdA | C58: uaV-5J5SjdA | D58: تكميم المعدة / ١١ نصيحة بعد العملية لتنجنب ان تندم عليها 😲😲 | E58: د. كريم علي | F58: فِكر تاني | G58: Has QA - batch output | H58: 5 | I58: 10 | J58: N | K58: N | L58: N
A59: 58 | B59: https://www.youtube.com/watch?v=01UDpD-Nqyg | C59: 01UDpD-Nqyg | D59: البروتينات النباتية خدعة واللحوم علاج لكثير من الامراض/ لقاءً تلفزيونى مع د كريم علي | E59: د. كريم علي | F59: فِكر تاني | G59: No QA found | H59: 0 | J59: N | K59: N
A60: 59 | B60: https://www.youtube.com/watch?v=-oI7sNGspT8 | C60: -oI7sNGspT8 | D60: امور تدمر ذاكرتك تفعلها كل يوم/ كيف نستعيد الذاكرة ونرفع الذكاء | E60: د. كريم علي | F60: فِكر تاني | G60: Has QA - batch output | H60: 5 | I60: 10 | J60: N | K60: N | L60: N
A61: 60 | B61: https://www.youtube.com/watch?v=wuQcp7Qw4tQ | C61: wuQcp7Qw4tQ | D61: علاج الامراض المناعية / لماذا تصاب وطريق الشفاء بدون ادوية | E61: د. كريم علي | F61: فِكر تاني | G61: Has QA - batch output | H61: 5 | I61: 10 | J61: N | K61: N | L61: N
A62: 61 | B62: https://www.youtube.com/watch?v=jxcFrpMkFn0 | C62: jxcFrpMkFn0 | D62: صحتك ونظامك الغذائي بعد رمضان/ خطوات سهلة للاستفادة القصوي بعد العيد | E62: د. كريم علي | F62: فِكر تاني | G62: Has QA - batch output | H62: 5 | I62: 10 | J62: N | K62: N | L62: N
A63: 62 | B63: https://www.youtube.com/watch?v=mFKVnjrMQM8 | C63: mFKVnjrMQM8 | D63: القولون والامراض النفسية/ دراسة حديثة ستنهي معاناتك نهائيا/ حل مشاكل القولون والاكتئاب | E63: د. كريم علي | F63: فِكر تاني | G63: Has QA - batch output | H63: 5 | I63: 10 | J63: N | K63: N | L63: N
A64: 63 | B64: https://www.youtube.com/watch?v=_oGMhT-jMfA | C64: _oGMhT-jMfA | D64: الكلاجين من عظام البقر او مكمل غذائى | E64: د. كريم علي | F64: فِكر تاني | G64: Has QA - batch output | H64: 5 | I64: 10 | J64: N | K64: N | L64: N
A65: 64 | B65: https://www.youtube.com/watch?v=bux_BaudRhg | C65: bux_BaudRhg | D65: التوتر والضغط العصبي و علاجهم الشافى.. من لقاء د كريم علي / برنامج رفرش | E65: د. كريم علي | F65: فِكر تاني | G65: Has QA - batch output | H65: 5 | I65: 10 | J65: N | K65: N | L65: N
A66: 65 | B66: https://www.youtube.com/watch?v=vEX4w0zsRRY | C66: vEX4w0zsRRY | D66: تخلص من خوف الامراض تماما( ٦ نقاط لتتخلص منه نهائيا ) استعد صحتك النفسية فورا | E66: د. كريم علي | F66: فِكر تاني | G66: Has QA - batch output | H66: 5 | I66: 10 | J66: N | K66: N | L66: N
A67: 66 | B67: https://www.youtube.com/watch?v=EpMblOPFOgA | C67: EpMblOPFOgA | D67: قواعد ازالة السموم من الجسم وطرق الديتوكس/ لقاء د كريم علي صباح الامارات | E67: د. كريم علي | F67: فِكر تاني | G67: Has QA - batch output | H67: 5 | I67: 10 | J67: N | K67: N | L67: N
A68: 67 | B68: https://www.youtube.com/watch?v=7D16IKEf3sA | C68: 7D16IKEf3sA | D68: الصيام المتقطع يزيد نسبة الوفاة من امراض القلب ٩١٪؜ / دراسة صادمة | E68: د. كريم علي | F68: فِكر تاني | G68: Has QA - batch output | H68: 5 | I68: 10 | J68: N | K68: N | L68: N
A69: 68 | B69: https://www.youtube.com/watch?v=WSEdZyCTH2g | C69: WSEdZyCTH2g | D69: شاي المتة/ هذا مايحدث لجسمك بعد شربه/ كنز امريكا اللاتينية | E69: د. كريم علي | F69: فِكر تاني | G69: Has QA - batch output | H69: 5 | I69: 11 | J69: N | K69: N | L69: N
A70: 69 | B70: https://www.youtube.com/watch?v=dbbb9jSqHNA | C70: dbbb9jSqHNA | D70: ١١ علامة تنبهك لصحتك النفسية مسبقا / لو وجدت احداها انتبه فورا🆘❌ | E70: د. كريم علي | F70: فِكر تاني | G70: Has QA - batch output | H70: 5 | I70: 11 | J70: N | K70: N | L70: N
A71: 70 | B71: https://www.youtube.com/watch?v=8yAHqfGsUMI | C71: 8yAHqfGsUMI | D71: الكيتو يسبب الجلطات وامراض القلب😳/ حقائق النظام الكيتوني واهم الخرافات | E71: د. كريم علي | F71: فِكر تاني | G71: Has QA - batch output | H71: 5 | I71: 11 | J71: N | K71: N | L71: N
... A79: 78 | B79: https://www.youtube.com/watch?v=-khNo2UPLeo | C79: -khNo2UPLeo | D79: عشبة المليسة/ مزاج رايق ونوم افضل وقضاء علي زياده الغده الدرقية ( رائعة) | E79: د. كريم علي | F79: فِكر تاني | G79: Has QA - batch output | H79: 5 | I79: 11 | J79: N | K79: N | L79: N
A80: 79 | B80: https://www.youtube.com/watch?v=yDmbPeoTMV8 | C80: yDmbPeoTMV8 | D80: الخرشوف/ من يعرفه لايتركه ابدا/ فوائد رائعة للجسم والديتوكس/ سوبر فوود | E80: د. كريم علي | F80: فِكر تاني | G80: Has QA - position-inferred | H80: 5 | I80: 12 | J80: N | K80: N
A81: 80 | B81: https://www.youtube.com/watch?v=Vs4A__ffSWc | C81: Vs4A__ffSWc | D81: زيت الخروع/ اسرار العلاج وكل مايلزم معرفته عن الاستخدام والمحاذير | E81: د. كريم علي | F81: فِكر تاني | G81: Has QA - position-inferred | H81: 5 | I81: 12 | J81: N | K81: N
A82: 81 | B82: https://www.youtube.com/watch?v=4iXFo0_Nny0 | C82: 4iXFo0_Nny0 | D82: المعادن والفيتامينات/ لماذا نهتم وهل طعامك يكفى ( من لايف د كريم على ) | E82: د. كريم علي | F82: فِكر تاني | G82: Has QA - position-inferred | H82: 5 | I82: 12 | J82: N | K82: N
A83: 82 | B83: https://www.youtube.com/watch?v=z083kmuRcJM | C83: z083kmuRcJM | D83: اسرار طبق السلاطة الغذائية/ لن تتركه ابدا بعد المشاهدة/غذاؤك دواؤك | E83: د. كريم علي | F83: فِكر تاني | G83: Has QA - position-inferred | H83: 5 | I83: 12 | J83: N | K83: N
A84: 83 | B84: https://www.youtube.com/watch?v=HGoV3PFzd6M | C84: HGoV3PFzd6M | D84: هرمونات الذكورة والانوثة/ المعادلة الصحيحة لضبط هرمونات الجنسين/ تونجات على | E84: د. كريم علي | F84: فِكر تاني | G84: Has QA - position-inferred | H84: 5 | I84: 12 | J84: N | K84: N
A85: 84 | B85: https://www.youtube.com/watch?v=-Lodo7fh9EY | C85: -Lodo7fh9EY | D85: حلويات صحية / وجبة متكامله وعالية البروتين لصيف حار وصحة افضل | E85: د. كريم علي | F85: فِكر تاني | G85: Has QA - position-inferred | H85: 5 | I85: 12 | J85: N | K85: N
A86: 85 | B86: https://www.youtube.com/watch?v=Dj6nGb16nkM | C86: Dj6nGb16nkM | D86: فوائد الحبهان / لن تتخيل كم الفوائد مع استخدام الهيل / بهار لكل الاعمار | E86: د. كريم علي | F86: فِكر تاني | G86: Has QA - position-inferred | H86: 5 | I86: 12 | J86: N | K86: N
A87: 86 | B87: https://www.youtube.com/watch?v=Aihy17rbnKQ | C87: Aihy17rbnKQ | D87: اسرع طرق لقتل جرثومة المعدة / تخلص من الميكروب الحلزونى نهائيا وبلا رجعة | E87: د. كريم علي | F87: فِكر تاني | G87: Has QA - position-inferred | H87: 5 | I87: 12 | J87: N | K87: N
A88: 87 | B88: https://www.youtube.com/watch?v=UQtjZSRsQzo | C88: UQtjZSRsQzo | D88: حل مشاكل القولون والجهاز الهضمي فى اسبوعين مع تواصل يومي مع د كريم علي | E88: د. كريم علي | F88: فِكر تاني | G88: Has QA - position-inferred | H88: 5 | I88: 12 | J88: N | K88: N
A89: 88 | B89: https://www.youtube.com/watch?v=TFpMiCggDFk | C89: TFpMiCggDFk | D89: ايس كريم صحي ولذيذ بدون سكر او حليب/ التحضير فى ٥ دقائق ولكل الاعمار | E89: د. كريم علي | F89: فِكر تاني | G89: Has QA - position-inferred | H89: 5 | I89: 12 | J89: N | K89: N
A90: 89 | B90: https://www.youtube.com/watch?v=_dse7ZSLgEA | C90: _dse7ZSLgEA | D90: الشيكولاتة الداكنة/ ستجدد خلايا جسمك الى الضعف واكثر من ذلك / بحث جديد | E90: د. كريم علي | F90: فِكر تاني | G90: Has QA - position-inferred | H90: 5 | I90: 12 | J90: N | K90: N
A91: 90 | B91: https://www.youtube.com/watch?v=f4s3J9M3bI8 | C91: f4s3J9M3bI8 | D91: فوائد بيكربونات الصوديوم/ خل التفاح/ الماء بالليمون التى لاتنتهي / كيمياء | E91: د. كريم علي | F91: فِكر تاني | G91: Has QA - batch output | H91: 5 | I91: 13 | J91: N | K91: N | L91: N
A92: 91 | B92: https://www.youtube.com/watch?v=F4ZtrYMEfyU | C92: F4ZtrYMEfyU | D92: سرطان الثدى/ الوقاية فى طعامك واهم الاغذية لعدم الإصابة به / صحتك تستاهل | E92: د. كريم علي | F92: فِكر تاني | G92: Has QA - batch output | H92: 5 | I92: 13 | J92: N | K92: N | L92: N
A93: 92 | B93: https://www.youtube.com/watch?v=aXibbNykT_g | C93: aXibbNykT_g | D93: اسرار نبات الشيح/ مالم تعرفه من قبل وعلاج الديدان الاقوي/ قتل خلايا السرطان | E93: د. كريم علي | F93: فِكر تاني | G93: Has QA - batch output | H93: 5 | I93: 13 | J93: N | K93: N | L93: N
A94: 93 | B94: https://www.youtube.com/watch?v=9Ex4MT0nggg | C94: 9Ex4MT0nggg | D94: التجربة الايطالية/ كيف تعيش بصحة جيدة ١٠٠ عام / اسرار جزيرة ساردينيا | E94: د. كريم علي | F94: فِكر تاني | G94: Has QA - batch output | H94: 5 | I94: 13 | J94: N | K94: N | L94: N
A95: 94 | B95: https://www.youtube.com/watch?v=c-7AP1_M3go | C95: c-7AP1_M3go | D95: علاج الانيميا ورفع الحديد/ اسرع طريقة لحل مشكلة الانيميا المستعصيه | E95: د. كريم علي | F95: فِكر تاني | G95: Has QA - batch output | H95: 5 | I95: 13 | J95: N | K95: N | L95: N
A96: 95 | B96: https://www.youtube.com/watch?v=RX8bAHD2n_Y | C96: RX8bAHD2n_Y | D96: فوائد الخميرة الغذائية/ لن تتركها بعد الان / معادن وفيتامينات لاغنى عنها | E96: د. كريم علي | F96: فِكر تاني | G96: Has QA - batch output | H96: 5 | I96: 13 | J96: N | K96: N | L96: N
A97: 96 | B97: https://www.youtube.com/watch?v=iYsZhhAZGFk | C97: iYsZhhAZGFk | D97: نهاية تساقط الشعر والفراغات/ خلاصة الطريق الى شعر غزير لامع بطرق طبيعية | E97: د. كريم علي | F97: فِكر تاني | G97: Has QA - batch output | H97: 5 | I97: 13 | J97: N | K97: N | L97: N
A98: 97 | B98: https://www.youtube.com/watch?v=fmlWEvCM_nI | C98: fmlWEvCM_nI | D98: قد تتوقفون تماما عن تناول الخبز (العيش) بعد الان // افضل بديل سهل وصحى | E98: د. كريم علي | F98: فِكر تاني | G98: Has QA - batch output | H98: 5 | I98: 13 | J98: N | K98: N | L98: N
A99: 98 | B99: https://www.youtube.com/watch?v=yqT-j_l6ETs | C99: yqT-j_l6ETs | D99: لاتترك الملح ابدا قبل المشاهدة / مصادر اليود وملح الهيمالايا الوردي | E99: د. كريم علي | F99: فِكر تاني | G99: No QA found | H99: 0 | J99: N | K99: N
A100: 99 | B100: https://www.youtube.com/watch?v=n-5R4Lr6BWY | C100: n-5R4Lr6BWY | D100: علاج مرضك بيدء من هنا /قصة بيشونب الذى غيرت نظريات الطب الحديث | E100: د. كريم علي | F100: فِكر تاني | G100: Has QA - batch output | H100: 5 | I100: 13 | J100: N | K100: N | L100: N
A101: 100 | B101: https://www.youtube.com/watch?v=qnSQFmQeF_o | C101: qnSQFmQeF_o | D101: هل الاندومي يسبب السرطان / ورق الالومنيوم هل يسبب التسمم؟/ اسألة المتابعين | E101: د. كريم علي | F101: فِكر تاني | G101: Has QA - batch output | H101: 5 | I101: 13 | J101: N | K101: N | L101: N
A102: 101 | B102: https://www.youtube.com/watch?v=09gK4rrE2xI | C102: 09gK4rrE2xI | D102: علاج الضغط العالى / ٣ خطوات لعلاج الضغط واهمية نوع الملح فى الطعام ( مهمة) | E102: د. كريم علي | F102: فِكر تاني | G102: Has QA - batch output | H102: 5 | I102: 14 | J102: N | K102: N | L102: N
A103: 102 | B103: https://www.youtube.com/watch?v=6LrgZo0hCi4 | C103: 6LrgZo0hCi4 | D103: علاج هشاشة العظام / عظام ومفاصل اقوى طوال الوقت / الخلاصة فى فكر تانى | E103: د. كريم علي | F103: فِكر تاني | G103: Has QA - batch output | H103: 5 | I103: 14 | J103: N | K103: N | L103: N
A104: 103 | B104: https://www.youtube.com/watch?v=xqHlWwEXHcE | C104: xqHlWwEXHcE | D104: نقص البوتاسيوم/ اعراضه واهميته ومصادره الاهم لصحة افضل وجهاز عصبي اقوي | E104: د. كريم علي | F104: فِكر تاني | G104: Has QA - batch output | H104: 5 | I104: 14 | J104: N | K104: N | L104: N
A105: 104 | B105: https://www.youtube.com/watch?v=YULrTVz4WKk | C105: YULrTVz4WKk | D105: حرق الدهون/ خلاصة آلاف الابحاث فى ٣ نقاط لتتخلص من الدهون العنيدة نهائيا | E105: د. كريم علي | F105: فِكر تاني | G105: Has QA - batch output | H105: 5 | I105: 14 | J105: N | K105: N | L105: N
A106: 105 | B106: https://www.youtube.com/watch?v=qoqxU0p4E0E | C106: qoqxU0p4E0E | D106: ارفع هرمونات السعاده والفرفشة مجانا/ طرق طبيعية لرفع كل هرمونات السعادة | E106: د. كريم علي | F106: فِكر تاني | G106: Has QA - batch output | H106: 5 | I106: 14 | J106: N | K106: N | L106: N
A107: 106 | B107: https://www.youtube.com/watch?v=BvKIHqIG5yw | C107: BvKIHqIG5yw | D107: التجربة اليابانية/ يعيشون فوق ال١٠٠ عام / كل مايجب عليك عمله لصحة افضل | E107: د. كريم علي | F107: فِكر تاني | G107: Has QA - batch output | H107: 5 | I107: 14 | J107: N | K107: N | L107: N
A108: 107 | B108: https://www.youtube.com/watch?v=Rk8DFU3rSfk | C108: Rk8DFU3rSfk | D108: الرياضة اثناء الصيام / الحفاظ على الكتلة العضلية للجنسين مع اوقات الصيام | E108: د. كريم علي | F108: فِكر تاني | G108: Has QA - batch output | H108: 5 | I108: 14 | J108: N | K108: N | L108: N
A109: 108 | B109: https://www.youtube.com/watch?v=kpdTlaOKK9Y | C109: kpdTlaOKK9Y | D109: المكملات الغذائية فى رمضان/ المهم فقط ودعوه لايقاف باقى المكملات | E109: د. كريم علي | F109: فِكر تاني | G109: Has QA - batch output | H109: 5 | I109: 14 | J109: N | K109: N | L109: N
A110: 109 | B110: https://www.youtube.com/watch?v=JrxaDbzkJ78 | C110: JrxaDbzkJ78 | D110: غسول الاسنان وشموع المنزل/ سموم فى كل بيت / الاضرار والبديل الافضل | E110: د. كريم علي | F110: فِكر تاني | G110: Has QA - batch output | H110: 5 | I110: 14 | J110: N | K110: N | L110: N
A111: 110 | B111: https://www.youtube.com/watch?v=WVr65VzbnJk | C111: WVr65VzbnJk | D111: طرق التنفس لرفع اكسيد النتريك ١٥٠٠٪؜ / تنفسك يغير حالتك الصحية فورا | E111: د. كريم علي | F111: فِكر تاني | G111: Has QA - batch output | H111: 5 | I111: 14 | J111: N | K111: N | L111: N
... A137: 136 | B137: https://www.youtube.com/watch?v=xhDN8AyZVFk | C137: xhDN8AyZVFk | D137: رياضة المشى / ١١ فائدة مجانية لن تتخيلها وعلاقته بالسرطان والسكرى | E137: د. كريم علي | F137: فِكر تاني | G137: Has QA - batch output | H137: 5 | I137: 17 | J137: N | K137: N | L137: N
A138: 137 | B138: https://www.youtube.com/watch?v=8KImAXTgggs | C138: 8KImAXTgggs | D138: اسرار الشيا/ مالم تسمعه من قبل لانقاص الوزن وحتى نشاط الحامض النووى | E138: د. كريم علي | F138: فِكر تاني | G138: No QA found | H138: 0 | J138: N | K138: N
A139: 138 | B139: https://www.youtube.com/watch?v=jbhKFHWGERA | C139: jbhKFHWGERA | D139: اينوزيتول فيتامين ب صانع المعجزات/ من مقاومة الانسولين الى علاج السرطان | E139: د. كريم علي | F139: فِكر تاني | G139: Has QA - batch output | H139: 5 | I139: 18 | J139: N | K139: N | L139: N
A140: 139 | B140: https://www.youtube.com/watch?v=GkZ0Wq_szEs | C140: GkZ0Wq_szEs | D140: اسرار غشاء المايلين/ اكسير الشباب وجهاز عصبى سليم/ التصلب اللويحى | E140: د. كريم علي | F140: فِكر تاني | G140: Has QA - batch output | H140: 5 | I140: 18 | J140: N | K140: N | L140: N
A141: 140 | B141: https://www.youtube.com/watch?v=KDXE31nA77M | C141: KDXE31nA77M | D141: احذر اكل الفواكة واللحوم بهذه الطريقة/ سموم الطعام التى نتناولها يوميا | E141: د. كريم علي | F141: فِكر تاني | G141: Has QA - batch output | H141: 5 | I141: 18 | J141: N | K141: N | L141: N
A142: 141 | B142: https://www.youtube.com/watch?v=TYR28HIDpwc | C142: TYR28HIDpwc | D142: تخلص من السموم وحسن بشرتك وارفع طاقتك فى عصير سهل ورخيص/ عصير الديتوكس | E142: د. كريم علي | F142: فِكر تاني | G142: No QA found | H142: 0 | J142: N | K142: N
A143: 142 | B143: https://www.youtube.com/watch?v=5IHndBtCTEQ | C143: 5IHndBtCTEQ | D143: شاى الكمون افقد وزن وحسن القولون / موانع الاكسدة ومضادات السرطان بدون تكاليف | E143: د. كريم علي | F143: فِكر تاني | G143: Has QA - batch output | H143: 5 | I143: 18 | J143: N | K143: N | L143: N
A144: 143 | B144: https://www.youtube.com/watch?v=TvekO8EGjRE | C144: TvekO8EGjRE | D144: حقن الساكسندا لنزول الوزن والجانب الاخر الذى لن يخبرك به احد/ نزول الوزن | E144: د. كريم علي | F144: فِكر تاني | G144: No QA found | H144: 0 | J144: N | K144: N
A145: 144 | B145: https://www.youtube.com/watch?v=G4TsdAOE7cY | C145: G4TsdAOE7cY | D145: علامات الصحة الاكيدة/ لو اختفت انت فى طريقك للمرض/ حلقة فى قلب الوقاية | E145: د. كريم علي | F145: فِكر تاني | G145: No QA found | H145: 0 | J145: N | K145: N
A146: 145 | B146: https://www.youtube.com/watch?v=dol3dmJBToE | C146: dol3dmJBToE | D146: العلاج بالكيروسين/ هل هو علاج ام سم جديد / الجاز وتاثيراته على الجسم | E146: د. كريم علي | F146: فِكر تاني | G146: No QA found | H146: 0 | J146: N | K146: N
A147: 146 | B147: https://www.youtube.com/watch?v=5T7_-61Mk5M | C147: 5T7_-61Mk5M | D147: فيتامين د يسبب الفشل الكلوى وتحذيرات جديدة منه/ مايجب معرفته قبل الاستخدام | E147: د. كريم علي | F147: فِكر تاني | G147: Has QA - batch output | H147: 5 | I147: 18 | J147: N | K147: N | L147: N
...

Sheet Transcripts
A1: Video_Index | B1: Video_ID | C1: Video_Title | D1: Batches | E1: Chars | F1: Truncated_At_Cell_Limit | G1: Transcript
A2: 1 | B2: BE85vJQel4Q | C2: لماذا يتباطأ فقدان الوزن في الشتاء؟ الحقيقة التي لم يُخبِرك بها أحد | D2: 1 | E2: =LEN(G2) -> 6535 | F2: =IF(E2>=32700,"Y","N") -> N | G2: Greerings all, Winter has started, and with it, bulking season Every day I hear: “Doctor, I barely eat and still can’t lose weight.” “Doctor, I’m dieting but seeing no results.” Let’s get into the real reason, so we go through winter and come out lean not heavier than before. I’m Kareem Ali. Stay tund. Ready? Let’s go. Welcome. If weight loss were just about willpower, no one would ever fail. And if diet and exercise were enough, most people wouldn’t gain the weight back. And the belly wouldn’t come back hiding the belt again. So where’s the truth, doctor? weight problems aren’t just about food, and not just about movement. It’s a complete system. Again, holistic means holistic. Let’s break it down. The first reason weight loss fails whether it’s dieting, nutrition plans, or even going to the gym is the resistance of.... insulin. Exactly, you are right. Insulin is a storage hormone When insulin stays high, your body shuts down fat burning even if you’re barely eating. High insulin means: fat burning is blocked, and fat cannot be burned. What causes this? sugar, bread. refined carbs, and croissants. High stress, cortisol causes the same problem. Lack of sleep too. And here’s an important point. I recently read a message saying: even healthy food, if eaten late at night, can be stored as fat. You eat grilled steak, grilled chicken, broccoli and salad, at midnight. Your body may store it as fat, almost like you ate pizza. “So let’s just eat pizza instead.” I know you. No, that leads to disease, not just weight gain. Back to the point: timing matters. That’s why some people eat less, yet their weight doesn’t change, and their diet keeps failing. Second point, and this is very important, inflammation, guys. Keep it in your mind, no body loses fat while inflamed. Chronic inflammation puts your body in a constant defense mode. I’m at war. Store everything. No burning. No fat loss. Inflammation makes cells resist insulin and reduces the efficiency of the mitochondria. This increases insulin resistance. If we don’t reduce inflammation, we stay in a closed loop. Your body burns fat very slowly, but stores fat very fast. It doesn’t benefit from eating less or exercising more. It's real experience. The third reason is stress and anxiety. Cortisol has a great purpose. It saves you from a lion, for one hour. But when it’s always high, your body stays in danger mode. No absorption. No immunity. The body stops holding fat properly and starts breaking down muscle and even bone. Especially belly fat and fat around the waist. When these are high, it’s cortisol. That’s why I see so many people dieting and training for years. One, two, even three years, same people, same gym, same treadmill… And the same belly. I recognize them by their belly. This isn’t bullying. It’s the truth. The fourth reason is lack of sleep. Sleep matters. When sleep is poor, your hormones get messed up as hunger and fullness hormones. You crave food at night. “Bring anything from the fridge.” “Order dinner, anything.” At the same time, no fat burning, only fat storage. So losing sleep and eating at night is a disaster. Now you’ll ask: “What if I work night shifts?” Nurses. Doctors. Police officers. If you stay up for work, not hanging out, then don’t eat. Don’t kill two birds at once. Sleep and food. If you stayed up, just for WORK, skip eating. From sunset until you wake up, no food. If your shift ends at 8 a.m., eat at 8 a.m. When daylight starts. This point is very important. You can do everything right, but if your sleep is bad, your hormones are off, your cortisol is high, your insulin is resistant, or you have inflammation Your results will be very weak. Why do extreme diets fail? Because the body sees them as a direct threat. Not a health plan. A danger. You don't wants six-pack abs, you're harming yourself. Very low calories is a danger signal. Eating pizza one day then starving for two days is not healthy. Many people tell me: “Doctor, I want to fast 3 or 4 days to lose weight.” Intermittent fasting alone does NOT cause fat loss. When the scale drops after fasting, that’s water and glycogen, stored carbs in muscles and liver. Fat loss takes weeks… months… sometimes a year. Very low calories slow metabolism, raise cortisol, and make the body hold fat. The body feels that there’s an outside war. And then it chooses: Me… or the belly. After a while, weight plateaus. Then comes rebound, worse than before. After extreme dieting, you gain more weight than you started with. Now, you’re fat and have a belly. You get upset but that’s the absolute truth. I was like that before. At 36, I had a belly. They called me “Karim the Belly.” But now I’m better, and I want the same for you. So what’s the solution? The solution is to identify what’s really blocking fat loss. The solution is not food deprivation. And a very important point: When I say “no deprivation”, God says: “Eat and drink, but do not overconsume.” Not eating pizza is health. Quitting soda is health. Stopping sweets is health. The verse means: Eat real food. Rice, chicken, salads, fish, seeds, very important. So to sum it up: We now know the solution. You must find what’s blocking fat burning and it’s never deprivation, self-punishment, or going to war with your body. You’ll lose that war. The solution is managing the entire system. 1- Fix meal timing Eat two hours after waking up. Stop eating three hours before sleep. 2- Calm your nervous system Relax. No one takes anything with them. Do like Karim Ali, I’m relaxed. 3- Fix your sleep It’s the master key. Sleep well, eat when you’re awake. 4️- Activate your mitochondria Eat properly. Get minerals and vitamins. Move consistently. Build muscle mass. All of that boosts energy. 5️- Never shock your body Your body will take revenge. When the body feels safe, fat burning turns on, and weight drops steadily and sustainably. That’s today’s episode. Because the belly got big in this one Weight loss is not a battle. It’s balance. Understand your body, it responds. Listen to your body, you’ll reach your goal. Love your body, your body will love you back. Love Karim Ali, Karim Ali loves you And I love you all anyway. This episode is very important, especially in months when weight usually increases. Pay attention to the reasons. Fix your sleep. Fix your mitochondria. Follow us on Fekr Tany channel. “And my success is only by Allah. Upon Him I rely, and to Him I return.” Stay safe. And send this episode to all your friends with bellies Have a nice day.
A3: 2 | B3: X6oFPkaSVfk | C3: لماذا لا يهدأ جسدك؟ الجهاز العصبي أولًا” | D3: 1 | E3: =LEN(G3) -> 7090 | F3: =IF(E3>=32700,"Y","N") -> N | G3: Greetings all, A new year starts, and we hear this a lot: “Doctor, I did everything. I took supplements. I went to the gym. I did cardio. I fixed my diet. But I didn’t lose weight, and my mental state didn’t improve.” Today, I’ll tell you the secret no one has talked about before. A new episode. A new year. Real change this time. Stay with me after the break. Are you ready for a new year, a new body, and better health? I’m Karim Ali. See you after the break. Let’s go. Welcome, Many people come to me and say, “Doctor, I did everything you said. I fixed my diet and sleep. I took supplements. I exercised.” “But my mental state isn’t right. I can’t lose a single kilo.” Whether you’re a man or a woman, if you have these problems, then you have an issue with your nervous system. The nervous system is the manager of your life. If your nervous system is in survival mode, no matter what you do, even if you clean up your diet, you won’t build muscle or bone. No matter how much you train, lift weights, or eat protein. Your mood won’t improve, even if you take ashwagandha, spend time in nature, get married to the one you love, or become the manager of the company you dream of. The nervous system decides: happiness, weight loss, mental balance, or survival mode. “I’m not available for digestion, reproduction, or good mood. I’m under extreme stress.” So how do you know your nervous system is in survival mode? You eat little but don’t lose weight. You sleep a lot but don’t feel rested. You have no clear problems, yet you feel anxious. You crave sugar intensely. Right now, you’re saying, “Yes doctor, that’s exactly us.” Your nervous system is in survival mode. And that’s a serious stress state. So what’s the solution, doctor? Let’s get into it. So take these rules from me for the new year. First rule: slow your pace. Slow down. This is my life game changer The world is racing you. Reels are 30 seconds. Deals close in one day. Projects are due in a week. All of this creates stress on your nervous system more than you can imagine. Your body has its own rhythm. When you speed up the world outside, your body gets confused. What should you do? Slow down. Sit in calm places. Disconnect during the day. If the world is fast, control your inner rhythm. At first, this sounds difficult. But once you get used to it, you’ll find the world full of conflict, while you stay calm inside. So first: reduce your pace. Don’t rush with those who rush. Avoid fast content. Fast reels. Quick summaries. Stress on top of stress. Disconnect as much as you can. Get back and slow down your life. Second: focus on the inside Don’t tell me you’ll fix the world. Or fix your home. Or fix work. Or change your wife. None of that. The only thing you can control to escape stress and survival mode is inner peace. Take this from someone with experience. No one decides your calm except you. No one gives you permission to be happy except you. No one disconnects you from the outside world and focuses on inner peace except you. You are the decision-maker. When a problem happens, put your hand on your chest: “Indeed, in the remembrance of God do hearts find peace.” I entrust my affair to God. You wake up early. You go to work. You organize your diet. You do everything you can for provision. Then leave the results to God. Is man only judged by results? No. “And that man shall have nothing but what he strives for.” Your role is effort. Not results. Results are not yours. Leave them to God. Do what is required of you. Let go of what is not. Focus on what you’re responsible for. Don’t obsess over what’s not in your hands. You’re doing your part. Relax. And leave the matter to God. This brings calm and inner peace. I’ve said it many times in conferences and retreats: Anything that costs you your inner peace a job, a relationship, money is a loss. A loss. A loss. Third point: exit danger mode. Sit with yourself. Identify your anxiety. Use paper and pen. Write down what bothers you most. Work stress? Fix it, or change it. A relationship? Fix it, or leave it. Your body image? Fix it with nutrition, or change your lifestyle and live like the “Fekr Tany” family, their bodies transformed. Identify the problem. Why does your body feel under threat? Knowing the problem is half the solution. What worries you? Work? Home? Relationships? Money? Income? Inheritance? The country? The economy? Put your hand on the problem so you can treat it. Otherwise, you’ll fight an imaginary enemy, stay anxious, constantly stressed, and not know why. Anything that bothers you remove it, or change it. Take this message from me: The body does not heal and does not regenerate under threat. The body does not heal and does not regenerate under threat. Your body feels threatened even if you’re not aware of it at the conscious level. Here are quick notes to exit survival mode and return to peace mode. That’s where weight loss happens, hormones balance, and mental health improves. First: Protect your sleep as much as possible. Sleep in a dark room from 10 PM to 4 AM. There is no substitute. Second: Maintain muscle mass. During exercise, muscles release “hope proteins” that make you feel fresh, calm, less stressed, and full of ideas. Third: Maintain magnesium glycinate before sleep. And vitamin D at noon or early afternoon. These two calm the nervous system and put it in its best state. Want more support? You can add ashwagandha. I’ll link the episode. Also lemon balm tea. Do not take St. John’s Wort capsules before sleep. After magnesium, it calms the nervous system, helps deep sleep, and you wake up less depressed, less anxious, and more calm. One last thing. I said it before in the happiness episode. If you have a bathtub, that’s a blessing. Warm water with Epsom salt (available at pharmacies). Ask for “English salt,” not for drinking. Add magnesium chloride, lavender oil, and a little lemongrass Sit for 10–15 minutes. Warm water with essential oils. You can add 15–30 drops of lavender. It’s magical. You can drink lavender tea, or place the leaves in the room. Or add the oil to the bath. This calms your nervous system, helps relaxation, and brings inner peace. The message is: be grateful if you have a bathtub. It’s a supportive tool to relax your body, lose weight in the new year, be productive, and feel better mentally. Please, exit survival mode. Stop abusing your nervous system. If your nervous system is calm, your life is calm. If not, your state will be bad. Share it with anyone who feels tense or wants a relaxed life. As we live. Now it’s time for the question. This year, the questions won’t be easy. They require thinking. This is for the Fekr Tany family. Not for random answers. Those who answer correctly I’ll mention by name, thank personally, and send love. What destroys the nervous system the most? 1. No exercise 2. No sleep 3. Eating sugar 4. All of the above Thank you. Share the episode. May it be a happy year, full of fat loss and endless happiness. “And my success is only by God. Upon Him I rely, and to Him I return.” Stay safe. Peace.
A4: 3 | B4: V3SGExIImWM | C4: د.كريم علي | 5 أسرار لإعادة بناء العظام والتخلص من الهشاشة | D4: 1 | E4: =LEN(G4) -> 6744 | F4: =IF(E4>=32700,"Y","N") -> N | G4: Greetings all. Men and women in your 40s, 50s, 60s, 70s, and even 80s do bones weaken with age, or is the problem our habits? A very important episode for all ages 40 and above. Your bones are the foundation of your health. Stay until the end. There’s a lot of information today. I’m Kareem Ali. See you after the break. Ready for powerful bones and valuable insights? Let’s go. Welcome. Let’s remove the idea that osteoporosis happens because we age, because hormones decline, that it’s simply “the rule of age,” or that bones must weaken over time. This has no scientific basis. Osteoporosis means weak bones. Bones do not weaken because we age. Bones weaken when we stop using them, and when we stop eating properly. When the body doesn’t find what it needs to renew bones or make them stronger, bones start to weaken, and osteoporosis appears. This can happen even at the age of 20, but its effects show up late. And I’m talking about both men and women. So what’s really going on? We should stop talking about bones as if they were stone. Bones are living tissue. A living system that breathes, feeds, and has a life cycle until the day we die. A layer is broken down, and a new layer is built. Broken down, then rebuilt, this happens every day. There is something called osteoclasts, which break down bone, and osteoblasts, which build new bone. If bone breakdown is greater than bone building, this is called osteoporosis. People say: “You’ve gotten old, pray sitting down.” But if building is stronger than breakdown, our bones stay strong until the last day of our lives, and we live without osteoporosis. So what affects this balance? First: common mistakes that lead to weak bones or osteoporosis. Number one: fear of movement. “You’re old, pray sitting down.” “You’re old, don’t climb stairs.” “You’re old, park closer.” “You’re old, go to the mosque by car.” Comfort and fear of movement cause osteoporosis not the other way around. Number two: total dependence on calcium. “Doctor, I’m afraid of osteoporosis. What should I do?” Most people will say: “Take calcium.” Most calcium supplements are calcium carbonate. You know this wall behind me? That’s calcium carbonate. Limestone is calcium carbonate. This enters the body and can: Increase joint stiffness. Cause atherosclerosis or artery hardening. Cause kidney stones and gallstones. Reduce muscle flexibility. So instead of living healthier, you stiffen your body and increase clot risk because of calcium. But the most important thing of all is… Pause the episode and write in the comments below. Yes, Vitamin D. Well done. People who say Vitamin D is toxic, unimportant, or “just a hormone”… I’ve even seen nutritionists say: “Thank God you tell people to take more Vitamin D, because its deficiency is one of today’s disease causes.” Believe it or not, I’ve met specialists who claim Vitamin D causes diseases. The bottom line: When Vitamin D is corrected, calcium absorption increases by up to 200%. But with two conditions. First: When we take Vitamin D to help calcium enter the body, you just said calcium can cause clots. You must take it with Vitamin K2, preferably the MK-7 form. I’ll link its episode to explain all its secrets. Vitamin K2 works with Vitamin D to keep calcium in bones and teeth. Third requirement: Magnesium. God created calcium everywhere. Remember when we asked: “Where do we get calcium from?” Almost everything contains calcium. Broccoli, for example. Anything firm in plants like the fibers inside lettuce leaves broccoli, for example, all of this contains calcium. Salmon, nuts, and many other sources. God knew that excess calcium can cause stones and problems, so He created its counterbalance. Both can make the balance. What is it? Write it in the comments… Magnesium. Well done. When we take magnesium, we’re no longer afraid of calcium. It won’t rise excessively and will do its job properly. When you take K2, calcium goes to the bones. Now the dangerous mistake that causes osteoporosis: The saying: “I’m too old for the gym.” “The gym is for free people.” “I only go on weekends.” The main role of the gym is building muscle. If your body does not build muscle, it will get rid of bone. Take this as a physiological rule: No muscle building = bone loss. It’s a signal from God: If you want to build, you must strengthen the foundation. You don’t build Burj Khalifa like a two-floor villa. The foundation is different. Before building muscle in the gym, the body sends a signal to strengthen the bones. This is critical. We build muscle from above, bones strengthen from below, and building exceeds breakdown. Some things people often overlook, like boron, silica, and phosphorus. They’re very important for bone health. Second point: people who consume a lot of sugar are more likely to develop osteoporosis. Sugar increases inflammation and causes protein glycation. The proteins that build bone and muscle get damaged and oxidized. For those who eat a lot of sugar, sugar is one of the main causes of osteoporosis, along with the mistakes I just warned you about. Today’s conclusion: Osteoporosis, weak bones, or age-related bone loss are not simply due to aging. It’s not because you got older, and it’s not “normal” for women or men. It happens because we don’t eat well, don’t sleep well, don’t exercise, don’t care about minerals and vitamins that protect and build bones, and don’t go to the gym consistently to build muscle and bone mass. If we do all of that, there will be no bone aging or weakness. We can live with strong bones until the last day, because bone is a living tissue. If it’s used, it grows stronger. If it’s neglected, it shrinks and weakens. Then we blame aging. Studies show that people who fix their diet, minerals, and vitamins, and go to the gym, even in their sixties, can improve bone density. I see this in my private consultations. I’ll put the consultation link below the video. People tell me: “Doctor, it said that osteoporosis can’t improve.” “They say I need injections for life.” “No solution.” That’s not true. Bone density can increase. DEXA scans improve year after year if we eat right, sleep well, and exercise. That’s the end of today’s episode. And now, the question: What is the most important element for building strong bones? 1- Vitamin D 2- Calcium 3- Magnesium 4- All of the above Thank you for watching until the end. There’s a gift for those who reached this point. There is one type of calcium that does not cause clots and makes bones extremely strong. It’s called calcium fructoborate. Ask about it and look for it. You will see the result, and your bones will be extremely strong. “And my success is only by Allah. In Him I trust, and to Him I return.” Stay safe. Peace.
A5: 4 | B5: KnDhFZ6N020 | C5: فضيحة المكملات كيف تميز المكمل الحقيقي من المغشوش؟ | D5: 1 | E5: =LEN(G5) -> 7229 | F5: =IF(E5>=32700,"Y","N") -> N | G5: Greetings all. A major scandal for anyone using supplements. Especially those trying to stay young. Collagen, minerals, and vitamins. Training and taking sports supplements. Fake supplements have gone further than we ever imagined. This is a very important episode. Especially after two situations I faced. Anyone using supplements, send them this episode. Listen until the end. Follow the advice inside. So we can reach safety together. I truly feel responsible for you. I’m Karim Ali. Stay tuned after the break. Are you ready? Let’s get started. Welcome! Two situations happened. The first one: Someone messaged us privately. He said he took the supplements I mentioned. Then it developed a liver problem. I asked him why. He said, Doctor, the NMN you promote damaged my liver. I told him clearly, I never promoted NMN. I talked about it in episodes, but I never advertised it. He showed me a Facebook page. And YouTube videos. They claimed I recommend it. That was the first situation. The second thing, I read a study a few days ago About something called astaxanthin. We will dedicate a full episode to it. It is a completely different issue. 22 brands were tested, and lab analysis was done. Thirteen out of twenty-two did not contain astaxanthin at all. The remaining ones had another problem. The dose was one milligram, but the label said ten milligrams. Imagine that, thirteen out of twenty-two. I felt this was a message to sit with Fekr Tany audience, and talk openly about this issue. Let's get into the point. I truly believe in supplements. I was one of the first to say they can help cover nutritional gaps. But caution is essential. You must fully understand anything you put in your mouth. Make sure I actually talked about that product. Many ads appear everywhere, and I swear, on Egypt TV channels. Thirty minutes of talk just sales and promotions. Guys, I don’t even know where these supplements come from. When I recommend something, like the collagen I use, I have personally tried it. I show it on camera. And I share the link either in a video or on my verified Instagram. Anything outside that, I am not responsible for. Because they say Karim Ali recommends spirulina and I never did. Some NMN products, I never promoted at all. And many collagen brands, I have never even seen. Colon products too. I have never heard of them. It is not personal, and let me return to the point. Right now, there is a parallel supplement market. They use the same packaging. They copy the same label and the same written claims. I wish they used something harmless. But no, they add harmful substances, that damage the liver, affect hormones, drain energy, cause acne or bloating, and may weaken immunity. So no matter what, nothing goes into your mouth unless it comes from a trusted source. I never imagined I would have to say this. This is basic logic. For me, as Karim, I must know the company. Do you remember? I was one of the first to say there is something called third-party certification. I talked about this five years ago. An independent body not part of the company tests the product and confirms GMP compliance or ISO certification. Approved, licensed companies test the product itself. Confirming the dose, the ingredient, and nothing inside not listed outside. And nothing listed outside that is not inside. So the question is, how do we tell a real supplement from a fake one? First: If the price is much cheaper. That is the first red flag. Cheap supplements will destroy your health. The second sign is the printing. The text looks shaky. Poor print quality. The font is unclear. Parts of the text are faded. These are clear warning signs. The third sign is the capsule, its shape or type. You see the box says capsules, but inside are tablets. Or it says tablets, and inside are capsules. All of this means the product is suspicious. From an unknown source, and it can seriously harm you. The real problem is this. Health systems still lack full control over supplements. Another issue is ethics. With AI now, people use my image and voice. I saw an ad myself talking about something I never discussed before. It is clearly AI, even I messaged them "If you use AI, use proper paid tools." Not cheap ones that make my speech fake. They say things like, loses fifty kilos in a week. Guys, please be careful. I am serious. I must define my responsibility. I am only responsible for products I link myself in my videos, my Instagram reels, or my official Facebook page. The one with three million followers. These points are very important. In the end, please, if you doubt a product, message me directly on Instagram, Facebook, or YouTube. My team will reply. Do not use something just because you heard it is good. I have said this many times. People come to consultations. They say, I bought everything you mentioned. They have a full cabinet of supplements. More than a hundred. I ask them why. When I say ashwagandha, I ask, why do you need it? What is your problem? They say, because you said it is good. If I say something is good, does that mean everyone takes it? No. If someone needs to calm nerves, we think of rhodiola or ashwagandha. If someone has gut issues, we think of glutamine aloe vera, licorice, or marshmallow root. If someone has skin issues, we think of zinc. If someone wants to stay young, then collagen makes sense. You must always ask yourself, why do I need this? Not everything I mention should be bought. I have warned about this again and again. I will link the episode titled "Do not use any supplement until you watch it." I made it about four years ago. Warning. Multiple warnings. People with liver issues, kidney problems, blood thinning conditions, or psychiatric medications. They must watch this episode as it is extremely important for them And for anyone using supplements. The summary is simple that there is now a parallel market. Fake products are spreading, especially in countries without full regulatory control. Our worldwid audience, please be careful. Second point. Always choose a trusted source. A well-known company and the original supplier, so you can buy from the company’s branch or its official website. If I talk about a supplement, it must be through my Instagram links, my Facebook links, or in the YouTube episode description. Anything else, I am not responsible for. There are hundreds of products that harm people while using my name. God is sufficient for them. They will face consequences. Please be aware. We are responsible for what enters our mouths. Dr. Karim Ali will not stand next to everyone telling them what to take or what to avoid. This is a personal duty that everyone must do it. Now I am done. I said the truth that was weighing on me. If anyone had an experience or discovered a fake product, Write to us in the comments below. The upcoming episodes will provide more clarification to raise awareness about supplements, promote proper nutrition awareness, and encourage a natural health culture. One hundred percent. Share this episode with everyone using supplements. From vitamin C to peptides. See you in the next episode. "My success is only by God. I trust in Him and return to Him." Salam! Stay safe!
A6: 5 | B6: PHSTCRsiO4k | C6: د.كريم علي | 6 خطوات لتجديد شباب البشرة | D6: 1 | E6: =LEN(G6) -> 9285 | F6: =IF(E6>=32700,"Y","N") -> N | G6: The cause of wrinkles isn’t aging, it’s not getting old the cause of wrinkles isn’t what you think— it’s other things I’ll tell you today, and we can completely get rid of them. I’ll cover 6 main points, and in the seventh point, I’ll give you a complete plan on how to eat so that your skin goes back to looking young like Karim Ali in his prime This episode is very important. If you’re not subscribed, subscribe to the channel, grab a notebook and a pen, and get ready. it is very cold! Let’s go! Hello everyone, things that no dermatologist or filler-and-Botox enthusiast would ever tell you. can I restore my skin and make my face youthful again without Botox or fillers? Let’s talk about them one by one. Point 1: The main cause of wrinkles. The main cause of wrinkles is not age, not the years passing, not what we imagine, and not just sun exposure. The main cause is chronic inflammation in the body. If you don’t have chronic inflammation, you’re fine. These inflammations cause oxidation. What does oxidation mean? If you cut an apple in half and leave it for half an hour, what happens? That’s what happens to your face from inflammation and the excessive oxidation in your body from the foods we eat foods I’ve warned you about like milk, bread, and sugar. Anyway, the important thing is: oxidation is the number one cause. If you want to maintain your body and especially your skin, increase antioxidants in your diet and avoid foods that cause oxidation. Studies show that the skin can actually reverse age, collagen can rebuild, and skin thickness can return to youthful levels if we stop the things that cause wrinkles. Point 2: Something surprising People who sleep on their face, people how sleep on rough pillows, on their arms, or on one side every night the lines from this daily pressure are one of the biggest reasons for facial aging. They compress nerves and blood circulation, which leads to wrinkles over time. Reduced oxygen and blood flow mean collagen doesn’t form well, it will age of course collagen won't form well and cells won't regenerate efficiently. So, if you sleep on rough pillows or on your arms or on one side, please try sleeping on your back, get a medical pillow that supports your neck and face, and make sure the pillowcase is silk or very soft cotton. Sometimes we used to wake up with squares and triangles on our faces. Remember when you sleep on something? This is the second biggest reason that affects the face and causes wrinkles. Point 3: Nutrition. When we talk about nutrition, we have to mention Karim Ali. The most important thing is to feed your body collagen. Also, include polyphenols found in vegetables and fruits. I’ve talked a lot about polyphenols in my other videos— like asparagus, avocado, and berries. any episode about plants includes polyphenols Next, zinc is very important. Third, Vitamin C. So, make sure to include polyphenols— berries are especially great. eat berries a lot Eat berries, avocado, raw cacao for zinc eat guava, bell peppers, oranges, lemons for Vitamin C And of course, take your collagen. The collagen I use, I will put the link under the video. If these things enter your body daily, your body will renew itself. Do not say, “I am 30 years old and I’m going to get Botox.” the problem is you, my friend. Fourth point: A new culture but very beneficial: facial yoga exercises. I give a full course about beauty and facial yoga, with more than 15 yoga exercises for the face. I did an episode before about face Yoga You can search YouTube and follow trusted people. Do face yoga What is face yoga? Facial yoga? They’ll tell you it’s Buddhist stuff. Buddhist what? We’re activating the nerves What does face yoga do? Wrinkles appear because muscles are weak and sagging. If the muscle is tight and the nerve is strong, it stays tight. It won’t sag or wrinkle. It won’t look old or loose.” Facial yoga is like biceps and triceps exercises, but for the face. We have more than 33 muscles in the face. There are exercises for the eyes, mouth, chin, and neck. know about face yoga Three minutes every morning can completely change the face within 3 to 6 months. Facial yoga is scientifically proven to reverse aging and restore youth to the face. Fifth point. For those who follow me on Instagram and Snapchat, and if you don’t, you’re missing a lot. I got the infrared mask. It is scientifically proven. Scientifically, it increases collagen. It activates the energy cells. It improves blood circulation. It balances facial oils. And it enhances skin regeneration continuously. I use it for six minutes in the morning and six minutes at night. I’ve been using it for about a month and a half. I bought it from America. Don’t ask me where I got it from. Don’t say you can’t find it. If I find it in the UAE, I’ll tell you where. If I find it in Saudi Arabia, I’ll tell you. But I got mine from America. Any brand works these days. Just check the reviews online. Infrared can be used by women and men. It really works. But pay attention. Cut this episode. don't continue it without hearing these two words. If you don’t eat well, don’t sleep well, and don’t exercise, it’s useless. Don’t waste money on supplements. Don’t buy zinc. Don’t buy collagen. Don’t buy a mask. It’s useless. All these things work together. What’s the point of doing all this while staying up all night? Doing all this while smoking? Doing all this while drinking alcohol? Forget it. Or while eating sweets? Please remember this point.It needs everything working together The body is one integrated system. to reach the desired result. Back to the topic: infrared. If you don’t have it at home, there are infrared centers now. There are clinics offering infrared therapy. The mask is available everywhere now. Use an infrared facial mask. It is one of the proven methods. When mitochondria and energy cells improve, collagen improves right after. Sixth point: Cortisol and stress. Let me tell you something very clearly. Cortisol eats your body. Remember this well. It eats your bones, so you end up with osteoporosis. It eats your muscles, so you look thin but full of fat. It eats your collagen, so you age and your skin wrinkles. It eats your brain, so you lose focus and clarity. It eats your gut, so your digestion gets messed up. It eats your fertility, and everything starts falling apart. Cortisol is dangerous. And cortisol comes from inside us. Remember those old movies? “Son, why are you worried so early?” “Why do you look so old already?” It’s stress. We are not people of worry, thank God. We leave it to Allah. That’s how cortisol stays under control. I’ll put to you a full episode about stress, because it’s extremely important. If you want to live young, if you want your skin to renew constantly, to look fresh, beautiful, and glowing, and yes, God willing, we’ll even help you find a groom, you must lower cortisol by every method we talked about before. That’s it. Six points done. I’m here so we can take control of our faces again, and stop running to Botox and filler clinics. I’ll link the Botox and filler episode so you understand exactly what I mean. Seventh point Since you stayed with me till the end, and you’re good people, I won’t leave you hanging. Take this system. Follow these rules to protect your skin long-term. First: Wake up early. Wash your face with cold water. Never, ever use hot water on your face. Second: Every day, your food must include some of these Berries, Nuts, Avocado, Green tea, Pomegranate, Guava, Lemon, Orange, Salmon, Seeds. Pick two or three daily. Keep them in your system consistently. Next: Use skincare products with the least amount of chemicals possible. NO SLS No parabens. No sodium laureth sulfate. These should never touch your skin. One day, they cause aging, DNA damage, and even serious diseases like cancers. After that: Always use natural masks made from natural ingredients. If you want an episode about face masks, write in the comments “Doctor, we want an episode about masks.” We’ll leave medicine and start making masks and pumping our lips, apparently. Next: Exercise is extremely important. It improves blood circulation and boosts collagen production. Last point is SLEEP! And after that: Sugar? Milk? Bread? Fried food? Refined oils? Completely forbidden. I challenge you. Do what I said in this episode for three months. And tell me your skin didn’t change. That your collagen didn’t increase. That people don’t tell you: “Doctor, why do you look younger every time we see you?” Now you know all the secrets. Because I truly believe we can reverse aging, or at least stop it at a youthful stage, if we eat right, sleep right, and listen carefully to Karim Ali, God bless him The episode is over. Now it’s time for the question. Scientifically proven ways to renew skin and increase collagen: One: Facial yoga exercises. Two: Infrared therapy. Three: Food rich in zinc, vitamin C, and polyphenols. Four: All of the above. Thank you for watching until the end. If you’re not subscribed, subscribe now. Write your suggestions in the comments, about the next episodes and we’ll execute them immediately. in the end “And my success is only by Allah. Upon Him I rely, and to Him I return.” Peace be upon you, and may Allah protect you.
A7: 6 | B7: i7Ee3qB9rwM | C7: لماذا توقفتُ عن شرب الحليب؟ (قرار طبي عاجل) | D7: 1 | E7: =LEN(G7) -> 8096 | F7: =IF(E7>=32700,"Y","N") -> N | G7: Hello all, In a previous episode, I talked about milk. And the problems with fruit yogurt. And I explained two dangerous compounds in cow’s milk that cause many health issues. I’ll talk about them today, so stay tuned, because global reports everywhere now say cow’s milk is a silent killer. If you or your family still drink cow’s milk, watch this video, it will change your point of veiw I’m Kareem Ali. See you after the break, ready for a life without cow’s milk. Let’s go. Welcome Since the first day I spoke about cow’s milk, I said: it’s a silent killer. But camel milk is a miracle I’ll link the episode. The problem with cow’s milk: First, it contains lactose, and Arabs, and 80% of people, struggle to digest it It causes bloating, but that’s not today’s issue. There’s lactose-free milk, sure. The real problem in milk is: A1 casein. And if what I’m saying wasn’t true, the UAE, especially Sharjah, wouldn’t have started importing cows without A1 casein and replacing them, because of the disaster-level risks that lead to cancers and autoimmune issues. They shifted to A2 casein, which doesn’t cause the problems I’m talking about. It’s easier to digest, and many people’s health improved when they switched to A2. That proves we’re right and we’ll stay right in the Fekr Tany family. Let’s get into it. There are two compounds in casein one it triggers, and one it causes. The first and most dangerous is: BSM7 Beta-casomorphin-7. So what is it? It’s what comes out when A1 mil k or casein breaks down. It’s an opioid compound, yes, it goes to your opioid receptors. When you drink cow’s milk, you activate opioid receptors. Its biggest problem is that it crosses the blood–brain barrier. Allah created a protective shield around the brain. This shield works like customs. Not every food, vitamin, drink, or mineral can enter the brain. The brain is protected. But this thing crosses the blood–brain barrier. Meaning it reaches deep inside the brain. And this is the same issue with heavy metals. Aluminum and Mercury enter the brain. A huge disaster. But let’s go back to BCM-7. People who drink milk feel their mind isn’t clear. Focus isn’t great. Memory weakens over time. That’s what happens inside the brain. Now outside the brain: First, it causes fatigue in the body. It causes constipation. And let me tell you a real story that happened to me during my Family Medicine master’s exam in Romania. I got a pediatrics case. You know, family medicine covers kids and adults. So I started taking the history. The girl had chest allergy. They put her on antibiotics and oxygen for the wheezing. So naturally, with my system, I asked about her nutrition. In Romania, they rarely do that. I asked her mom: What does she eat? What does she drink? Any other issues? She told me the girl’s been constipated for three years. She eats very little but drinks two cups of milk every day. I said: “Wait… stop.” I wrote everything clearly in the history. Then I went to the exam board. They asked: “What’s the case?” I said: Chest allergy, but that’s not the real problem. They looked at me confused. I told them: It’s nutrition. She’s on cow’s milk and chronic constipation. Constipation causes sinus issues. And milk with constipation are major triggers for chest allergy in kids. This girl was hospitalized every month. Nebulizers. Almost chronic asthma. And no one fixed the cause: the cow’s milk in her diet. Five doctors were sitting there. They didn’t expect that from me. But when I said it, they all stopped and looked at me. I pointed out a cause that wasn’t in the sheet. Wasn’t in the treatment plan. But that was the real cause. And I got full marks in the pediatric oral exam. People with constipation won’t get better unless they stop cow’s milk and all cow-dairy products. Back to the point. BCM-7 doesn’t only cause brain fog and memory issues. It also creates body confusion,low energy, chronic constipation, and bloating. Lactose causes more bloating than BCM-7, but both of them stress the colon. There’s something else: they increase the body’s mucus. Anyone with sinus problems, constant mucus, clearing their throat, gets frequent colds, with a scratchy chest, and feels their lungs full of mucus, please stop dairy products. BCM-7 increases the body’s mucus. Another problem BCM-7 causes is leaky gut. It means the intestines start leaking proteins directly into the bloodstream. Leaky gut leads to three things. First: autoimmune diseases, like Hashimoto’s, multiple sclerosis, or whatever the body targets when it gets confused. A large amount of proteins cross the gut wall, the immune system panics, and starts attacking nerves, joints, or any tissue it mistakes for an enemy. Second: do you remember COVID? People were dying because of a cytokine storm a massive wave of inflammatory chemicals. BCM-7 doesn’t create a full “storm,” but it increases inflammatory cytokines all over the body. So your body stays inflamed because of BCM-7 and the daily milk habit. High inflammation combined with leaky gut pushes autoimmune issues again and again. The point is simple: BCM-7 from cow’s milk is a major problem. You won’t reach real health as long as you drink cow’s milk or your kids drink it. Replace it with goat cheese, coconut milk, cashew milk, or plant-based options. If you’re worried about calcium, you have sesame, seeds, broccoli, goat cheese, and sheep cheese, none of them contain A1 casein. And you can now choose A2 casein products. They don’t produce BCM-7 or the opioid compounds that come with it. Let’s move to the second problem: IGF-1, Insulin-like Growth Factor 1 that comes from milk. What is IGF-1? It’s normal for milk in a baby’s body. to raise growth factors. That’s the whole purpose of milk: to make infants grow. Not adults. So when we drink milk as adults, our bodies increase IGF-1. And this is scientifically proven, and it’s in textbooks and biochemistry references. When IGF-1 goes up, it’s linked to breast cancer, prostate cancer, and colon cancer. It also blocks apoptosis— the natural self-destruction of weak or cancerous cells. IGF-1 stops that process because it signals the body to grow, not to break down cells. There’s more. When IGF-1 speeds up growth and stops old cells from dying, the body enters a state of early aging. So high IGF-1 in adults pushes cellular aging faster. It also speeds up cell turnover, which leads to acne on the face. And because it increases size, it adds fat to the cheeks. That’s why people who drink milk often get puffy faces, three kilos of cheeks and they call it “healthy.” Healthy what? That’s face fat. That’s a belly on your face caused by IGF-1 from the milk you drink every day or the milk your wife drinks during pregnancy or otherwise. To sum it up: IGF-1 speeds up cell growth, is linked to several cancers, accelerates aging, causes acne, and increases face fat. And IGF-1 rises every time we drink cow’s milk. This is the conclusion of the episode. Recent research says: stop cow’s milk. And I’ll keep repeating, cow’s milk is a silent killer. Thank God we have many alternatives. there are other animals you can take milk from without stealing the baby’s food so we can drink it. The message is simple: stop milk if you want real health. Cow’s milk is harmful. anyone who stopped milk and saw improvement in any health issue, write it in the comments. Let the world know we are right. We gain nothing from telling people to avoid a food if it wasn’t harmful. I swear the wheat you eat today and the milk you drink today have nothing to do with what our ancestors consumed, not our great-grandparents, not in the Prophet’s time. They never saw what we are dealing with now. Today these products have become harmful to humanity. And I’ll keep saying it: cow’s milk is a silent killer. Whoever gets upset, gets upset. Enjoy the belly and the double chin, my friend. Write below what improved when you stopped milk. And share this episode no matter what. In the end: "success is only from God. On Him I rely, and to Him I return." Stay safe.
A8: 7 | B8: 9ZUNPpmGwTE | C8: السكر الخفي: كيف يؤثر على صحتك دون أن تشعر / د كريم علي | D8: 1 | E8: =LEN(G8) -> 11297 | F8: =IF(E8>=32700,"Y","N") -> N | G8: Greetings all! The most dangerous types of sugar are not the ones added to tea. The most dangerous sugars are the ones you eat and are told that this food is okay, normal, or even healthy, or recommended by many doctors. Five foods that raise your blood sugar without you even realizing it — a very important episode for everyone who is looking for a healthy weight and wants to prevent metabolic syndrome, high blood pressure, diabetes, and arteriosclerosis. I’m Dr. Karim Ali. Stay with me until the end of the episode; today’s information is new, and you will take a lot of notes — all about the secrets of sugar. Welcome! White sugar you know it’s a disaster, and many people are convinced of that. But there are foods and things we use every day that a lot of people consume, thinking it’s fine, and in the end, they develop insulin resistance. Millions of people are in the prediabetes stage. Prediabetes has no symptoms. The first symptoms appear only when you become diabetic, or have high blood pressure, arteriosclerosis, or fatty liver. But along the way, if you’re not careful, you won’t feel anything, and your body won’t give you any warning. there are five foods—or five things— that bring sugar into your body without you even realizing it. Stop them immediately to protect your health, prevent aging, and live in good health until your last day. Let’s start with the first one. Honestly, it’s not really a food—it’s juice. Fruit juices—even when they tell you it’s 100% natural juice. Many doctors even recommend drinking orange juice. For example, when you visit someone in the hospital, you bring them orange juice, or in the morning, you have a croissant Jam and orange juice are sugar bombs— whether it’s orange juice, apple juice, or any kind of fruit juice. God created fruits with high natural sugar but also lots of fiber. When you break down the fiber or remove it, what’s left is essentially pure sugar. which can cause fatty liver and lead you to diabetes without you even realizing it. So, avoid giving any fruit juice to yourself or your children —except for like strawberries and blueberries, of course, because their sugar content is low and they’re high in fiber. Otherwise, don’t drink juice at all. Always eat the whole fruit. I’ll keep repeating this: fruit is magical, full of benefits, fruit is magical, full of benefits, but only if consumed in small quantities. Number two: white bread —and you don't know what white bread is— along with French bread, croissants, pastries, and biscuits. Even the traditional Egyptian ‘whole wheat’ bread, medical bread, and whole-grain bread— all types of bread raise blood sugar. All bread has a high glycemic index and triggers a strong insulin response. All kinds of bread will continue to affect you because of the gliadin and gluten they contain. They can cause bloating, leaky gut, endocrine problems, obesity, fatty liver, facial puffiness, and allergic diseases. So, for people who say, 'I eat whole wheat bread, diet bread, brown bread, bran bread '—bread is bread, all types of bread, in my opinion, increase the glycemic index and are one of the main causes of modern problems like obesity and fatty liver and colon problems Please cut out bread and switch to almond flour, coconut flour, flour made from rice, lentils, or whole seeds like flax, chia, and sesame. These are the things you can use instead of bread because they don’t contain wheat flour, gluten , or gliadin, which can damage your digestive system and weaken your immune system. Avoid bread altogether, even diet bread. Number three: yogurt with fruit— and this is actually two disasters, not just one. People think fruit yogurt is a healthy food, high in protein —but whose protein? It’s misleading. As for milk, that’s a whole other topic. There are new papers, new studies proving what I’m saying casein in cow’s milk produces a substance called BCM-7. I could make a separate episode about it. This substance can increase cancer risk, cause leaky gut, increase sensitivities, and affect mucus. If you want, I can do a full episode about the substance in cow’s milk. Id you want a such an episode, write to me in the comments and we will do an special espisode for this substance. By the way, cow’s milk also raises IGF —insulin-like growth factor—which can increase cancer risk because of casein and lactose. If you want a full episode on this, let me know in the comments "we can go deeper into the harmful compounds in milk, because it’s a serious issue". Back to fruit yogurt: the fruit might be unnatural, but the yogurt isn’t purely beneficial and doesn't contains casein it contanis lactose. The fruits in these yogurts are basically jam, not real fruit. Even when they say 'natural pieces,' okay, natural pieces—but then you find 14 grams of sugar. If it’s truly natural pieces, where is all that sugar coming from? The truth is, they add jam and sweeten it heavily. Even strawberries—they say ‘strawberries are healthy’ Even berries yogurt, which some of you say is healthy, is basically sugar it is like sugar jam The bottom line: if you want to eat yogurt, eat sheep or goat yogurt that is natural, from a natural source, with no additives, no fruit, no cornflakes, no whole grains—just plain natural yogurt. People who eat fruit yogurt thinking it’s healthy are actually consuming a food loaded with sugar and harmful substances that damage the gut and increase cancer cell growth. Write in the comments if you want an episode about the two harmful substances in cow’s milk. The fourth food: ready-made sauces and condiments If you just check the can of ketchup or any ready-made sauce, you’ll be surprised at how much sugar, refined oils, and preservatives are in it. God created tomatoes to last two or three days, yet they can last three years in a can because of all these additives! So please, replace all ready-made sauces with homemade ones. Not difficult, a few tomatoes, some olive oil or a piece of butter, and you can make perfect homemade ketchup. Same with mayonnaise—make it at home or use natural ingredients provided by God. Salt, pepper, cumin, sumac, bay leaves, basil, rosemary, turmeric… all these spices are available, but some people rely on sauces to enhance flavor. add extra salt, dressing, cloves, or anything else, people mistakenly think that taking ready-made sauces or condiments is healthy, but they are actually loaded with sugar and preservatives. These sauces will not bring any benefit; they contribute to insulin resistance, fatty liver, and prediabetes. Make your sauces at home, use natural spices, and stay away from processed condiments. Number five: soft drinks. I still see poor children drinking soda. I still see children in fast-food restaurants drinking soda. This is a crime like if I'm giving a 10-year old child cigarette to smoke. Let’s focus on adults. How long are we going to keep consuming things that increase insulin resistance, ause fatty liver, increase belly fat, and hit your testosterone right at the core? The same goes for women if fatty liver increases and belly fat rises, strogen will increase, leading to polycystic ovary syndrome, irregular periods, and hormonal problems—all because of drinking too much soda. So please, replace soda—all kinds of soda—with… natural juices? No, doctor, you told us not to. Yes, that’s correct. Many people drink green juices without fiber, or water —the water from which God made all living things. People don’t drink water anymore; they drink soda. What can I say?" So the fifth thing that causes diabetes and prediabetes —and people don’t even notice—is this: ‘Doctor, it’s just a small cup, eat and drink but don’t overdo it.’ I will not respond to you. This is how we were taught, and in our Islamic principle: what intoxicates in large amounts is forbidden in small amounts. Why? Why? Because God closes the door for your own safety. And from another perspective, out of fear for you, I am also closing the door to protect you. Sugar ends badly—stop it now Bread ends badly—stop it now Cow’s milk—stop it from the beginning. Sauces—stop them when they start getting out of hand. Soda—stop it before it becomes a habit. Use your mind and you’ll know what saves you. Before I finish, I want to mention something called the glycemic index. The glycemic index works like this: when we eat something, the body needs the sugar level to rise, and then it needs insulin to bring it back to normal. The higher the sugar rises, the more insulin is needed. This is a serious problem, because it exhausts your insulin, causes insulin resistance, and over time stresses the pancreas. The glycemic index affects many foods, including the ones we mentioned today soda, sauces, and even foods with low calories, like popcorn. Yes.. which is popcorn, ok its calories are very low, but its glycemic index is high, That’s why popcorn isn’t included in the keto diet. You might ask: “Doctor, why not? It’s low in calories and high in fiber. Yes, it is, but it raises insulin Diabetics shouldn’t eat a lot of popcorn. People with fatty liver shouldn’t eat a lot of popcorn. There are many foods like this their calories seem low, but the glycemic index is very high. I’ve seen the lab results of people who followed the right diet for three months You will never believe it! Some had HbA1c of 7–8, and it went down to 4.5–5. Fatty liver completely improved. Some had abdominal fat disappear, and women with polycystic ovary syndrome (PCOS) improved —all this just by cutting sugar and hidden sugar. I see cases like this every day. You wouldn’t believe how much people’s lives change when they just pay attention to sugar, both visible and hidden, like the foods I mentioned today. So please, sugar is a killer —stop it, and be careful about what you eat, even if it’s labeled “healthy” or “good for you.” For example, protein bars— they contain abnormally high amounts of sugar. And don’t be fooled by labels like “No Added Sugar” that just means no sugar was added Even natural juice can have a lot of sugar, even if it’s “No Added Sugar.” its natural sugar is high So you might ask, “Doctor, what about Zero Sugar or Sugar-Free?” It doesn’t mean it’s free of sugar, whether natural or artificial, from you or anyone else. Be careful—don’t be fooled when they say “No Added Sugar.” That just means no sugar was added, but the product can still be naturally high in sugar. For example: Grapes labeled “No Added Sugar” Dates, no added sugar, right? but if you eat 20 dates, it could lead to fatty liver. Honey labeled “No Added Sugar” — natural, pure but if you eat 3–4 tablespoons, your sugar level will rise because it has a high glycemic index. So be careful, and watch out for hidden sugar, because it’s the reason many people develop obesity without knowing the cause as they eat orange juice and fruit yogurt the products is labeled for athelets, doctor This is misleading! The takeaway: Be mindful of sugar, whether visible or hidden. Write in the comments which of these five items you’ve used and were surprised to learn today that they aren’t healthy and contain a lot of sugar. Finally, let’s cover and protect each other, I won’t reveal anyone’s names publicly. "My success is only by God’s will. I rely on Him." Stay safe, bye.
